Workbook
Name RoleList: Lists!$A$4:$A$19
Name LevelList: Lists!$B$4:$B$7
Name PhaseList: Lists!$C$4:$C$8
Name StatusList: Lists!$D$4:$D$7
Name ConfList: Lists!$E$4:$E$6
Name TypeList: Lists!$F$4:$F$16

Sheet Summary
A1: EdVidura Question Bank v1.0 FINAL — what a new joiner must be able to answer
A2: 2639 questions · 44 products and frameworks · 16 roles · 4 levels · generated per the Onboarding Question-Bank Engineering Prompt v1 (Loops 1–10), extended with the coverage cross-check tranche. See Version & Change Log.
A3: Four uses, one dataset: onboarding paths · interview bank · SME interview guide · documentation backlog (the Unanswerable Register).
A4: YELLOW columns on the Question Bank sheet are yours to fill: AskedTo, AnsweredBy, AnswerDate, DocLink, Confidence.
A6: Headline
A7: Total questions | B7: 2639
A8: Products & frameworks covered | B8: 44
A9: Roles covered | B9: 16
A10: Questions with NO answer anywhere today | B10: 1279
A11: …as a share of the bank | B11: 48%
A12: Second-order / emergent questions | B12: 454
A13: Day 1 + Week 1 questions (the onboarding core) | B13: 746
A16: By role (live counts)
A17: Code | B17: Role | C17: Total | D17: L1 | E17: L2 | F17: L3 | G17: L4 | H17: Day1+Wk1 | I17: No answer | J17: Answered so far
A18: FE | B18: Front-End Developer | C18: =COUNTIF('Question Bank'!$D:$D,$A18) | D18: =COUNTIFS('Question Bank'!$D:$D,$A18,'Question Bank'!$F:$F,"L1 Junior") | E18: =COUNTIFS('Question Bank'!$D:$D,$A18,'Question Bank'!$F:$F,"L2 Mid") | F18: =COUNTIFS('Question Bank'!$D:$D,$A18,'Question Bank'!$F:$F,"L3 Senior") | G18: =COUNTIFS('Question Bank'!$D:$D,$A18,'Question Bank'!$F:$F,"L4 Architect") | H18: =COUNTIFS('Question Bank'!$D:$D,$A18,'Question Bank'!$G:$G,"Day 1")+COUNTIFS('Question Bank'!$D:$D,$A18,'Question Bank'!$G:$G,"Week 1") | I18: =COUNTIFS('Question Bank'!$D:$D,$A18,'Question Bank'!$L:$L,"Undocumented — no answer exists") | J18: =COUNTIFS('Question Bank'!$D:$D,$A18,'Question Bank'!$R:$R,"<>")
A19: BE | B19: Back-End Developer | C19: =COUNTIF('Question Bank'!$D:$D,$A19) | D19: =COUNTIFS('Question Bank'!$D:$D,$A19,'Question Bank'!$F:$F,"L1 Junior") | E19: =COUNTIFS('Question Bank'!$D:$D,$A19,'Question Bank'!$F:$F,"L2 Mid") | F19: =COUNTIFS('Question Bank'!$D:$D,$A19,'Question Bank'!$F:$F,"L3 Senior") | G19: =COUNTIFS('Question Bank'!$D:$D,$A19,'Question Bank'!$F:$F,"L4 Architect") | H19: =COUNTIFS('Question Bank'!$D:$D,$A19,'Question Bank'!$G:$G,"Day 1")+COUNTIFS('Question Bank'!$D:$D,$A19,'Question Bank'!$G:$G,"Week 1") | I19: =COUNTIFS('Question Bank'!$D:$D,$A19,'Question Bank'!$L:$L,"Undocumented — no answer exists") | J19: =COUNTIFS('Question Bank'!$D:$D,$A19,'Question Bank'!$R:$R,"<>")
A20: DE | B20: Data Engineer | C20: =COUNTIF('Question Bank'!$D:$D,$A20) | D20: =COUNTIFS('Question Bank'!$D:$D,$A20,'Question Bank'!$F:$F,"L1 Junior") | E20: =COUNTIFS('Question Bank'!$D:$D,$A20,'Question Bank'!$F:$F,"L2 Mid") | F20: =COUNTIFS('Question Bank'!$D:$D,$A20,'Question Bank'!$F:$F,"L3 Senior") | G20: =COUNTIFS('Question Bank'!$D:$D,$A20,'Question Bank'!$F:$F,"L4 Architect") | H20: =COUNTIFS('Question Bank'!$D:$D,$A20,'Question Bank'!$G:$G,"Day 1")+COUNTIFS('Question Bank'!$D:$D,$A20,'Question Bank'!$G:$G,"Week 1") | I20: =COUNTIFS('Question Bank'!$D:$D,$A20,'Question Bank'!$L:$L,"Undocumented — no answer exists") | J20: =COUNTIFS('Question Bank'!$D:$D,$A20,'Question Bank'!$R:$R,"<>")
A21: BI | B21: BI / Analytics Developer (Metabase) | C21: =COUNTIF('Question Bank'!$D:$D,$A21) | D21: =COUNTIFS('Question Bank'!$D:$D,$A21,'Question Bank'!$F:$F,"L1 Junior") | E21: =COUNTIFS('Question Bank'!$D:$D,$A21,'Question Bank'!$F:$F,"L2 Mid") | F21: =COUNTIFS('Question Bank'!$D:$D,$A21,'Question Bank'!$F:$F,"L3 Senior") | G21: =COUNTIFS('Question Bank'!$D:$D,$A21,'Question Bank'!$F:$F,"L4 Architect") | H21: =COUNTIFS('Question Bank'!$D:$D,$A21,'Question Bank'!$G:$G,"Day 1")+COUNTIFS('Question Bank'!$D:$D,$A21,'Question Bank'!$G:$G,"Week 1") | I21: =COUNTIFS('Question Bank'!$D:$D,$A21,'Question Bank'!$L:$L,"Undocumented — no answer exists") | J21: =COUNTIFS('Question Bank'!$D:$D,$A21,'Question Bank'!$R:$R,"<>")
A22: DA | B22: Data Analyst | C22: =COUNTIF('Question Bank'!$D:$D,$A22) | D22: =COUNTIFS('Question Bank'!$D:$D,$A22,'Question Bank'!$F:$F,"L1 Junior") | E22: =COUNTIFS('Question Bank'!$D:$D,$A22,'Question Bank'!$F:$F,"L2 Mid") | F22: =COUNTIFS('Question Bank'!$D:$D,$A22,'Question Bank'!$F:$F,"L3 Senior") | G22: =COUNTIFS('Question Bank'!$D:$D,$A22,'Question Bank'!$F:$F,"L4 Architect") | H22: =COUNTIFS('Question Bank'!$D:$D,$A22,'Question Bank'!$G:$G,"Day 1")+COUNTIFS('Question Bank'!$D:$D,$A22,'Question Bank'!$G:$G,"Week 1") | I22: =COUNTIFS('Question Bank'!$D:$D,$A22,'Question Bank'!$L:$L,"Undocumented — no answer exists") | J22: =COUNTIFS('Question Bank'!$D:$D,$A22,'Question Bank'!$R:$R,"<>")
A23: AI | B23: AI/ML Engineer | C23: =COUNTIF('Question Bank'!$D:$D,$A23) | D23: =COUNTIFS('Question Bank'!$D:$D,$A23,'Question Bank'!$F:$F,"L1 Junior") | E23: =COUNTIFS('Question Bank'!$D:$D,$A23,'Question Bank'!$F:$F,"L2 Mid") | F23: =COUNTIFS('Question Bank'!$D:$D,$A23,'Question Bank'!$F:$F,"L3 Senior") | G23: =COUNTIFS('Question Bank'!$D:$D,$A23,'Question Bank'!$F:$F,"L4 Architect") | H23: =COUNTIFS('Question Bank'!$D:$D,$A23,'Question Bank'!$G:$G,"Day 1")+COUNTIFS('Question Bank'!$D:$D,$A23,'Question Bank'!$G:$G,"Week 1") | I23: =COUNTIFS('Question Bank'!$D:$D,$A23,'Question Bank'!$L:$L,"Undocumented — no answer exists") | J23: =COUNTIFS('Question Bank'!$D:$D,$A23,'Question Bank'!$R:$R,"<>")
A24: AIG | B24: AI Generalist | C24: =COUNTIF('Question Bank'!$D:$D,$A24) | D24: =COUNTIFS('Question Bank'!$D:$D,$A24,'Question Bank'!$F:$F,"L1 Junior") | E24: =COUNTIFS('Question Bank'!$D:$D,$A24,'Question Bank'!$F:$F,"L2 Mid") | F24: =COUNTIFS('Question Bank'!$D:$D,$A24,'Question Bank'!$F:$F,"L3 Senior") | G24: =COUNTIFS('Question Bank'!$D:$D,$A24,'Question Bank'!$F:$F,"L4 Architect") | H24: =COUNTIFS('Question Bank'!$D:$D,$A24,'Question Bank'!$G:$G,"Day 1")+COUNTIFS('Question Bank'!$D:$D,$A24,'Question Bank'!$G:$G,"Week 1") | I24: =COUNTIFS('Question Bank'!$D:$D,$A24,'Question Bank'!$L:$L,"Undocumented — no answer exists") | J24: =COUNTIFS('Question Bank'!$D:$D,$A24,'Question Bank'!$R:$R,"<>")
A25: MXR | B25: Mobile & XR Developer | C25: =COUNTIF('Question Bank'!$D:$D,$A25) | D25: =COUNTIFS('Question Bank'!$D:$D,$A25,'Question Bank'!$F:$F,"L1 Junior") | E25: =COUNTIFS('Question Bank'!$D:$D,$A25,'Question Bank'!$F:$F,"L2 Mid") | F25: =COUNTIFS('Question Bank'!$D:$D,$A25,'Question Bank'!$F:$F,"L3 Senior") | G25: =COUNTIFS('Question Bank'!$D:$D,$A25,'Question Bank'!$F:$F,"L4 Architect") | H25: =COUNTIFS('Question Bank'!$D:$D,$A25,'Question Bank'!$G:$G,"Day 1")+COUNTIFS('Question Bank'!$D:$D,$A25,'Question Bank'!$G:$G,"Week 1") | I25: =COUNTIFS('Question Bank'!$D:$D,$A25,'Question Bank'!$L:$L,"Undocumented — no answer exists") | J25: =COUNTIFS('Question Bank'!$D:$D,$A25,'Question Bank'!$R:$R,"<>")
A26: DEVOPS | B26: DevSecOps / Platform Engineer | C26: =COUNTIF('Question Bank'!$D:$D,$A26) | D26: =COUNTIFS('Question Bank'!$D:$D,$A26,'Question Bank'!$F:$F,"L1 Junior") | E26: =COUNTIFS('Question Bank'!$D:$D,$A26,'Question Bank'!$F:$F,"L2 Mid") | F26: =COUNTIFS('Question Bank'!$D:$D,$A26,'Question Bank'!$F:$F,"L3 Senior") | G26: =COUNTIFS('Question Bank'!$D:$D,$A26,'Question Bank'!$F:$F,"L4 Architect") | H26: =COUNTIFS('Question Bank'!$D:$D,$A26,'Question Bank'!$G:$G,"Day 1")+COUNTIFS('Question Bank'!$D:$D,$A26,'Question Bank'!$G:$G,"Week 1") | I26: =COUNTIFS('Question Bank'!$D:$D,$A26,'Question Bank'!$L:$L,"Undocumented — no answer exists") | J26: =COUNTIFS('Question Bank'!$D:$D,$A26,'Question Bank'!$R:$R,"<>")
A27: SEC | B27: Security Engineer | C27: =COUNTIF('Question Bank'!$D:$D,$A27) | D27: =COUNTIFS('Question Bank'!$D:$D,$A27,'Question Bank'!$F:$F,"L1 Junior") | E27: =COUNTIFS('Question Bank'!$D:$D,$A27,'Question Bank'!$F:$F,"L2 Mid") | F27: =COUNTIFS('Question Bank'!$D:$D,$A27,'Question Bank'!$F:$F,"L3 Senior") | G27: =COUNTIFS('Question Bank'!$D:$D,$A27,'Question Bank'!$F:$F,"L4 Architect") | H27: =COUNTIFS('Question Bank'!$D:$D,$A27,'Question Bank'!$G:$G,"Day 1")+COUNTIFS('Question Bank'!$D:$D,$A27,'Question Bank'!$G:$G,"Week 1") | I27: =COUNTIFS('Question Bank'!$D:$D,$A27,'Question Bank'!$L:$L,"Undocumented — no answer exists") | J27: =COUNTIFS('Question Bank'!$D:$D,$A27,'Question Bank'!$R:$R,"<>")
A28: QA | B28: QA / Test Engineer | C28: =COUNTIF('Question Bank'!$D:$D,$A28) | D28: =COUNTIFS('Question Bank'!$D:$D,$A28,'Question Bank'!$F:$F,"L1 Junior") | E28: =COUNTIFS('Question Bank'!$D:$D,$A28,'Question Bank'!$F:$F,"L2 Mid") | F28: =COUNTIFS('Question Bank'!$D:$D,$A28,'Question Bank'!$F:$F,"L3 Senior") | G28: =COUNTIFS('Question Bank'!$D:$D,$A28,'Question Bank'!$F:$F,"L4 Architect") | H28: =COUNTIFS('Question Bank'!$D:$D,$A28,'Question Bank'!$G:$G,"Day 1")+COUNTIFS('Question Bank'!$D:$D,$A28,'Question Bank'!$G:$G,"Week 1") | I28: =COUNTIFS('Question Bank'!$D:$D,$A28,'Question Bank'!$L:$L,"Undocumented — no answer exists") | J28: =COUNTIFS('Question Bank'!$D:$D,$A28,'Question Bank'!$R:$R,"<>")
A29: SDET | B29: Test Architect / SDET | C29: =COUNTIF('Question Bank'!$D:$D,$A29) | D29: =COUNTIFS('Question Bank'!$D:$D,$A29,'Question Bank'!$F:$F,"L1 Junior") | E29: =COUNTIFS('Question Bank'!$D:$D,$A29,'Question Bank'!$F:$F,"L2 Mid") | F29: =COUNTIFS('Question Bank'!$D:$D,$A29,'Question Bank'!$F:$F,"L3 Senior") | G29: =COUNTIFS('Question Bank'!$D:$D,$A29,'Question Bank'!$F:$F,"L4 Architect") | H29: =COUNTIFS('Question Bank'!$D:$D,$A29,'Question Bank'!$G:$G,"Day 1")+COUNTIFS('Question Bank'!$D:$D,$A29,'Question Bank'!$G:$G,"Week 1") | I29: =COUNTIFS('Question Bank'!$D:$D,$A29,'Question Bank'!$L:$L,"Undocumented — no answer exists") | J29: =COUNTIFS('Question Bank'!$D:$D,$A29,'Question Bank'!$R:$R,"<>")
... A33: SUP | B33: Support & Service Engineer | C33: =COUNTIF('Question Bank'!$D:$D,$A33) | D33: =COUNTIFS('Question Bank'!$D:$D,$A33,'Question Bank'!$F:$F,"L1 Junior") | E33: =COUNTIFS('Question Bank'!$D:$D,$A33,'Question Bank'!$F:$F,"L2 Mid") | F33: =COUNTIFS('Question Bank'!$D:$D,$A33,'Question Bank'!$F:$F,"L3 Senior") | G33: =COUNTIFS('Question Bank'!$D:$D,$A33,'Question Bank'!$F:$F,"L4 Architect") | H33: =COUNTIFS('Question Bank'!$D:$D,$A33,'Question Bank'!$G:$G,"Day 1")+COUNTIFS('Question Bank'!$D:$D,$A33,'Question Bank'!$G:$G,"Week 1") | I33: =COUNTIFS('Question Bank'!$D:$D,$A33,'Question Bank'!$L:$L,"Undocumented — no answer exists") | J33: =COUNTIFS('Question Bank'!$D:$D,$A33,'Question Bank'!$R:$R,"<>")
B34: TOTAL | C34: =SUM(C18:C33) | D34: =SUM(D18:D33) | E34: =SUM(E18:E33) | F34: =SUM(F18:F33) | G34: =SUM(G18:G33) | H34: =SUM(H18:H33) | I34: =SUM(I18:I33) | J34: =SUM(J18:J33)
A36: By onboarding phase and answer status
A37: Phase | B37: Questions | C37: No answer today
A38: Day 1 | B38: =COUNTIF('Question Bank'!$G:$G,$A38) | C38: =COUNTIFS('Question Bank'!$G:$G,$A38,'Question Bank'!$L:$L,"Undocumented — no answer exists")
A39: Week 1 | B39: =COUNTIF('Question Bank'!$G:$G,$A39) | C39: =COUNTIFS('Question Bank'!$G:$G,$A39,'Question Bank'!$L:$L,"Undocumented — no answer exists")
A40: Month 1 | B40: =COUNTIF('Question Bank'!$G:$G,$A40) | C40: =COUNTIFS('Question Bank'!$G:$G,$A40,'Question Bank'!$L:$L,"Undocumented — no answer exists")
A41: Quarter 1 | B41: =COUNTIF('Question Bank'!$G:$G,$A41) | C41: =COUNTIFS('Question Bank'!$G:$G,$A41,'Question Bank'!$L:$L,"Undocumented — no answer exists")
A42: Ongoing | B42: =COUNTIF('Question Bank'!$G:$G,$A42) | C42: =COUNTIFS('Question Bank'!$G:$G,$A42,'Question Bank'!$L:$L,"Undocumented — no answer exists")
A44: Answer status | B44: Questions | C44: Share
A45: Undocumented — no answer exists | B45: 1262 | C45: =B45/2639
A46: Partially documented | B46: 1231 | C46: =B46/2639
A47: Documented | B47: 129 | C47: =B47/2639
A48: Tribal knowledge only | B48: 17 | C48: =B48/2639

Sheet Question Bank
A1: QID | B1: ProductID | C1: Component | D1: Role | E1: RoleName | F1: Level | G1: OnboardingPhase | H1: QuestionType | I1: Question | J1: WhyItMatters | K1: AnswerSource | L1: AnswerStatus | M1: BlocksWork | N1: ParentQID | O1: FollowUps | P1: SampleAnswerShape | Q1: AskedTo | R1: AnsweredBy | S1: AnswerDate | T1: DocLink | U1: Confidence
A2: QTU0088 | B2: D01 | C2: AI SME Chatbot (learner) | D2: AIG | E2: AI Generalist | F2: L4 Architect | G2: Quarter 1 | H2: Emergent | I2: Should the learner chatbot cite a source the learner is not cleared to open? | J2: Citing an inaccessible source either discloses the existence of restricted material or leaves the learner with an unverifiable claim, and both undermine the grounding promise the product is sold on. | K2: None - undocumented; Security Architect; Product Manager | L2: Undocumented — no answer exists | M2: AIA-07.x citation and grounding requirements | N2: QTU0087 | O2: Should retrieval exclude restricted material entirely? / What does the learner see instead of the citation? / Does this differ per tenant? | P2: Chooses between excluding the source from retrieval and citing without access, and justifies it
A3: QST0107 | B3: D01 | C3: AI SME Chatbot (learner) | D3: SUP | E3: Support & Service Engineer | F3: L1 Junior | G3: Day 1 | H3: Orientation | I3: Which of the three chatbots is a learner most likely to mean when they say the assistant gave a wrong answer? | J3: Routing a chatbot ticket to the wrong owning team costs a day and the learner keeps receiving the wrong answer meanwhile. | K3: Product Plan v2 (M15, M23, M26) | L3: Partially documented | M3: E09 ticket routing by module | N3: - | O3: How do I tell them apart from a screenshot? / Do they share an index? / Who owns each? | P3: Distinguishes the three by audience and names the owning team for each
A4: QST0124 | B4: D01 | C4: AI SME Chatbot (learner) | D4: SUP | E4: Support & Service Engineer | F4: L2 Mid | G4: Month 1 | H4: Mechanism | I4: How do you confirm that a chatbot answer was drawn from a superseded document rather than being simply wrong? | J4: Misdiagnosing a retrieval-currency failure as a model quality failure sends the fix to the wrong team entirely. | K4: Architecture Review Report §D-M25 (Scenario 4); §I.7 | L4: Partially documented | M4: D01 citation and index version recording | N4: - | O4: Are citations shown? / Is the index version recorded on the answer? / Can support replay the query? | P4: Uses the recorded citation and index version to identify the source revision
A5: QST0125 | B5: D01 | C5: AI SME Chatbot (learner) | D5: SUP | E5: Support & Service Engineer | F5: L2 Mid | G5: Month 1 | H5: Failure mode | I5: What do you do when the assistant refuses a question the customer considers entirely legitimate? | J5: Over-refusal looks like a broken product to the customer and there is no defined route to distinguish it from correct caution. | K5: Architecture Review Report §I.1; Master Checklist v3 (TST-11.1.04) | L5: Partially documented | M5: D01 refusal calibration and false-refusal budget | N5: - | O5: Is there a false-refusal budget? / Where is the probe set? / Who tunes it? | P5: Distinguishes correct refusal from over-refusal using the evaluation set
A6: QST0142 | B6: D01 | C6: AI SME Chatbot (learner) | D6: SUP | E6: Support & Service Engineer | F6: L2 Mid | G6: Month 1 | H6: Emergent | I6: If an answer records its index version, how does support find out which document revision that index was built from? | J6: Without the revision link the citation proves nothing and the supersession investigation stalls at the first step. | K6: Architecture Review Report §I.7 item 5 | L6: Undocumented — no answer exists | M6: D10 content lineage record | N6: QST0124 | O6: Is lineage queryable? / Is it per site? / Who maintains it? | P6: Traces index version to source revision through a lineage record
A7: QST0155 | B7: D01 | C7: AI SME Chatbot (learner) | D7: SUP | E7: Support & Service Engineer | F7: L3 Senior | G7: Quarter 1 | H7: Ethics/Validity | I7: When the assistant cites a superseded procedure at a site that has not yet received the tombstone, who is accountable? | J7: The accountability gap in the propagation window is the question a customer asks after somebody follows the old procedure. | K7: Architecture Review Report §D-M25 (Scenario 4) | L7: Undocumented — no answer exists | M7: D10 supersession propagation SLA | N7: - | O7: What is the propagation SLA? / What does the learner see meanwhile? / Is the window disclosed? | P7: Names the propagation window, its disclosure and the accountable role
A8: QST0177 | B8: D01 | C8: AI SME Chatbot (learner) | D8: SUP | E8: Support & Service Engineer | F8: L4 Architect | G8: Quarter 1 | H8: Trade-off | I8: Should the retrieval assistant be offered to support engineers as a first-line diagnostic tool? | J8: An assistant that confidently gives a support engineer a wrong procedure turns a single incident into a customer-facing error. | K8: Architecture Review Report §I.1 | L8: Undocumented — no answer exists | M8: E09 internal knowledge tooling | N8: - | O8: What corpus would it use? / What is its refusal behaviour? / Is its output logged? | P8: Weighs speed gains against the cost of a confidently wrong internal answer
A9: QAI0003 | B9: D01 | C9: SME Chatbot (learner) | D9: AI | E9: AI/ML Engineer | F9: L1 Junior | G9: Day 1 | H9: Orientation | I9: Where does the learner chatbot's model inference physically run in an enclave deployment of EdVidura? | J9: An engineer who assumes a hosted API is reachable will build a code path that cannot exist in a zero-egress site and fails acceptance. | K9: Architecture Review Report SS Q.3; Master Checklist v3 (AIA-03.1.01) | L9: Partially documented | M9: AIA-12.1.05 zero-egress install of M26 | N9: - | O9: Which model is approved for that enclave? / Who approves it? | P9: Names the shared local inference service, the GPU appliance, and the absence of any hosted fallback
A10: QAI0009 | B10: D01 | C10: SME Chatbot (learner) | D10: AI | E10: AI/ML Engineer | F10: L2 Mid | G10: Month 1 | H10: Data | I10: How does an answer record capture which model, prompt and index version produced it? | J10: Without the version block, a wrong answer six months later cannot be attributed to a model, so nothing can be regression-tested or rolled back. | K10: Master Checklist v3 (AIA-08.1.02, AIA-09.1.06) | L10: Partially documented | M10: AIA-09.1.06 chat audit trail | N10: - | O10: Is the weights hash recorded? / How long is the record retained? | P10: Names the fields, where they are stored, and the query that reconstructs an answer
A11: QAI0015 | B11: D01 | C11: SME Chatbot (learner) | D11: AI | E11: AI/ML Engineer | F11: L3 Senior | G11: Quarter 1 | H11: Performance/Scale | I11: What is the blast radius when the shared inference service saturates during a class-wide chatbot session in an enclave? | J11: With no hosted relief valve, every AI feature in the site fails at the moment of peak instructional use and adoption does not recover. | K11: Architecture Review Report Scenario 11; Master Checklist v3 (AIA-03.1.03) | L11: Partially documented | M11: AIA-03.2.04 Scenario 11 acceptance test | N11: - | O11: Which priority class loses first? / What does the learner see while queued? | P11: Names the priority classes, the degraded modes, and which features stop entirely
A12: QAI0022 | B12: D01 | C12: SME Chatbot (learner) | D12: AI | E12: AI/ML Engineer | F12: L4 Architect | G12: Quarter 1 | H12: Trade-off | I12: Why is the quantized open-weight model on the enclave appliance treated as the release-gating configuration rather than the hosted model? | J12: Gating on the hosted configuration ships an enclave product whose safety behaviour has never been measured on the model it runs. | K12: Architecture Review Report SS I.1-6, Operating Principle 4.7 | L12: Documented | M12: AIA-04.2.02 release gates wired into CI | N12: - | O12: What if the local model cannot pass? / Who accepts the delta in writing? | P12: Argues from the enclave commitment to the quality bar and names the descope options
A13: QAI0001 | B13: D01 | C13: SME Chatbot (learner) | D13: AIG | E13: AI Generalist | F13: L1 Junior | G13: Week 1 | H13: Orientation | I13: What is a supersession tombstone in the learner chatbot's retrieval path and why does EdVidura block a chunk before the index is rebuilt? | J13: A new joiner who assumes re-indexing is the only supersession control will ship a window in which a learner can be served an obsolete maintenance procedure. | K13: Master Checklist v3 (KNI-02.2.03, AIA-09.1.03); Architecture Review Report SS I.1-4 | L13: Partially documented | M13: KNI-02.2.03 M26 supersession compliance | N13: - | O13: Who applies the tombstone? / How does a tombstone reach an air-gapped enclave? / What does the learner see in the gap? | P13: Names the tombstone list, the query-time block, and the difference between blocking and re-indexing
... A2640: QPF0123 | B2640: XCUT | C2640: xAPI and the LRS | D2640: SUP | E2640: Support & Service Engineer | F2640: L3 Senior | G2640: Quarter 1 | H2640: Emergent | I2640: A learner insists they completed a module and the LRS has no statement — what evidence can support actually gather? | J2640: Without client-side evidence the dispute is the learner's word against an empty query, and the platform always appears to be right. | K2640: Architecture Review Report §F Scenario 3 (no audit chain) | L2640: Undocumented — no answer exists | M2640: PLT-09.x offline store-and-forward SDK | N2640: QPF0108 | O2640: Does the client keep a local receipt? / Is there a failed-send queue on the device? / How long is it retained? | P2640: Names a client-side artefact that can corroborate the learner

Sheet Onboarding Paths
A1: Onboarding Paths
A2: One walkable path per role: Day 1 → Week 1 → Month 1 → Quarter 1. Work top-down within a phase. Tick 'Done?' when you can answer it unaided.
A4: Role | B4: Role name | C4: Phase | D4: # | E4: QID | F4: ProductID | G4: Component | H4: Level | I4: Question | J4: Ask / read | K4: Answer status | L4: Done?
A5: FE | B5: Front-End Developer | C5: Day 1 | D5: 1 | E5: QCT0029 | F5: D11 | G5: DCT Authoring & Lesson Planner (M22) | H5: L1 Junior | I5: Where does the DCT authoring UI run, and does an author reach it inside the LMS or as a separate application? | J5: Product Plan v2 M22 scope; Master Checklist v3 CNT-02.1.01 | K5: Partially documented
A6: FE | B6: Front-End Developer | C6: Day 1 | D6: 2 | E6: QCT0052 | F6: D12 | G6: Interactive eBooks & Digitization (M9/M24) | H6: L1 Junior | I6: What is NRPS, and what does the eBook use it for rather than building its own roster? | J6: Master Checklist v3 COR-13.1.02, COR-01.1.05; Architecture Review §D1 M9 (roster duplication) | K6: Partially documented
A7: FE | B7: Front-End Developer | C7: Day 1 | D7: 3 | E7: QAX0006 | F7: D18 | G7: Analytics Dashboard Suite (M6/M10/M30) | H7: L1 Junior | I7: What is signed static embedding and how does it differ from putting a Metabase URL in an iframe? | J7: Master Checklist v3 (ANA-06.1.01, ANA-06.1.03) | K7: Partially documented
A8: FE | B8: Front-End Developer | C8: Day 1 | D8: 4 | E8: QPF0002 | F8: E01 | G8: Core Platform & Identity | H8: L1 Junior | I8: What is a JWK, and at which exact point in an EdVidura front-end's login flow is a JWK actually used? | J8: OIDC/JOSE spec; Platform Architect | K8: Partially documented
A9: FE | B9: Front-End Developer | C9: Day 1 | D9: 5 | E9: QPF0053 | F9: E03 | G9: LMS & Course-Site Integration | H9: L1 Junior | I9: What is an LTI 1.3 launch, and what does the EdVidura tool receive at the moment a learner clicks a link in Moodle? | J9: Product Plan v2 (M7); 1EdTech LTI 1.3 spec | K9: Partially documented
A10: FE | B10: Front-End Developer | C10: Day 1 | D10: 6 | E10: QCT0202 | F10: XCUT | G10: Accessibility (WCAG 2.2 AA + Indian standard) | H10: L1 Junior | I10: Which team owns the accessibility quality bar across eBooks, dashboards, chatbot and XR? | J10: Master Checklist v3 COR-11.2.02; Architecture Review §D1 M9 (CONTRADICTED ownership) | K10: Partially documented
A11: FE | B11: Front-End Developer | C11: Day 1 | D11: 7 | E11: QPF0193 | F11: XCUT | G11: Keycloak, OIDC, JWT and JWKS | H11: L1 Junior | I11: What are the three parts of a JWT, and which of them may a front-end read safely? | J11: JWT specification; Platform Architect | K11: Documented
A12: FE | B12: Front-End Developer | C12: Day 1 | D12: 8 | E12: QPF0134 | F12: XCUT | G12: Learning-data API (single event door) | H12: L1 Junior | I12: Does a browser-based EdVidura tool call the event door directly, or does its own back end call it? | J12: Product Plan v2 (M3); Platform Architect | K12: Undocumented — no answer exists
A13: FE | B13: Front-End Developer | C13: Day 1 | D13: 9 | E13: QCT0233 | F13: XCUT | G13: Localisation & Language Tier Matrix | H13: L1 Junior | I13: What does string externalisation mean, and why is it mandated before more interface code is written? | J13: Master Checklist v3 PRG-07.1.02, PRG-07.1.03; Architecture Review §V.4 decision V-D2 | K13: Partially documented
A14: FE | B14: Front-End Developer | C14: Day 1 | D14: 10 | E14: QWP0281 | F14: XCUT | G14: MOSA Conformance | H14: L1 Junior | I14: Where would a front-end developer look up the current version of the interface they are building against? | J14: Master Checklist v3 (PLT-05.1.01, PLT-05.1.02) | K14: Partially documented
A15: FE | B15: Front-End Developer | C15: Day 1 | D15: 11 | E15: QPF0168 | F15: XCUT | G15: Multi-tenancy and row-level security | H15: L1 Junior | I15: Does a front-end ever send a tenant identifier, and would the back end believe it? | J15: Architecture Review Report §G.3; Platform Architect | K15: Undocumented — no answer exists
A16: FE | B16: Front-End Developer | C16: Day 1 | D16: 12 | E16: QWP0286 | F16: XCUT | G16: Observability & Operations | H16: L1 Junior | I16: Where does a front-end developer find the correlation identifier to attach to a bug report about a failed launch? | J16: Master Checklist v3 (PLT-06.1.01, PLT-06.1.02) | K16: Undocumented — no answer exists
... A2642: SUP | B2642: Support & Service Engineer | C2642: Quarter 1 | D2642: 118 | E2642: QST0190 | F2642: E09 | G2642: Support & Service Management | H2642: L4 Architect | I2642: If workarounds must expire, who funds the permanent fix when the customer is satisfied with the workaround? | J2642: Master Checklist v3 (PRG-96.2.07) | K2642: Undocumented — no answer exists

Sheet Documentation Backlog
A1: Documentation Backlog
A2: THE MOST VALUABLE SHEET. Sorted by leverage: writing the top document answers the most questions at once. Day1+Wk1 counts show which gaps hurt a new joiner immediately.
A4: ProductID | B4: Product | C4: Component / topic | D4: Questions unanswered | E4: of which Day1+Wk1 | F4: Roles affected | G4: Phases | H4: Example QIDs | I4: Document to write | J4: Owner | K4: Target date
A5: XCUT | B5: Cross-cutting framework / Whole Product | C5: Whole Product | D5: 126 | E5: 32 | F5: AI, BE, BI, DA, DE, DEVOPS, FE, ID, MXR, PM, PRODM, QA, SDET, SEC, SUP | G5: Day 1, Week 1, Month 1, Quarter 1 | H5: QWP0016; QWP0078; QWP0011; QWP0012; QWP0060; QWP0014…
A6: XCUT | B6: Cross-cutting framework / Whole Product | C6: Multi-tenancy and row-level security | D6: 29 | E6: 2 | F6: AI, BE, BI, DA, DE, DEVOPS, FE, PM, QA, SDET, SEC, SUP | G6: Day 1, Month 1, Quarter 1 | H6: QPF0172; QPF0190; QPF0164; QPF0169; QPF0174; QPF0181…
A7: XCUT | B7: Cross-cutting framework / Whole Product | C7: PostgreSQL, replicas and migrations | D7: 29 | E7: 5 | F7: BE, BI, DA, DE, DEVOPS, PM, QA, SDET, SEC, SUP | G7: Day 1, Week 1, Month 1, Quarter 1 | H7: QPF0229; QPF0232; QPF0238; QPF0245; QPF0234; QPF0251…
A8: E02 | B8: Learning Records Spine — LRS + Learning-data API (enabler) | C8: Learning Records Spine | D8: 28 | E8: 7 | F8: AI, BE, BI, DE, DEVOPS, QA, SEC, SUP | G8: Day 1, Week 1, Month 1, Quarter 1 | H8: QPF0284; QPF0052; QPF0036; QPF0043; QPF0049; QPF0040…
A9: XCUT | B9: Cross-cutting framework / Whole Product | C9: Contract registry and API/event versioning | D9: 28 | E9: 6 | F9: AI, BE, BI, DE, DEVOPS, FE, PRODM, QA, SDET, SEC, SUP | G9: Day 1, Week 1, Month 1, Quarter 1 | H9: QPF0264; QPF0253; QPF0254; QPF0259; QPF0269; QPF0275…
A10: XCUT | B10: Cross-cutting framework / Whole Product | C10: Learning-data API (single event door) | D10: 28 | E10: 4 | F10: AI, BE, BI, DA, DE, DEVOPS, FE, QA, SDET, SEC, SUP | G10: Day 1, Week 1, Month 1, Quarter 1 | H10: QPF0145; QPF0160; QPF0140; QPF0155; QPF0157; QPF0146…
A11: E10 | B11: Commercial, Legal & Compliance (India) | C11: Commercial, Legal & Compliance (India) | D11: 26 | E11: 5 | F11: AIG, BE, DE, PM, PRODM, SEC, SUP | G11: Week 1, Month 1, Quarter 1 | H11: QCV0075; QPG0259; QCV0069; QTU0031; QCV0073; QPG0256…
A12: XCUT | B12: Cross-cutting framework / Whole Product | C12: Keycloak, OIDC, JWT and JWKS | D12: 26 | E12: 5 | F12: AI, BE, BI, DE, DEVOPS, FE, MXR, QA, SDET, SEC, SUP | G12: Day 1, Week 1, Month 1, Quarter 1 | H12: QPF0205; QPF0199; QPF0203; QPF0210; QPF0216; QPF0220…
A13: XCUT | B13: Cross-cutting framework / Whole Product | C13: Security & Trust Boundaries | D13: 25 | E13: 5 | F13: AI, AIG, BE, DEVOPS, ID, PM, PRODM, SDET, SEC, SUP | G13: Week 1, Month 1, Quarter 1 | H13: QWP0156; QWP0180; QWP0161; QWP0152; QWP0169; QWP0178…
A14: E09 | B14: Support, Service Management & Operational Handover | C14: Support & Service Management | D14: 24 | E14: 1 | F14: MXR, PRODM, QA, SDET, SUP | G14: Week 1, Month 1, Quarter 1 | H14: QTU0111; QST0289; QTU0119; QCV0116; QST0117; QST0152…
A15: XCUT | B15: Cross-cutting framework / Whole Product | C15: Observability & Operations | D15: 24 | E15: 5 | F15: AI, BI, DA, DE, DEVOPS, FE, MXR, PM, QA, SUP | G15: Day 1, Week 1, Month 1, Quarter 1 | H15: QWP0236; QWP0227; QWP0237; QWP0246; QWP0225; QWP0226…
A16: XCUT | B16: Cross-cutting framework / Whole Product | C16: Air-gapped Enclave Operation | D16: 23 | E16: 3 | F16: AI, BI, DE, DEVOPS, ID, MXR, PM, QA, SEC, SUP | G16: Week 1, Month 1, Quarter 1 | H16: QWP0129; QWP0145; QTU0055; QWP0146; QWP0123; QWP0124…
... A101: D25 | B101: Accelerate Upgrade Readiness Measurement Plan | C101: Upgrade Readiness Measurement Plan | D101: 1 | E101: 0 | F101: DA | G101: Month 1 | H101: QCV0136

Sheet Interview Bank
A1: Interview Bank
A2: Filter by Level and Role to build a sitting. 'What a good answer contains' lets a non-specialist interviewer score. Scores are 1-5; three or more sub-3 answers at the target level is a fail.
A4: Level | B4: Role | C4: Role name | D4: ProductID | E4: Component | F4: Type | G4: Question | H4: What a good answer contains | I4: Why it matters | J4: Score 1-5 | K4: Interviewer | L4: Notes
A5: L1 Junior | B5: AI | C5: AI/ML Engineer | D5: D01 | E5: SME Chatbot (learner) | F5: Orientation | G5: Where does the learner chatbot's model inference physically run in an enclave deployment of EdVidura? | H5: Names the shared local inference service, the GPU appliance, and the absence of any hosted fallback | I5: An engineer who assumes a hosted API is reachable will build a code path that cannot exist in a zero-egress site and fails acceptance.
A6: L1 Junior | B6: AI | C6: AI/ML Engineer | D6: D02 | E6: AI Assessment and Auto Grader | F6: Orientation | G6: What fields make up the mandatory version block on an AI-influenced grade? | H6: Lists model ID with weights hash, quantization, prompt and rubric version, item version, deployment class | I6: A grade without its model, quantization and rubric version cannot be defended when a competency record is disputed two years later.
A7: L1 Junior | B7: AI | C7: AI/ML Engineer | D7: D13 | E7: SME Chatbot (authoring) | F7: Data | G7: What provenance metadata must every AI suggestion in the authoring tool carry? | H7: Lists source references, model version and prompt version, and where they persist | I7: Without provenance nobody can tell which published lesson came from a model version that was later found defective.
A8: L1 Junior | B8: AI | C8: AI/ML Engineer | D8: E04 | E8: Shared Local AI Inference Platform | F8: Orientation | G8: What is quantisation and why does it decide what EdVidura can promise in an enclave? | H8: Defines quantisation and links it to the measured quality delta and VRAM budget | I8: An engineer who benchmarks a full-precision model has measured a configuration the customer will never run.
A9: L1 Junior | B9: AI | C9: AI/ML Engineer | D9: E04 | E9: Shared Local AI Inference Platform | F9: Orientation | G9: What is the shared local inference platform, and which EdVidura products call it rather than running their own model? | H9: Names the platform, its consumers and the interface they call | I9: A product that stands up its own inference stack doubles the GPU footprint at a site and escapes every evaluation gate the shared platform enforces.
A10: L1 Junior | B10: AI | C10: AI/ML Engineer | D10: XCUT | E10: AI evaluation gates and drift | F10: Orientation | G10: How does groundedness differ from an answer simply being correct? | H10: Defines sentence-level support by retrieved context and separates it from truth | I10: Confusing the two lets an ungrounded but plausible answer pass a groundedness review.
A11: L1 Junior | B11: AI | C11: AI/ML Engineer | D11: XCUT | E11: AI evaluation gates and drift | F11: Orientation | G11: What is an evaluation gate, and which gate blocks a model or prompt change from reaching learners? | H11: Names the gate, its threshold, and the release step it blocks | I11: A change shipped without passing its gate can degrade grounding across every answer a learner sees, and nobody will notice until a teacher disputes an answer.
A12: L1 Junior | B12: AI | C12: AI/ML Engineer | D12: XCUT | E12: AI evaluation gates and drift | F12: Emergent | G12: Once a model has passed its evaluation gate, what still has to be re-run when only the retrieval index is rebuilt? | H12: Ties the evaluation result to the model, prompt and index triple rather than the model alone | I12: Treating an index rebuild as a data operation rather than a release change lets retrieval quality regress behind an evaluation result that no longer applies.
A13: L1 Junior | B13: AI | C13: AI/ML Engineer | D13: XCUT | E13: AI governance and human review | F13: Orientation | G13: What does version pinning mean for a model, a prompt and an index, and why all three? | H13: Names all three pins, where they are stored and what a change to each triggers | I13: Pinning the model but not the prompt or index means a reproduced answer still cannot be explained.
A14: L1 Junior | B14: AI | C14: AI/ML Engineer | D14: XCUT | E14: AI governance and human review | F14: Governance/Process | G14: Where is EdVidura's approved-model registry, and what does one entry in it record? | H14: Points at the registry and lists the fields an entry carries, including deployment class | I14: Running an unapproved model in a customer deployment is a contractual and accreditation problem regardless of how well the model performs.
A15: L1 Junior | B15: AI | C15: AI/ML Engineer | D15: XCUT | E15: AI governance and human review | F15: Governance/Process | G15: Where is a chatbot's system prompt stored, and how is a change to it versioned and released? | H15: Names the storage location, the version identifier and the release path | I15: A prompt edited in a running service is an untracked change to learner-facing behaviour that no test covered and no rollback can undo.
A16: L1 Junior | B16: AI | C16: AI/ML Engineer | D16: XCUT | E16: Local model serving and GPU capacity | F16: Orientation | G16: What does open-weight mean in EdVidura's context and why can a commercial hosted model not simply be substituted? | H16: Defines open weights, the enclave constraint, and the licence clearance requirement | I16: Assuming a hosted frontier model will be available produces designs that cannot be deployed to the customer who is buying.
... A2643: L2 | B2643: SUP | C2643: Support & Service Engineer | D2643: E10 | E2643: Commercial, Legal & Compliance (India) | F2643: Failure mode | G2643: What does support do when a breach-notification trigger fires inside an air-gapped site? | H2643: Describes the enclave-specific detection-to-notification path with the timing budget | I2643: A notification clock that starts at detection is breached while the evidence is still inside the enclave.

Sheet SME Interview Guide
A1: SME Interview Guide
A2: Group your questions by who can answer them so one meeting resolves many. Sources reading '(nobody — needs a decision)' are not meetings — they are decisions to escalate.
A4: Answer source / who to ask | B4: Questions they can settle | C4: Roles waiting on them | D4: Products | E4: Example QIDs | F4: Meeting booked | G4: Notes
A5: (nobody — needs a decision) | B5: 126 | C5: AI, AIG, BI, DA, DE, FE, ID, MXR | D5: D01, D02, D04, D10, D11, D13, D14, D15, D18, D19 | E5: QTU0088; QAI0026; QAI0029; QAI0020; QAI0024; QAI0028; QAI0005; QAI0027…
A6: Architecture Review Report §H.5 | B6: 6 | C6: ID, SUP | D6: D08, D15, D18, XCUT | E6: QST0029; QST0046; QST0157; QST0166; QST0042; QPF0125
A7: Master Checklist v3 (PRG-96.1.03) | B7: 5 | C7: PRODM, SUP | D7: E09 | E7: QST0289; QST0109; QST0139; QST0147; QST0187
A8: Architecture Review Report §I.8 | B8: 4 | C8: ID | D8: D12, D19, XCUT | E8: QST0021; QST0057; QST0002; QST0072
A9: Architecture Review Report §F Scenario 7 | B9: 4 | C9: BE, DEVOPS, QA, SUP | D9: E01, XCUT | E9: QPF0016; QPF0203; QPF0213; QPF0198
A10: Master Checklist v3 (PRG-06.1.02) | B10: 4 | C10: SDET | D10: E05, E07 | E10: QPG0213; QST0229; QPG0219; QST0249
A11: Master Checklist v3 (PRG-96.1.04) | B11: 4 | C11: SUP | D11: E09 | E11: QST0104; QST0121; QST0170; QST0189
A12: Architecture Review Report §D-M25 (Scenario 4) | B12: 3 | C12: ID, SUP | D12: D01, D10, D11 | E12: QST0155; QST0108; QST0068
A13: Master Checklist v3 (TLA-91.1.01, TLA-91.1.03) | B13: 3 | C13: DA, ID | D13: D08, D28 | E13: QTL0074; QTL0157; QTL0172
A14: Master Checklist v3 (TLA-15.1.02) | B14: 3 | C14: BE, SDET | D14: D09 | E14: QTL0082; QTL0085; QTL0084
A15: Architecture Review Report §H.5; Instructional Design Lead | B15: 3 | C15: AI, AIG, MXR | D15: D13, XCUT | E15: QTU0091; QTU0108; QPF0130
A16: Architecture Review Report §I; Instructional Design Lead | B16: 3 | C16: DA | D16: D14, D18, XCUT | E16: QTU0074; QTU0071; QTU0062
... A124: Architecture Review Report §G.3 required layered enforcement | B124: 2 | C124: DEVOPS, SDET | D124: XCUT | E124: QPF0187; QPF0178

Sheet Second-Order Questions
A1: Second-Order Questions
A2: Loop 6 output — the questions that only arise AFTER the first answer, when two components' rules collide, or from the first ninety days of lived experience. These are the ones nobody thinks to write down.
A4: QID | B4: Parent QID | C4: ProductID | D4: Component | E4: Role | F4: Level | G4: Question | H4: Why it matters
A5: QTU0088 | B5: QTU0087 | C5: D01 | D5: AI SME Chatbot (learner) | E5: AIG | F5: L4 Architect | G5: Should the learner chatbot cite a source the learner is not cleared to open? | H5: Citing an inaccessible source either discloses the existence of restricted material or leaves the learner with an unverifiable claim, and both undermine the grounding promise the product is sold on.
A6: QST0142 | B6: QST0124 | C6: D01 | D6: AI SME Chatbot (learner) | E6: SUP | F6: L2 Mid | G6: If an answer records its index version, how does support find out which document revision that index was built from? | H6: Without the revision link the citation proves nothing and the supersession investigation stalls at the first step.
A7: QAI0026 | B7: QAI0001 | C7: D01 | D7: SME Chatbot (learner) | E7: AIG | F7: L3 Senior | G7: Who is accountable for a learner who followed an obsolete procedure during the window between a manual revision and tombstone arrival in their enclave? | H7: An unassigned accountability for the known unsafe window means nobody is funded to shrink it.
A8: QAI0029 | B8: QAI0022 | C8: D01 | D8: SME Chatbot (learner) | E8: PM | F8: L4 Architect | G8: If the hosted-versus-local delta proves unacceptable at Slice D, which already-signed commitments have to be re-opened? | H8: Discovering the contractual exposure after the measurement is what turns a technical finding into a commercial crisis.
A9: QAI0028 | B9: QAI0008 | C9: D01 | D9: SME Chatbot (learner) | E9: SEC | F9: L3 Senior | G9: When the post-retrieval tenant assertion fires in production, is that a defect ticket or a reportable isolation incident? | H9: Classifying a real cross-tenant retrieval as a bug means it never reaches the security register or the customer.
A10: QAI0027 | B10: QAI0005 | C10: D01 | D10: SME Chatbot (learner) | E10: SUP | F10: L2 Mid | G10: If high refusal turns out to be a calibrated threshold rather than a defect, what evidence does support attach to close the ticket? | H10: Closing safety-adjacent tickets with an opinion destroys the audit trail we need when refusal calibration is later challenged.
A11: QAI0030 | B11: QAI0019 | C11: D01 | D11: SME Chatbot (learner) | E11: SUP | F11: L4 Architect | G11: What may an air-gapped site export to us for diagnosis without breaching its own accreditation? | H11: A diagnostic request that violates the site's security rules is refused, and the defect stays unfixed for an entire update cycle.
A12: QST0048 | B12: QST0031 | C12: D02 | D12: AI Assessment Tools | E12: ID | F12: L2 Mid | G12: If AI-generated items must all be human reviewed until escape rates are measured, how is the escape rate measured before any sampling exists? | H12: Circular gating means the sampling rate never moves and the reviewer queue is permanently the bottleneck for the whole content pipeline.
A13: QST0069 | B13: QST0052 | C13: D02 | D13: AI Assessment Tools | E13: ID | F13: L3 Senior | G13: If grading models are pinned per enclave, how do you compare item statistics computed at two sites running different pinned versions? | H13: Pooling statistics across model versions produces item difficulty figures that describe neither site and are used to retire good items.
A14: QAI0051 | B14: QAI0035 | C14: D02 | D14: AI Assessment and Auto Grader | E14: AI | F14: L3 Senior | G14: If the reproducibility gate fails on the quantized enclave model, is the deterministic fallback the enclave product for grading? | H14: Treating the fallback as a temporary measure hides the possibility that semantic grading is simply not deliverable air-gapped.
A15: QAI0052 | B15: QAI0040 | C15: D02 | D15: AI Assessment and Auto Grader | E15: DA | F15: L3 Senior | G15: If a fairness disparity is found after grades have already been issued, which prior grades get re-examined? | H15: Fixing the model forward while leaving issued grades untouched leaves a known-biased cohort on the record.
... A458: QPF0123 | B458: QPF0108 | C458: XCUT | D458: xAPI and the LRS | E458: SUP | F458: L3 Senior | G458: A learner insists they completed a module and the LRS has no statement — what evidence can support actually gather? | H458: Without client-side evidence the dispute is the learner's word against an empty query, and the platform always appears to be right.

Sheet Coverage — Role x Level
A1: Coverage — Role x Level
A2: Every cell must hold at least 15 questions. Generated by the Loop 10 verification gate.
A4: Code | B4: Role | C4: L1 Junior | D4: L2 Mid | E4: L3 Senior | F4: L4 Architect | G4: Total | H4: Floor 15
A5: FE | B5: Front-End Developer | C5: 27 | D5: 24 | E5: 18 | F5: 18 | G5: 87 | H5: OK
A6: BE | B6: Back-End Developer | C6: 47 | D6: 93 | E6: 42 | F6: 33 | G6: 215 | H6: OK
A7: DE | B7: Data Engineer | C7: 23 | D7: 60 | E7: 57 | F7: 18 | G7: 158 | H7: OK
A8: BI | B8: BI / Analytics Developer (Metabase) | C8: 18 | D8: 23 | E8: 23 | F8: 18 | G8: 82 | H8: OK
A9: DA | B9: Data Analyst | C9: 18 | D9: 17 | E9: 32 | F9: 18 | G9: 85 | H9: OK
A10: AI | B10: AI/ML Engineer | C10: 18 | D10: 21 | E10: 37 | F10: 26 | G10: 102 | H10: OK
A11: AIG | B11: AI Generalist | C11: 19 | D11: 19 | E11: 15 | F11: 18 | G11: 71 | H11: OK
A12: MXR | B12: Mobile & XR Developer | C12: 19 | D12: 19 | E12: 19 | F12: 18 | G12: 75 | H12: OK
A13: DEVOPS | B13: DevSecOps / Platform Engineer | C13: 24 | D13: 54 | E13: 67 | F13: 24 | G13: 169 | H13: OK
A14: SEC | B14: Security Engineer | C14: 16 | D14: 48 | E14: 87 | F14: 40 | G14: 191 | H14: OK
A15: QA | B15: QA / Test Engineer | C15: 43 | D15: 55 | E15: 74 | F15: 18 | G15: 190 | H15: OK
A16: SDET | B16: Test Architect / SDET | C16: 18 | D16: 31 | E16: 74 | F16: 20 | G16: 143 | H16: OK
... A20: SUP | B20: Support & Service Engineer | C20: 56 | D20: 47 | E20: 101 | F20: 25 | G20: 229 | H20: OK

Sheet Coverage — by product
A1: Coverage — by product
A2: Floors: ≥24 per client deliverable, ≥12 per enabling product, ≥30 per cross-cutting framework (XCUT aggregates many frameworks).
A4: ProductID | B4: Product / framework | C4: Questions | D4: Roles | E4: Levels | F4: No answer today | G4: Floor
A5: D01 | B5: AI SME Chatbot — Learner-Facing | C5: 37 | D5: 12 | E5: 4 | F5: 15 | G5: OK
A6: D02 | B6: AI Assessment Tools & Test Banks + Auto Grader | C6: 35 | D6: 12 | E6: 4 | F6: 11 | G6: OK
A7: D03 | B7: Security Accreditation & Authorisation to Operate — Initiation | C7: 36 | D7: 7 | E7: 8 | F7: 22 | G7: OK
A8: D04 | B8: Pedagogy Design Review Protocol | C8: 33 | D8: 9 | E8: 5 | F8: 26 | G8: OK
A9: D05 | B9: TLA CMM Level 2 — Microservices | C9: 26 | D9: 11 | E9: 5 | F9: 19 | G9: OK
A10: D06 | B10: TLA Experience-Index (ELRR) | C10: 26 | D10: 11 | E10: 4 | F10: 8 | G10: OK
A11: D07 | B11: TLA Course Catalogue (ECC) | C11: 26 | D11: 12 | E11: 4 | F11: 6 | G11: OK
A12: D08 | B12: TLA Competency-Registry | C12: 37 | D12: 11 | E12: 4 | F12: 13 | G12: OK
A13: D09 | B13: TLA CMM Level 3 | C13: 25 | D13: 10 | E13: 5 | F13: 11 | G13: OK
A14: D10 | B14: PDFs & Technical Manuals Integration — Live TO Connection | C14: 29 | D14: 12 | E14: 4 | F14: 10 | G14: OK
A15: D11 | B15: DCT — Content Authoring & Lesson Planner | C15: 33 | D15: 12 | E15: 4 | F15: 10 | G15: OK
A16: D12 | B16: Interactive eBooks — Technical Manuals Digitization | C16: 32 | D16: 13 | E16: 4 | F16: 9 | G16: OK
... A48: XCUT | B48: Cross-cutting framework / Whole Product | C48: 1214 | D48: 16 | E48: 8 | F48: 658 | G48: OK

Sheet Lists
A1: Controlled vocabularies (named ranges)
A3: RoleList | B3: LevelList | C3: PhaseList | D3: StatusList | E3: ConfList | F3: TypeList
A4: FE | B4: L1 Junior | C4: Day 1 | D4: Documented | E4: High | F4: Cost
A5: BE | B5: L2 Mid | C5: Week 1 | D5: Partially documented | E5: Medium | F5: Data
A6: DE | B6: L3 Senior | C6: Month 1 | D6: Tribal knowledge only | E6: Low | F6: Emergent
A7: BI | B7: L4 Architect | C7: Quarter 1 | D7: Undocumented — no answer exists | F7: Ethics/Validity
A8: DA | C8: Ongoing | F8: Failure mode
A9: AI | F9: Governance/Process
A10: AIG | F10: Interface/Contract
A11: MXR | F11: Mechanism
A12: DEVOPS | F12: Orientation
A13: SEC | F13: Performance/Scale
A14: QA | F14: Security
A15: SDET | F15: Standards
A16: PM | F16: Trade-off
A17: PRODM
A18: ID
A19: SUP

Sheet How to use
A1: How to use the question bank
A3: THE FOUR USES
A4: Onboarding | B4: Open **Onboarding Paths**, filter to your role, and work Day 1 → Week 1 → Month 1 → Quarter 1. Tick 'Done?' only when you can answer unaided. A Day 1 question never depends on Week 1 knowledge.
A5: Interviewing | B5: Open **Interview Bank**, filter to the level and role you are hiring. 'What a good answer contains' lets a non-specialist score. Three or more sub-3 answers at the target level is a fail.
A6: Asking the right people | B6: Open **SME Interview Guide**. It groups questions by who can settle them, so one meeting clears many. Rows reading '(nobody — needs a decision)' are escalations, not meetings.
A7: Fixing the documentation | B7: Open **Documentation Backlog** — sorted so the top row is the document that answers the most open questions. This is the highest-value sheet in the workbook.
A9: HOW TO READ A QUESTION
A10: Level | B10: L1 Junior = orientation and mechanics. L2 Mid = how it works end to end and how to extend it. L3 Senior = how it fails, how we detect it, how we recover. L4 Architect = judgement between defensible alternatives. If the answer is a procedure it is L2; a judgement about failure is L3; a defensible choice among alternatives is L4.
A11: Answer status | B11: Documented = an existing artefact answers it. Partially documented = the work item exists but the answer does not yet. Tribal knowledge only = one person knows. Undocumented = nobody can answer it today. The last two are findings, not failures.
A12: Why it matters | B12: Names the real failure if the person does not know this. If you cannot see why a question matters, read this column before dismissing it.
A13: Follow-ups | B13: The second-order questions the answer should provoke. Ask them in the same meeting — that is where the expensive surprises hide.
A15: KEEPING IT ALIVE
A16: When you get an answer | B16: Fill AnsweredBy, AnswerDate and DocLink on the Question Bank sheet, and change AnswerStatus. The Summary counts update automatically.
A17: When you write a document | B17: Work the top of the Documentation Backlog first, then re-run the status counts. One good document can close dozens of questions.
A18: When scope changes | B18: Add questions rather than editing old ones; QIDs are stable and referenced elsewhere.
A19: When a contradiction appears | B19: There are questions in this bank about the programme's own contradictions (the same acronym naming two products, two components claiming the same event). Do not resolve them by guessing — escalate them.

Sheet Version & Change Log
A1: Version & Change Log
A2: This bank is versioned. QIDs are stable identifiers referenced by onboarding paths, the interview bank and the documentation backlog - never renumber one.
A4: Version | B4: Date | C4: Change | D4: Questions | E4: Affected
A5: v1.0 Final | B5: 28 Jul 2026 | C5: Coverage-findings tranche added (QCV set, 161 questions) from the product coverage cross-check: D29 acceptance authority, D03 accreditation evidence, E05 MOSA conformance instrumentation, D28 hollow maturity claim, the three scope-drift products (D21, E10, D30), portfolio-wide ownership, and the five systemic dimension failures. | D5: +161 | E5: Question Bank, all views
A6: v1.0 Final | B6: 28 Jul 2026 | C6: Answer-status vocabulary normalised (hyphen/em-dash variants merged). | D6: - | E6: Question Bank
A7: v1.0 Final | B7: 28 Jul 2026 | C7: All existing QIDs preserved unchanged; no question renumbered or deleted. | D7: 0 changed | E7: Question Bank
A8: v0.9 | B8: 27 Jul 2026 | C8: Initial generation per the Onboarding Question-Bank Engineering Prompt v1, Loops 1-10; coverage gate passed with zero Role x Level cells under floor. | D8: 2,478 | E8: All
C9: FUTURE CHANGES: add a row here for every tranche. Never renumber an issued QID; add new ones.
