Workbook

Sheet Summary
A1: EdVidura Master Checklist v3 — remediated delivery system
A2: 2120 items (1830 carried from v2 + 290 added by audit) · 43 products · 8 squads + QA guild · 9 test teams · 6 stages
A3: v3 applies the audit fixes: India re-basing, 11 new delivery-management sheets, 7 new columns, controlled vocabularies, conditional formatting, protection and a change log.
A4: YELLOW = you fill in. Start with Assignee on Stage 0–1 rows, then EstDays, then the Sprint Calendar and Capacity sheets.
A6: Locked provisional decisions
A7: Metabase edition | B7: OSS; tenant isolation at DB level (RLS / per-tenant schemas); signed static embedding
A8: Tenancy model | B8: Hybrid — shared schema + RLS for SaaS tenants; instance-per-command/organisation for enclaves
A9: Accreditation authority | B9: Deferred by direction — product renamed market-neutral; authority is a Human-Input entry, no authority asserted
A10: Market | B10: India-first, with air-gapped/enclave capability retained; immersive labs are now a repeatable India lab product
A11: Event transport | B11: PostgreSQL transactional outbox + workers first; broker promotion later
A12: Local AI | B12: One shared local-inference platform (E04) consumed by every AI module
A15: Progress by squad (live)
A16: Squad | B16: Build | C16: Test | D16: Total | E16: Done | F16: In progress | G16: Blocked | H16: % done | I16: Unassigned | J16: Est. days
A17: SQ1 Platform Core | B17: =COUNTIFS('Master Checklist'!$H:$H,$A17,'Master Checklist'!$D:$D,"Build") -> 290 | C17: =COUNTIFS('Master Checklist'!$H:$H,$A17,'Master Checklist'!$D:$D,"Test") -> 27 | D17: =COUNTIF('Master Checklist'!$H:$H,$A17) -> 317 | E17: =COUNTIFS('Master Checklist'!$H:$H,$A17,'Master Checklist'!$Y:$Y,"Done") -> 0 | F17: =COUNTIFS('Master Checklist'!$H:$H,$A17,'Master Checklist'!$Y:$Y,"In progress") -> 0 | G17: =COUNTIFS('Master Checklist'!$H:$H,$A17,'Master Checklist'!$Y:$Y,"Blocked") -> 0 | H17: =IF(D17=0,0,E17/D17) -> 0 | I17: =COUNTIFS('Master Checklist'!$H:$H,$A17,'Master Checklist'!$L:$L,"") -> 317 | J17: =SUMIF('Master Checklist'!$H:$H,$A17,'Master Checklist'!$M:$M) -> 0
A18: SQ2 Learning Tools | B18: =COUNTIFS('Master Checklist'!$H:$H,$A18,'Master Checklist'!$D:$D,"Build") -> 277 | C18: =COUNTIFS('Master Checklist'!$H:$H,$A18,'Master Checklist'!$D:$D,"Test") -> 58 | D18: =COUNTIF('Master Checklist'!$H:$H,$A18) -> 335 | E18: =COUNTIFS('Master Checklist'!$H:$H,$A18,'Master Checklist'!$Y:$Y,"Done") -> 0 | F18: =COUNTIFS('Master Checklist'!$H:$H,$A18,'Master Checklist'!$Y:$Y,"In progress") -> 0 | G18: =COUNTIFS('Master Checklist'!$H:$H,$A18,'Master Checklist'!$Y:$Y,"Blocked") -> 0 | H18: =IF(D18=0,0,E18/D18) -> 0 | I18: =COUNTIFS('Master Checklist'!$H:$H,$A18,'Master Checklist'!$L:$L,"") -> 335 | J18: =SUMIF('Master Checklist'!$H:$H,$A18,'Master Checklist'!$M:$M) -> 0
A19: SQ3 Data & Analytics | B19: =COUNTIFS('Master Checklist'!$H:$H,$A19,'Master Checklist'!$D:$D,"Build") -> 183 | C19: =COUNTIFS('Master Checklist'!$H:$H,$A19,'Master Checklist'!$D:$D,"Test") -> 19 | D19: =COUNTIF('Master Checklist'!$H:$H,$A19) -> 202 | E19: =COUNTIFS('Master Checklist'!$H:$H,$A19,'Master Checklist'!$Y:$Y,"Done") -> 0 | F19: =COUNTIFS('Master Checklist'!$H:$H,$A19,'Master Checklist'!$Y:$Y,"In progress") -> 0 | G19: =COUNTIFS('Master Checklist'!$H:$H,$A19,'Master Checklist'!$Y:$Y,"Blocked") -> 0 | H19: =IF(D19=0,0,E19/D19) -> 0 | I19: =COUNTIFS('Master Checklist'!$H:$H,$A19,'Master Checklist'!$L:$L,"") -> 202 | J19: =SUMIF('Master Checklist'!$H:$H,$A19,'Master Checklist'!$M:$M) -> 0
A20: SQ4 TLA & Federation | B20: =COUNTIFS('Master Checklist'!$H:$H,$A20,'Master Checklist'!$D:$D,"Build") -> 225 | C20: =COUNTIFS('Master Checklist'!$H:$H,$A20,'Master Checklist'!$D:$D,"Test") -> 39 | D20: =COUNTIF('Master Checklist'!$H:$H,$A20) -> 264 | E20: =COUNTIFS('Master Checklist'!$H:$H,$A20,'Master Checklist'!$Y:$Y,"Done") -> 0 | F20: =COUNTIFS('Master Checklist'!$H:$H,$A20,'Master Checklist'!$Y:$Y,"In progress") -> 0 | G20: =COUNTIFS('Master Checklist'!$H:$H,$A20,'Master Checklist'!$Y:$Y,"Blocked") -> 0 | H20: =IF(D20=0,0,E20/D20) -> 0 | I20: =COUNTIFS('Master Checklist'!$H:$H,$A20,'Master Checklist'!$L:$L,"") -> 264 | J20: =SUMIF('Master Checklist'!$H:$H,$A20,'Master Checklist'!$M:$M) -> 0
A21: SQ5 AI & Assessment | B21: =COUNTIFS('Master Checklist'!$H:$H,$A21,'Master Checklist'!$D:$D,"Build") -> 270 | C21: =COUNTIFS('Master Checklist'!$H:$H,$A21,'Master Checklist'!$D:$D,"Test") -> 34 | D21: =COUNTIF('Master Checklist'!$H:$H,$A21) -> 304 | E21: =COUNTIFS('Master Checklist'!$H:$H,$A21,'Master Checklist'!$Y:$Y,"Done") -> 0 | F21: =COUNTIFS('Master Checklist'!$H:$H,$A21,'Master Checklist'!$Y:$Y,"In progress") -> 0 | G21: =COUNTIFS('Master Checklist'!$H:$H,$A21,'Master Checklist'!$Y:$Y,"Blocked") -> 0 | H21: =IF(D21=0,0,E21/D21) -> 0 | I21: =COUNTIFS('Master Checklist'!$H:$H,$A21,'Master Checklist'!$L:$L,"") -> 304 | J21: =SUMIF('Master Checklist'!$H:$H,$A21,'Master Checklist'!$M:$M) -> 0
A22: SQ6 Content & Authoring | B22: =COUNTIFS('Master Checklist'!$H:$H,$A22,'Master Checklist'!$D:$D,"Build") -> 131 | C22: =COUNTIFS('Master Checklist'!$H:$H,$A22,'Master Checklist'!$D:$D,"Test") -> 26 | D22: =COUNTIF('Master Checklist'!$H:$H,$A22) -> 157 | E22: =COUNTIFS('Master Checklist'!$H:$H,$A22,'Master Checklist'!$Y:$Y,"Done") -> 0 | F22: =COUNTIFS('Master Checklist'!$H:$H,$A22,'Master Checklist'!$Y:$Y,"In progress") -> 0 | G22: =COUNTIFS('Master Checklist'!$H:$H,$A22,'Master Checklist'!$Y:$Y,"Blocked") -> 0 | H22: =IF(D22=0,0,E22/D22) -> 0 | I22: =COUNTIFS('Master Checklist'!$H:$H,$A22,'Master Checklist'!$L:$L,"") -> 157 | J22: =SUMIF('Master Checklist'!$H:$H,$A22,'Master Checklist'!$M:$M) -> 0
A23: SQ7 Field & Immersive | B23: =COUNTIFS('Master Checklist'!$H:$H,$A23,'Master Checklist'!$D:$D,"Build") -> 227 | C23: =COUNTIFS('Master Checklist'!$H:$H,$A23,'Master Checklist'!$D:$D,"Test") -> 44 | D23: =COUNTIF('Master Checklist'!$H:$H,$A23) -> 271 | E23: =COUNTIFS('Master Checklist'!$H:$H,$A23,'Master Checklist'!$Y:$Y,"Done") -> 0 | F23: =COUNTIFS('Master Checklist'!$H:$H,$A23,'Master Checklist'!$Y:$Y,"In progress") -> 0 | G23: =COUNTIFS('Master Checklist'!$H:$H,$A23,'Master Checklist'!$Y:$Y,"Blocked") -> 0 | H23: =IF(D23=0,0,E23/D23) -> 0 | I23: =COUNTIFS('Master Checklist'!$H:$H,$A23,'Master Checklist'!$L:$L,"") -> 271 | J23: =SUMIF('Master Checklist'!$H:$H,$A23,'Master Checklist'!$M:$M) -> 0
A24: SQ8 Program & Governance | B24: =COUNTIFS('Master Checklist'!$H:$H,$A24,'Master Checklist'!$D:$D,"Build") -> 192 | C24: =COUNTIFS('Master Checklist'!$H:$H,$A24,'Master Checklist'!$D:$D,"Test") -> 0 | D24: =COUNTIF('Master Checklist'!$H:$H,$A24) -> 192 | E24: =COUNTIFS('Master Checklist'!$H:$H,$A24,'Master Checklist'!$Y:$Y,"Done") -> 0 | F24: =COUNTIFS('Master Checklist'!$H:$H,$A24,'Master Checklist'!$Y:$Y,"In progress") -> 0 | G24: =COUNTIFS('Master Checklist'!$H:$H,$A24,'Master Checklist'!$Y:$Y,"Blocked") -> 0 | H24: =IF(D24=0,0,E24/D24) -> 0 | I24: =COUNTIFS('Master Checklist'!$H:$H,$A24,'Master Checklist'!$L:$L,"") -> 192 | J24: =SUMIF('Master Checklist'!$H:$H,$A24,'Master Checklist'!$M:$M) -> 0
A25: QA Guild | B25: =COUNTIFS('Master Checklist'!$H:$H,$A25,'Master Checklist'!$D:$D,"Build") -> 0 | C25: =COUNTIFS('Master Checklist'!$H:$H,$A25,'Master Checklist'!$D:$D,"Test") -> 78 | D25: =COUNTIF('Master Checklist'!$H:$H,$A25) -> 78 | E25: =COUNTIFS('Master Checklist'!$H:$H,$A25,'Master Checklist'!$Y:$Y,"Done") -> 0 | F25: =COUNTIFS('Master Checklist'!$H:$H,$A25,'Master Checklist'!$Y:$Y,"In progress") -> 0 | G25: =COUNTIFS('Master Checklist'!$H:$H,$A25,'Master Checklist'!$Y:$Y,"Blocked") -> 0 | H25: =IF(D25=0,0,E25/D25) -> 0 | I25: =COUNTIFS('Master Checklist'!$H:$H,$A25,'Master Checklist'!$L:$L,"") -> 78 | J25: =SUMIF('Master Checklist'!$H:$H,$A25,'Master Checklist'!$M:$M) -> 0
A26: TOTAL | B26: =SUM(B17:B25) -> 1795 | C26: =SUM(C17:C25) -> 325 | D26: =SUM(D17:D25) -> 2120 | E26: =SUM(E17:E25) -> 0 | F26: =SUM(F17:F25) -> 0 | G26: =SUM(G17:G25) -> 0 | H26: =IF(D26=0,0,E26/D26) -> 0 | I26: =SUM(I17:I25) -> 2120 | J26: =SUM(J17:J25) -> 0
A28: Progress by stage (live)
A29: Stage | B29: Scope | C29: Build | D29: Test | E29: Total | F29: Done | G29: % done | H29: P0 open
A30: 0 | B30: Stage 0 — Contracts, schemas & decisions | C30: =COUNTIFS('Master Checklist'!$O:$O,$A30,'Master Checklist'!$D:$D,"Build") -> 292 | D30: =COUNTIFS('Master Checklist'!$O:$O,$A30,'Master Checklist'!$D:$D,"Test") -> 0 | E30: =COUNTIF('Master Checklist'!$O:$O,$A30) -> 292 | F30: =COUNTIFS('Master Checklist'!$O:$O,$A30,'Master Checklist'!$Y:$Y,"Done") -> 0 | G30: =IF(E30=0,0,F30/E30) -> 0 | H30: =COUNTIFS('Master Checklist'!$O:$O,$A30,'Master Checklist'!$E:$E,"P0",'Master Checklist'!$Y:$Y,"<>Done") -> 25
A31: 1 | B31: Stage 1 — Slice A validation | C31: =COUNTIFS('Master Checklist'!$O:$O,$A31,'Master Checklist'!$D:$D,"Build") -> 367 | D31: =COUNTIFS('Master Checklist'!$O:$O,$A31,'Master Checklist'!$D:$D,"Test") -> 131 | E31: =COUNTIF('Master Checklist'!$O:$O,$A31) -> 498 | F31: =COUNTIFS('Master Checklist'!$O:$O,$A31,'Master Checklist'!$Y:$Y,"Done") -> 0 | G31: =IF(E31=0,0,F31/E31) -> 0 | H31: =COUNTIFS('Master Checklist'!$O:$O,$A31,'Master Checklist'!$E:$E,"P0",'Master Checklist'!$Y:$Y,"<>Done") -> 13
A32: 2 | B32: Stage 2 — Content & competency | C32: =COUNTIFS('Master Checklist'!$O:$O,$A32,'Master Checklist'!$D:$D,"Build") -> 438 | D32: =COUNTIFS('Master Checklist'!$O:$O,$A32,'Master Checklist'!$D:$D,"Test") -> 58 | E32: =COUNTIF('Master Checklist'!$O:$O,$A32) -> 496 | F32: =COUNTIFS('Master Checklist'!$O:$O,$A32,'Master Checklist'!$Y:$Y,"Done") -> 0 | G32: =IF(E32=0,0,F32/E32) -> 0 | H32: =COUNTIFS('Master Checklist'!$O:$O,$A32,'Master Checklist'!$E:$E,"P0",'Master Checklist'!$Y:$Y,"<>Done") -> 6
A33: 3 | B33: Stage 3 — AI & field slices | C33: =COUNTIFS('Master Checklist'!$O:$O,$A33,'Master Checklist'!$D:$D,"Build") -> 428 | D33: =COUNTIFS('Master Checklist'!$O:$O,$A33,'Master Checklist'!$D:$D,"Test") -> 85 | E33: =COUNTIF('Master Checklist'!$O:$O,$A33) -> 513 | F33: =COUNTIFS('Master Checklist'!$O:$O,$A33,'Master Checklist'!$Y:$Y,"Done") -> 0 | G33: =IF(E33=0,0,F33/E33) -> 0 | H33: =COUNTIFS('Master Checklist'!$O:$O,$A33,'Master Checklist'!$E:$E,"P0",'Master Checklist'!$Y:$Y,"<>Done") -> 6
A34: 4 | B34: Stage 4 — Controlled pilot | C34: =COUNTIFS('Master Checklist'!$O:$O,$A34,'Master Checklist'!$D:$D,"Build") -> 173 | D34: =COUNTIFS('Master Checklist'!$O:$O,$A34,'Master Checklist'!$D:$D,"Test") -> 39 | E34: =COUNTIF('Master Checklist'!$O:$O,$A34) -> 212 | F34: =COUNTIFS('Master Checklist'!$O:$O,$A34,'Master Checklist'!$Y:$Y,"Done") -> 0 | G34: =IF(E34=0,0,F34/E34) -> 0 | H34: =COUNTIFS('Master Checklist'!$O:$O,$A34,'Master Checklist'!$E:$E,"P0",'Master Checklist'!$Y:$Y,"<>Done") -> 0
A35: 5 | B35: Stage 5 — Production & scale | C35: =COUNTIFS('Master Checklist'!$O:$O,$A35,'Master Checklist'!$D:$D,"Build") -> 97 | D35: =COUNTIFS('Master Checklist'!$O:$O,$A35,'Master Checklist'!$D:$D,"Test") -> 12 | E35: =COUNTIF('Master Checklist'!$O:$O,$A35) -> 109 | F35: =COUNTIFS('Master Checklist'!$O:$O,$A35,'Master Checklist'!$Y:$Y,"Done") -> 0 | G35: =IF(E35=0,0,F35/E35) -> 0 | H35: =COUNTIFS('Master Checklist'!$O:$O,$A35,'Master Checklist'!$E:$E,"P0",'Master Checklist'!$Y:$Y,"<>Done") -> 0

Sheet Product Index
A1: Product / Deliverable Index — 30 client deliverables + 13 enabling products
A2: Renamed products are marked. Yellow = assign owners. Counts are live.
A4: ProductID | B4: Product / deliverable | C4: Type | D4: Primary squad | E4: Modules | F4: Product owner | G4: Tech lead | H4: QA lead | I4: Build | J4: Test | K4: Total | L4: Stage span | M4: Done | N4: % done | O4: Blocked | P4: Renamed in v3
A5: D01 | B5: AI SME Chatbot — Learner-Facing | C5: Client deliverable | D5: SQ5 AI & Assessment | E5: M15, M26 | I5: =COUNTIFS('Master Checklist'!$B:$B,$A5,'Master Checklist'!$D:$D,"Build") -> 89 | J5: =COUNTIFS('Master Checklist'!$B:$B,$A5,'Master Checklist'!$D:$D,"Test") -> 14 | K5: =COUNTIF('Master Checklist'!$B:$B,$A5) -> 103 | L5: Stage 0–3 | M5: =COUNTIFS('Master Checklist'!$B:$B,$A5,'Master Checklist'!$Y:$Y,"Done") -> 0 | N5: =IF(K5=0,0,M5/K5) -> 0 | O5: =COUNTIFS('Master Checklist'!$B:$B,$A5,'Master Checklist'!$Y:$Y,"Blocked") -> 0
A6: D02 | B6: AI Assessment Tools & Test Banks + Auto Grader | C6: Client deliverable | D6: SQ5 AI & Assessment | E6: M8, M27 | I6: =COUNTIFS('Master Checklist'!$B:$B,$A6,'Master Checklist'!$D:$D,"Build") -> 84 | J6: =COUNTIFS('Master Checklist'!$B:$B,$A6,'Master Checklist'!$D:$D,"Test") -> 14 | K6: =COUNTIF('Master Checklist'!$B:$B,$A6) -> 98 | L6: Stage 0–3 | M6: =COUNTIFS('Master Checklist'!$B:$B,$A6,'Master Checklist'!$Y:$Y,"Done") -> 0 | N6: =IF(K6=0,0,M6/K6) -> 0 | O6: =COUNTIFS('Master Checklist'!$B:$B,$A6,'Master Checklist'!$Y:$Y,"Blocked") -> 0
A7: D03 | B7: Security Accreditation & Authorisation to Operate — Initiation | C7: Client deliverable | D7: SQ8 Program & Governance | E7: P1, SVC | I7: =COUNTIFS('Master Checklist'!$B:$B,$A7,'Master Checklist'!$D:$D,"Build") -> 17 | J7: =COUNTIFS('Master Checklist'!$B:$B,$A7,'Master Checklist'!$D:$D,"Test") -> 0 | K7: =COUNTIF('Master Checklist'!$B:$B,$A7) -> 17 | L7: Stage 0–1 | M7: =COUNTIFS('Master Checklist'!$B:$B,$A7,'Master Checklist'!$Y:$Y,"Done") -> 0 | N7: =IF(K7=0,0,M7/K7) -> 0 | O7: =COUNTIFS('Master Checklist'!$B:$B,$A7,'Master Checklist'!$Y:$Y,"Blocked") -> 0 | P7: was: ATO Initiation — AFGSC
A8: D04 | B8: Pedagogy Design Review Protocol | C8: Client deliverable | D8: SQ6 Content & Authoring | E8: P2 | I8: =COUNTIFS('Master Checklist'!$B:$B,$A8,'Master Checklist'!$D:$D,"Build") -> 13 | J8: =COUNTIFS('Master Checklist'!$B:$B,$A8,'Master Checklist'!$D:$D,"Test") -> 0 | K8: =COUNTIF('Master Checklist'!$B:$B,$A8) -> 13 | L8: Stage 0–4 | M8: =COUNTIFS('Master Checklist'!$B:$B,$A8,'Master Checklist'!$Y:$Y,"Done") -> 0 | N8: =IF(K8=0,0,M8/K8) -> 0 | O8: =COUNTIFS('Master Checklist'!$B:$B,$A8,'Master Checklist'!$Y:$Y,"Blocked") -> 0
A9: D05 | B9: TLA CMM Level 2 — Microservices | C9: Client deliverable | D9: SQ4 TLA & Federation | E9: M21 | I9: =COUNTIFS('Master Checklist'!$B:$B,$A9,'Master Checklist'!$D:$D,"Build") -> 8 | J9: =COUNTIFS('Master Checklist'!$B:$B,$A9,'Master Checklist'!$D:$D,"Test") -> 5 | K9: =COUNTIF('Master Checklist'!$B:$B,$A9) -> 13 | L9: Stage 1–5 | M9: =COUNTIFS('Master Checklist'!$B:$B,$A9,'Master Checklist'!$Y:$Y,"Done") -> 0 | N9: =IF(K9=0,0,M9/K9) -> 0 | O9: =COUNTIFS('Master Checklist'!$B:$B,$A9,'Master Checklist'!$Y:$Y,"Blocked") -> 0
A10: D06 | B10: TLA Experience-Index (ELRR) | C10: Client deliverable | D10: SQ4 TLA & Federation | E10: M17 | I10: =COUNTIFS('Master Checklist'!$B:$B,$A10,'Master Checklist'!$D:$D,"Build") -> 29 | J10: =COUNTIFS('Master Checklist'!$B:$B,$A10,'Master Checklist'!$D:$D,"Test") -> 7 | K10: =COUNTIF('Master Checklist'!$B:$B,$A10) -> 36 | L10: Stage 0–3 | M10: =COUNTIFS('Master Checklist'!$B:$B,$A10,'Master Checklist'!$Y:$Y,"Done") -> 0 | N10: =IF(K10=0,0,M10/K10) -> 0 | O10: =COUNTIFS('Master Checklist'!$B:$B,$A10,'Master Checklist'!$Y:$Y,"Blocked") -> 0
A11: D07 | B11: TLA Course Catalogue (ECC) | C11: Client deliverable | D11: SQ4 TLA & Federation | E11: M18 | I11: =COUNTIFS('Master Checklist'!$B:$B,$A11,'Master Checklist'!$D:$D,"Build") -> 26 | J11: =COUNTIFS('Master Checklist'!$B:$B,$A11,'Master Checklist'!$D:$D,"Test") -> 6 | K11: =COUNTIF('Master Checklist'!$B:$B,$A11) -> 32 | L11: Stage 0–2 | M11: =COUNTIFS('Master Checklist'!$B:$B,$A11,'Master Checklist'!$Y:$Y,"Done") -> 0 | N11: =IF(K11=0,0,M11/K11) -> 0 | O11: =COUNTIFS('Master Checklist'!$B:$B,$A11,'Master Checklist'!$Y:$Y,"Blocked") -> 0
A12: D08 | B12: TLA Competency-Registry | C12: Client deliverable | D12: SQ4 TLA & Federation | E12: M19 | I12: =COUNTIFS('Master Checklist'!$B:$B,$A12,'Master Checklist'!$D:$D,"Build") -> 55 | J12: =COUNTIFS('Master Checklist'!$B:$B,$A12,'Master Checklist'!$D:$D,"Test") -> 7 | K12: =COUNTIF('Master Checklist'!$B:$B,$A12) -> 62 | L12: Stage 0–2 | M12: =COUNTIFS('Master Checklist'!$B:$B,$A12,'Master Checklist'!$Y:$Y,"Done") -> 0 | N12: =IF(K12=0,0,M12/K12) -> 0 | O12: =COUNTIFS('Master Checklist'!$B:$B,$A12,'Master Checklist'!$Y:$Y,"Blocked") -> 0
A13: D09 | B13: TLA CMM Level 3 | C13: Client deliverable | D13: SQ4 TLA & Federation | E13: M21 | I13: =COUNTIFS('Master Checklist'!$B:$B,$A13,'Master Checklist'!$D:$D,"Build") -> 4 | J13: =COUNTIFS('Master Checklist'!$B:$B,$A13,'Master Checklist'!$D:$D,"Test") -> 1 | K13: =COUNTIF('Master Checklist'!$B:$B,$A13) -> 5 | L13: Stage 4–5 | M13: =COUNTIFS('Master Checklist'!$B:$B,$A13,'Master Checklist'!$Y:$Y,"Done") -> 0 | N13: =IF(K13=0,0,M13/K13) -> 0 | O13: =COUNTIFS('Master Checklist'!$B:$B,$A13,'Master Checklist'!$Y:$Y,"Blocked") -> 0
A14: D10 | B14: PDFs & Technical Manuals Integration — Live TO Connection | C14: Client deliverable | D14: SQ6 Content & Authoring | E14: M25 | I14: =COUNTIFS('Master Checklist'!$B:$B,$A14,'Master Checklist'!$D:$D,"Build") -> 26 | J14: =COUNTIFS('Master Checklist'!$B:$B,$A14,'Master Checklist'!$D:$D,"Test") -> 6 | K14: =COUNTIF('Master Checklist'!$B:$B,$A14) -> 32 | L14: Stage 0–3 | M14: =COUNTIFS('Master Checklist'!$B:$B,$A14,'Master Checklist'!$Y:$Y,"Done") -> 0 | N14: =IF(K14=0,0,M14/K14) -> 0 | O14: =COUNTIFS('Master Checklist'!$B:$B,$A14,'Master Checklist'!$Y:$Y,"Blocked") -> 0
A15: D11 | B15: DCT — Content Authoring & Lesson Planner | C15: Client deliverable | D15: SQ6 Content & Authoring | E15: M22 | I15: =COUNTIFS('Master Checklist'!$B:$B,$A15,'Master Checklist'!$D:$D,"Build") -> 38 | J15: =COUNTIFS('Master Checklist'!$B:$B,$A15,'Master Checklist'!$D:$D,"Test") -> 6 | K15: =COUNTIF('Master Checklist'!$B:$B,$A15) -> 44 | L15: Stage 0–2 | M15: =COUNTIFS('Master Checklist'!$B:$B,$A15,'Master Checklist'!$Y:$Y,"Done") -> 0 | N15: =IF(K15=0,0,M15/K15) -> 0 | O15: =COUNTIFS('Master Checklist'!$B:$B,$A15,'Master Checklist'!$Y:$Y,"Blocked") -> 0
A16: D12 | B16: Interactive eBooks — Technical Manuals Digitization | C16: Client deliverable | D16: SQ6 Content & Authoring | E16: M9, M24, SVC | I16: =COUNTIFS('Master Checklist'!$B:$B,$A16,'Master Checklist'!$D:$D,"Build") -> 62 | J16: =COUNTIFS('Master Checklist'!$B:$B,$A16,'Master Checklist'!$D:$D,"Test") -> 14 | K16: =COUNTIF('Master Checklist'!$B:$B,$A16) -> 76 | L16: Stage 0–3 | M16: =COUNTIFS('Master Checklist'!$B:$B,$A16,'Master Checklist'!$Y:$Y,"Done") -> 0 | N16: =IF(K16=0,0,M16/K16) -> 0 | O16: =COUNTIFS('Master Checklist'!$B:$B,$A16,'Master Checklist'!$Y:$Y,"Blocked") -> 0
A17: D13 | B17: SME Chatbot — Content Authoring Support | C17: Client deliverable | D17: SQ5 AI & Assessment | E17: M23 | I17: =COUNTIFS('Master Checklist'!$B:$B,$A17,'Master Checklist'!$D:$D,"Build") -> 14 | J17: =COUNTIFS('Master Checklist'!$B:$B,$A17,'Master Checklist'!$D:$D,"Test") -> 6 | K17: =COUNTIF('Master Checklist'!$B:$B,$A17) -> 20 | L17: Stage 0–3 | M17: =COUNTIFS('Master Checklist'!$B:$B,$A17,'Master Checklist'!$Y:$Y,"Done") -> 0 | N17: =IF(K17=0,0,M17/K17) -> 0 | O17: =COUNTIFS('Master Checklist'!$B:$B,$A17,'Master Checklist'!$Y:$Y,"Blocked") -> 0
A18: D14 | B18: Personalized Learning Engine — Core | C18: Client deliverable | D18: SQ2 Learning Tools | E18: M11, M13, M28 | I18: =COUNTIFS('Master Checklist'!$B:$B,$A18,'Master Checklist'!$D:$D,"Build") -> 101 | J18: =COUNTIFS('Master Checklist'!$B:$B,$A18,'Master Checklist'!$D:$D,"Test") -> 20 | K18: =COUNTIF('Master Checklist'!$B:$B,$A18) -> 121 | L18: Stage 0–4 | M18: =COUNTIFS('Master Checklist'!$B:$B,$A18,'Master Checklist'!$Y:$Y,"Done") -> 0 | N18: =IF(K18=0,0,M18/K18) -> 0 | O18: =COUNTIFS('Master Checklist'!$B:$B,$A18,'Master Checklist'!$Y:$Y,"Blocked") -> 0
A19: D15 | B19: Competency Assessment Tool | C19: Client deliverable | D19: SQ2 Learning Tools | E19: M12, M29 | I19: =COUNTIFS('Master Checklist'!$B:$B,$A19,'Master Checklist'!$D:$D,"Build") -> 53 | J19: =COUNTIFS('Master Checklist'!$B:$B,$A19,'Master Checklist'!$D:$D,"Test") -> 13 | K19: =COUNTIF('Master Checklist'!$B:$B,$A19) -> 66 | L19: Stage 0–3 | M19: =COUNTIFS('Master Checklist'!$B:$B,$A19,'Master Checklist'!$Y:$Y,"Done") -> 0 | N19: =IF(K19=0,0,M19/K19) -> 0 | O19: =COUNTIFS('Master Checklist'!$B:$B,$A19,'Master Checklist'!$Y:$Y,"Blocked") -> 0
A20: D16 | B20: TLA Profile Management — Initial Deployment | C20: Client deliverable | D20: SQ4 TLA & Federation | E20: M20 | I20: =COUNTIFS('Master Checklist'!$B:$B,$A20,'Master Checklist'!$D:$D,"Build") -> 23 | J20: =COUNTIFS('Master Checklist'!$B:$B,$A20,'Master Checklist'!$D:$D,"Test") -> 6 | K20: =COUNTIF('Master Checklist'!$B:$B,$A20) -> 29 | L20: Stage 2–3 | M20: =COUNTIFS('Master Checklist'!$B:$B,$A20,'Master Checklist'!$Y:$Y,"Done") -> 0 | N20: =IF(K20=0,0,M20/K20) -> 0 | O20: =COUNTIFS('Master Checklist'!$B:$B,$A20,'Master Checklist'!$Y:$Y,"Blocked") -> 0
A21: D17 | B21: Cross-Organisation / Cross-Command Data Pipeline | C21: Client deliverable | D21: SQ4 TLA & Federation | E21: M31 | I21: =COUNTIFS('Master Checklist'!$B:$B,$A21,'Master Checklist'!$D:$D,"Build") -> 78 | J21: =COUNTIFS('Master Checklist'!$B:$B,$A21,'Master Checklist'!$D:$D,"Test") -> 7 | K21: =COUNTIF('Master Checklist'!$B:$B,$A21) -> 85 | L21: Stage 0–5 | M21: =COUNTIFS('Master Checklist'!$B:$B,$A21,'Master Checklist'!$Y:$Y,"Done") -> 0 | N21: =IF(K21=0,0,M21/K21) -> 0 | O21: =COUNTIFS('Master Checklist'!$B:$B,$A21,'Master Checklist'!$Y:$Y,"Blocked") -> 0 | P21: was: Cross-Command Data Pipeline
A22: D18 | B22: Analytics Dashboard Suite (incl. TLA) — All Roles | C22: Client deliverable | D22: SQ3 Data & Analytics | E22: M6, M10, M30 | I22: =COUNTIFS('Master Checklist'!$B:$B,$A22,'Master Checklist'!$D:$D,"Build") -> 201 | J22: =COUNTIFS('Master Checklist'!$B:$B,$A22,'Master Checklist'!$D:$D,"Test") -> 19 | K22: =COUNTIF('Master Checklist'!$B:$B,$A22) -> 220 | L22: Stage 0–5 | M22: =COUNTIFS('Master Checklist'!$B:$B,$A22,'Master Checklist'!$Y:$Y,"Done") -> 0 | N22: =IF(K22=0,0,M22/K22) -> 0 | O22: =COUNTIFS('Master Checklist'!$B:$B,$A22,'Master Checklist'!$Y:$Y,"Blocked") -> 0
A23: D19 | B23: XR Store App — Android & Windows | C23: Client deliverable | D23: SQ7 Field & Immersive | E23: M16, M32, SVC | I23: =COUNTIFS('Master Checklist'!$B:$B,$A23,'Master Checklist'!$D:$D,"Build") -> 69 | J23: =COUNTIFS('Master Checklist'!$B:$B,$A23,'Master Checklist'!$D:$D,"Test") -> 12 | K23: =COUNTIF('Master Checklist'!$B:$B,$A23) -> 81 | L23: Stage 0–4 | M23: =COUNTIFS('Master Checklist'!$B:$B,$A23,'Master Checklist'!$Y:$Y,"Done") -> 0 | N23: =IF(K23=0,0,M23/K23) -> 0 | O23: =COUNTIFS('Master Checklist'!$B:$B,$A23,'Master Checklist'!$Y:$Y,"Blocked") -> 0
A24: D20 | B24: Immersive Lab — Reference Site (India) | C24: Client deliverable | D24: SQ7 Field & Immersive | E24: M33, SVC | I24: =COUNTIFS('Master Checklist'!$B:$B,$A24,'Master Checklist'!$D:$D,"Build") -> 59 | J24: =COUNTIFS('Master Checklist'!$B:$B,$A24,'Master Checklist'!$D:$D,"Test") -> 7 | K24: =COUNTIF('Master Checklist'!$B:$B,$A24) -> 66 | L24: Stage 3–4 | M24: =COUNTIFS('Master Checklist'!$B:$B,$A24,'Master Checklist'!$Y:$Y,"Done") -> 0 | N24: =IF(K24=0,0,M24/K24) -> 0 | O24: =COUNTIFS('Master Checklist'!$B:$B,$A24,'Master Checklist'!$Y:$Y,"Blocked") -> 0 | P24: was: Hardware Immersive Labs — Site A (Barksdale AFB)
A25: D21 | B25: Immersive Lab — Replication Site (India) | C25: Client deliverable | D25: SQ7 Field & Immersive | E25: M34 | I25: =COUNTIFS('Master Checklist'!$B:$B,$A25,'Master Checklist'!$D:$D,"Build") -> 22 | J25: =COUNTIFS('Master Checklist'!$B:$B,$A25,'Master Checklist'!$D:$D,"Test") -> 6 | K25: =COUNTIF('Master Checklist'!$B:$B,$A25) -> 28 | L25: Stage 5–5 | M25: =COUNTIFS('Master Checklist'!$B:$B,$A25,'Master Checklist'!$Y:$Y,"Done") -> 0 | N25: =IF(K25=0,0,M25/K25) -> 0 | O25: =COUNTIFS('Master Checklist'!$B:$B,$A25,'Master Checklist'!$Y:$Y,"Blocked") -> 0 | P25: was: Hardware Immersive Labs — Site B (Minot AFB)
A26: D22 | B26: AI/ML Procedural Walkthrough Engine | C26: Client deliverable | D26: SQ7 Field & Immersive | E26: M35 | I26: =COUNTIFS('Master Checklist'!$B:$B,$A26,'Master Checklist'!$D:$D,"Build") -> 27 | J26: =COUNTIFS('Master Checklist'!$B:$B,$A26,'Master Checklist'!$D:$D,"Test") -> 7 | K26: =COUNTIF('Master Checklist'!$B:$B,$A26) -> 34 | L26: Stage 0–4 | M26: =COUNTIFS('Master Checklist'!$B:$B,$A26,'Master Checklist'!$Y:$Y,"Done") -> 0 | N26: =IF(K26=0,0,M26/K26) -> 0 | O26: =COUNTIFS('Master Checklist'!$B:$B,$A26,'Master Checklist'!$Y:$Y,"Blocked") -> 0
A27: D23 | B27: Difference Training Application | C27: Client deliverable | D27: SQ2 Learning Tools | E27: M14, M36 | I27: =COUNTIFS('Master Checklist'!$B:$B,$A27,'Master Checklist'!$D:$D,"Build") -> 49 | J27: =COUNTIFS('Master Checklist'!$B:$B,$A27,'Master Checklist'!$D:$D,"Test") -> 12 | K27: =COUNTIF('Master Checklist'!$B:$B,$A27) -> 61 | L27: Stage 0–4 | M27: =COUNTIFS('Master Checklist'!$B:$B,$A27,'Master Checklist'!$Y:$Y,"Done") -> 0 | N27: =IF(K27=0,0,M27/K27) -> 0 | O27: =COUNTIFS('Master Checklist'!$B:$B,$A27,'Master Checklist'!$Y:$Y,"Blocked") -> 0
A28: D24 | B28: Microlearning Mobile Application | C28: Client deliverable | D28: SQ7 Field & Immersive | E28: M37, SVC | I28: =COUNTIFS('Master Checklist'!$B:$B,$A28,'Master Checklist'!$D:$D,"Build") -> 18 | J28: =COUNTIFS('Master Checklist'!$B:$B,$A28,'Master Checklist'!$D:$D,"Test") -> 6 | K28: =COUNTIF('Master Checklist'!$B:$B,$A28) -> 24 | L28: Stage 2–4 | M28: =COUNTIFS('Master Checklist'!$B:$B,$A28,'Master Checklist'!$Y:$Y,"Done") -> 0 | N28: =IF(K28=0,0,M28/K28) -> 0 | O28: =COUNTIFS('Master Checklist'!$B:$B,$A28,'Master Checklist'!$Y:$Y,"Blocked") -> 0
A29: D25 | B29: Accelerate Upgrade Readiness Measurement Plan | C29: Client deliverable | D29: SQ8 Program & Governance | E29: P3 | I29: =COUNTIFS('Master Checklist'!$B:$B,$A29,'Master Checklist'!$D:$D,"Build") -> 21 | J29: =COUNTIFS('Master Checklist'!$B:$B,$A29,'Master Checklist'!$D:$D,"Test") -> 0 | K29: =COUNTIF('Master Checklist'!$B:$B,$A29) -> 21 | L29: Stage 0–5 | M29: =COUNTIFS('Master Checklist'!$B:$B,$A29,'Master Checklist'!$Y:$Y,"Done") -> 0 | N29: =IF(K29=0,0,M29/K29) -> 0 | O29: =COUNTIFS('Master Checklist'!$B:$B,$A29,'Master Checklist'!$Y:$Y,"Blocked") -> 0
A30: D26 | B30: Measure of Operational Effectiveness (MOE) AR Application | C30: Client deliverable | D30: SQ7 Field & Immersive | E30: M38 | I30: =COUNTIFS('Master Checklist'!$B:$B,$A30,'Master Checklist'!$D:$D,"Build") -> 16 | J30: =COUNTIFS('Master Checklist'!$B:$B,$A30,'Master Checklist'!$D:$D,"Test") -> 6 | K30: =COUNTIF('Master Checklist'!$B:$B,$A30) -> 22 | L30: Stage 3–4 | M30: =COUNTIFS('Master Checklist'!$B:$B,$A30,'Master Checklist'!$Y:$Y,"Done") -> 0 | N30: =IF(K30=0,0,M30/K30) -> 0 | O30: =COUNTIFS('Master Checklist'!$B:$B,$A30,'Master Checklist'!$Y:$Y,"Blocked") -> 0
A31: D27 | B31: Train the Trainer — Embedded SME Service | C31: Client deliverable | D31: SQ8 Program & Governance | E31: P4 | I31: =COUNTIFS('Master Checklist'!$B:$B,$A31,'Master Checklist'!$D:$D,"Build") -> 11 | J31: =COUNTIFS('Master Checklist'!$B:$B,$A31,'Master Checklist'!$D:$D,"Test") -> 0 | K31: =COUNTIF('Master Checklist'!$B:$B,$A31) -> 11 | L31: Stage 2–5 | M31: =COUNTIFS('Master Checklist'!$B:$B,$A31,'Master Checklist'!$Y:$Y,"Done") -> 0 | N31: =IF(K31=0,0,M31/K31) -> 0 | O31: =COUNTIFS('Master Checklist'!$B:$B,$A31,'Master Checklist'!$Y:$Y,"Blocked") -> 0
A32: D28 | B32: TLA CMM Level 5 — Enterprise Competency Mapping | C32: Client deliverable | D32: SQ4 TLA & Federation | E32: M21 | I32: =COUNTIFS('Master Checklist'!$B:$B,$A32,'Master Checklist'!$D:$D,"Build") -> 2 | J32: =COUNTIFS('Master Checklist'!$B:$B,$A32,'Master Checklist'!$D:$D,"Test") -> 0 | K32: =COUNTIF('Master Checklist'!$B:$B,$A32) -> 2 | L32: Stage 1–5 | M32: =COUNTIFS('Master Checklist'!$B:$B,$A32,'Master Checklist'!$Y:$Y,"Done") -> 0 | N32: =IF(K32=0,0,M32/K32) -> 0 | O32: =COUNTIFS('Master Checklist'!$B:$B,$A32,'Master Checklist'!$Y:$Y,"Blocked") -> 0
A33: D29 | B33: Full Multiverse Platform Integration & Acceptance | C33: Client deliverable | D33: SQ8 Program & Governance | E33: P5 | I33: =COUNTIFS('Master Checklist'!$B:$B,$A33,'Master Checklist'!$D:$D,"Build") -> 22 | J33: =COUNTIFS('Master Checklist'!$B:$B,$A33,'Master Checklist'!$D:$D,"Test") -> 0 | K33: =COUNTIF('Master Checklist'!$B:$B,$A33) -> 22 | L33: Stage 0–5 | M33: =COUNTIFS('Master Checklist'!$B:$B,$A33,'Master Checklist'!$Y:$Y,"Done") -> 0 | N33: =IF(K33=0,0,M33/K33) -> 0 | O33: =COUNTIFS('Master Checklist'!$B:$B,$A33,'Master Checklist'!$Y:$Y,"Blocked") -> 0
A34: D30 | B34: Final Report | C34: Client deliverable | D34: SQ8 Program & Governance | E34: P6 | I34: =COUNTIFS('Master Checklist'!$B:$B,$A34,'Master Checklist'!$D:$D,"Build") -> 10 | J34: =COUNTIFS('Master Checklist'!$B:$B,$A34,'Master Checklist'!$D:$D,"Test") -> 0 | K34: =COUNTIF('Master Checklist'!$B:$B,$A34) -> 10 | L34: Stage 1–5 | M34: =COUNTIFS('Master Checklist'!$B:$B,$A34,'Master Checklist'!$Y:$Y,"Done") -> 0 | N34: =IF(K34=0,0,M34/K34) -> 0 | O34: =COUNTIFS('Master Checklist'!$B:$B,$A34,'Master Checklist'!$Y:$Y,"Blocked") -> 0
A35: E01 | B35: Core Platform, Identity & Shared Services (enabler) | C35: Enabling platform | D35: SQ1 Platform Core | E35: M1, M4, SVC | I35: =COUNTIFS('Master Checklist'!$B:$B,$A35,'Master Checklist'!$D:$D,"Build") -> 143 | J35: =COUNTIFS('Master Checklist'!$B:$B,$A35,'Master Checklist'!$D:$D,"Test") -> 13 | K35: =COUNTIF('Master Checklist'!$B:$B,$A35) -> 156 | L35: Stage 0–3 | M35: =COUNTIFS('Master Checklist'!$B:$B,$A35,'Master Checklist'!$Y:$Y,"Done") -> 0 | N35: =IF(K35=0,0,M35/K35) -> 0 | O35: =COUNTIFS('Master Checklist'!$B:$B,$A35,'Master Checklist'!$Y:$Y,"Blocked") -> 0
A36: E02 | B36: Learning Records Spine — LRS + Learning-data API (enabler) | C36: Enabling platform | D36: SQ1 Platform Core | E36: M2, M3 | I36: =COUNTIFS('Master Checklist'!$B:$B,$A36,'Master Checklist'!$D:$D,"Build") -> 72 | J36: =COUNTIFS('Master Checklist'!$B:$B,$A36,'Master Checklist'!$D:$D,"Test") -> 14 | K36: =COUNTIF('Master Checklist'!$B:$B,$A36) -> 86 | L36: Stage 0–1 | M36: =COUNTIFS('Master Checklist'!$B:$B,$A36,'Master Checklist'!$Y:$Y,"Done") -> 0 | N36: =IF(K36=0,0,M36/K36) -> 0 | O36: =COUNTIFS('Master Checklist'!$B:$B,$A36,'Master Checklist'!$Y:$Y,"Blocked") -> 0
A37: E03 | B37: LMS & Course-Site Integration — LTI 1.3 (enabler) | C37: Enabling platform | D37: SQ2 Learning Tools | E37: M5, M7 | I37: =COUNTIFS('Master Checklist'!$B:$B,$A37,'Master Checklist'!$D:$D,"Build") -> 65 | J37: =COUNTIFS('Master Checklist'!$B:$B,$A37,'Master Checklist'!$D:$D,"Test") -> 13 | K37: =COUNTIF('Master Checklist'!$B:$B,$A37) -> 78 | L37: Stage 0–3 | M37: =COUNTIFS('Master Checklist'!$B:$B,$A37,'Master Checklist'!$Y:$Y,"Done") -> 0 | N37: =IF(K37=0,0,M37/K37) -> 0 | O37: =COUNTIFS('Master Checklist'!$B:$B,$A37,'Master Checklist'!$Y:$Y,"Blocked") -> 0
... A47: E13 | B47: Internal Enablement & Knowledge Continuity | C47: Enabling programme | D47: SQ8 Program & Governance | E47: SVC | I47: =COUNTIFS('Master Checklist'!$B:$B,$A47,'Master Checklist'!$D:$D,"Build") -> 12 | J47: =COUNTIFS('Master Checklist'!$B:$B,$A47,'Master Checklist'!$D:$D,"Test") -> 0 | K47: =COUNTIF('Master Checklist'!$B:$B,$A47) -> 12 | L47: Stage 1–5 | M47: =COUNTIFS('Master Checklist'!$B:$B,$A47,'Master Checklist'!$Y:$Y,"Done") -> 0 | N47: =IF(K47=0,0,M47/K47) -> 0 | O47: =COUNTIFS('Master Checklist'!$B:$B,$A47,'Master Checklist'!$Y:$Y,"Blocked") -> 0
B48: TOTAL | I48: =SUM(I5:I47) -> 1795 | J48: =SUM(J5:J47) -> 325 | K48: =SUM(K5:K47) -> 2120 | M48: =SUM(M5:M47) -> 0 | O48: =SUM(O5:O47) -> 0

Sheet Master Checklist
A1: ID | B1: ProductID | C1: Product | D1: WorkType | E1: Priority | F1: Category | G1: Module | H1: Squad | I1: OwnerRole | J1: TestTeam | K1: TestCaseID | L1: Assignee | M1: EstDays | N1: TargetSprint | O1: Stage | P1: Task | Q1: Subtask | R1: Item | S1: DependsOn | T1: Evidence | U1: EvidenceLink | V1: AcceptanceCriterion | W1: DeploymentClass | X1: SourceRef | Y1: Status | Z1: Waiver | AA1: LastUpdated | AB1: SeqFlag | AC1: Notes
A2: FND-01.1.01 | B2: E01 | C2: Core Platform, Identity & Shared Services (enabler) | D2: Build | E2: P1 | F2: FND | G2: M1 | H2: SQ1 Platform Core | I2: Platform Architect | J2: — | O2: 0 | P2: M1 identity contracts | Q2: Tenancy and token contract | R2: Tenancy decision record written (realm-per-tenant vs single realm with tenant claims) covering token contents, session behavior, admin tooling, and onboarding cost, and approved by architecture board | S2: - | T2: Signed decision record in decision register | V2: Decision record merged with named approver and date | W2: All | X2: Review D-M1 gap; MOD-008 | Y2: Not started
A3: FND-01.1.02 | B3: E01 | C3: Core Platform, Identity & Shared Services (enabler) | D3: Build | E3: P0 | F3: FND | G3: M1 | H3: SQ1 Platform Core | I3: Platform Architect | J3: — | O3: 0 | P3: M1 identity contracts | Q3: Tenancy and token contract | R3: Token claim schema defined (tenant ID, command ID, roles, audience, per-service scopes) and issued as versioned contract document | S3: FND-01.1.01 | T3: Claim schema v1 in contract repo | V3: Schema validates sample tokens for 3 personas plus 1 service account without ambiguity | W3: All | X3: Review G.4; HS-11 | Y3: Not started
A4: FND-01.1.03 | B4: E01 | C4: Core Platform, Identity & Shared Services (enabler) | D4: Build | E4: P1 | F4: FND | G4: M1 | H4: SQ1 Platform Core | I4: Platform Architect | J4: — | O4: 0 | P4: M1 identity contracts | Q4: Tenancy and token contract | R4: Token lifecycle policy documented: access/refresh lifetimes, revocation propagation SLA, signing-key rotation schedule, offline-device credential rules | S4: FND-01.1.02 | T4: Token lifecycle policy doc | V4: Policy states numeric lifetime, SLA, and rotation interval for every token type; approved | W4: All | X4: Review D-M1 token lifecycle gap | Y4: Not started
A5: FND-01.1.04 | B5: E01 | C5: Core Platform, Identity & Shared Services (enabler) | D5: Build | E5: P1 | F5: FND | G5: M1 | H5: SQ1 Platform Core | I5: Platform Architect | J5: — | O5: 0 | P5: M1 identity contracts | Q5: Tenancy and token contract | R5: Role precedence rule between Keycloak roles and LTI launch roles documented with M1 as owner and M7 as read-only consumer | S5: - | T5: Role precedence rule doc referenced by M7 spec | V5: Rule resolves the teacher-in-Moodle/student-in-Keycloak case deterministically; COR team acknowledged | W5: All | X5: Review D-M1 [CONTRADICTED] role truth | Y5: Not started
A6: FND-01.1.05 | B6: E01 | C6: Core Platform, Identity & Shared Services (enabler) | D6: Build | E6: P1 | F6: FND | G6: M1 | H6: SQ1 Platform Core | I6: Platform Architect | J6: — | O6: 0 | P6: M1 identity contracts | Q6: Tenancy and token contract | R6: Tenant-resolution contract defined for the shared middleware/library consumed by all modules (claim parsing, missing-claim rejection, audited denial format) | S6: FND-01.1.02 | T6: Tenant-resolution contract v1 | V6: Contract specifies behavior for present, missing, and malformed tenant claims; reject-by-default | W6: All | X6: MOD-008 | Y6: Not started
A7: FND-01.1.06 | B7: E01 | C7: Core Platform, Identity & Shared Services (enabler) | D7: Build | E7: P1 | F7: FND | G7: M1 | H7: SQ1 Platform Core | I7: Platform Architect | J7: — | O7: 0 | P7: M1 identity contracts | Q7: Tenancy and token contract | R7: Service-to-service authentication model defined: machine identity per module, client-credentials or mTLS, least-privilege scopes, no all-tenant service tokens | S7: FND-01.1.02 | T7: Service-auth model doc listing every Slice A service identity | V7: Every Slice A module has a named machine identity with an explicit scope list; zero wildcard-tenant scopes | W7: All | X7: R-sec-G (G.4 service auth absent) | Y7: Not started
A8: FND-01.2.01 | B8: E01 | C8: Core Platform, Identity & Shared Services (enabler) | D8: Build | E8: P0 | F8: FND | G8: M1 | H8: SQ1 Platform Core | I8: Platform Architect | J8: — | O8: 0 | P8: M1 identity contracts | Q8: Publication and conformance | R8: Identity contracts (token claims, tenant resolution, service auth) published to the contract registry with semver | S8: FND-01.1.02, FND-13.1.01 | T8: Registry entries with version tags | V8: All three contracts retrievable from registry at v1.0.0 | W8: All | X8: HS-11; PLAN M1 main-jobs | Y8: Not started
A9: FND-01.2.02 | B9: E01 | C9: Core Platform, Identity & Shared Services (enabler) | D9: Build | E9: P1 | F9: FND | G9: M1 | H9: SQ1 Platform Core | I9: QA Engineer | J9: — | O9: 0 | P9: M1 identity contracts | Q9: Publication and conformance | R9: Token conformance test suite written and green against a stub IdP in CI (valid, expired, missing tenant claim, wrong audience, revoked) | S9: FND-01.2.01 | T9: CI job run link | V9: All 5 case classes pass; suite blocks merge on failure | W9: All | X9: Stage 0 exit gate (Section T) | Y9: Not started
A10: FND-01.2.03 | B10: E01 | C10: Core Platform, Identity & Shared Services (enabler) | D10: Build | E10: P1 | F10: FND | G10: M1 | H10: SQ1 Platform Core | I10: QA Lead | J10: — | O10: 0 | P10: M1 identity contracts | Q10: Publication and conformance | R10: Exit-gate evidence bundle assembled and reviewed for M1 identity contracts task | S10: FND-01.2.02 | T10: Evidence bundle in program repo | V10: All task items evidenced; reviewer sign-off recorded | W10: All | X10: Brief mandatory lane | Y10: Not started
A11: FND-02.1.01 | B11: E01 | C11: Core Platform, Identity & Shared Services (enabler) | D11: Build | E11: P2 | F11: FND | G11: M1 | H11: SQ1 Platform Core | I11: DevSecOps Engineer | J11: — | O11: 1 | P11: Keycloak deployment | Q11: Realm and client provisioning | R11: Keycloak pinned version deployed via IaC with external PostgreSQL and HA replicas | S11: FND-01.1.01 | T11: IaC repo commit plus running environment | V11: Two Keycloak nodes serve logins; single-node kill causes no login failures in test | W11: All | X11: PLAN M1 main-jobs | Y11: Not started
A12: FND-02.1.02 | B12: E01 | C12: Core Platform, Identity & Shared Services (enabler) | D12: Build | E12: P2 | F12: FND | G12: M1 | H12: SQ1 Platform Core | I12: DevSecOps Engineer | J12: — | O12: 1 | P12: Keycloak deployment | Q12: Realm and client provisioning | R12: Tenant onboarding automation provisions a new tenant (realm or claims per decision record) in under 30 minutes | S12: FND-02.1.01 | T12: Automation script plus timed run log | V12: Fresh tenant provisioned end-to-end in one command in under 30 min | W12: All | X12: Review D-M1 exit criteria | Y12: Not started
A13: FND-02.1.03 | B13: E01 | C13: Core Platform, Identity & Shared Services (enabler) | D13: Build | E13: P2 | F13: FND | G13: M1 | H13: SQ1 Platform Core | I13: DevSecOps Engineer | J13: — | O13: 1 | P13: Keycloak deployment | Q13: Realm and client provisioning | R13: OIDC clients registered for M3, M5, M6, and M7 with per-client scopes and secrets stored in vault | S13: FND-02.1.01 | T13: Client inventory export | V13: Each client authenticates with only its declared scopes; secrets absent from git | W13: All | X13: PLAN M1 main-jobs | Y13: Not started
... A290: COR-14.3.02 | B290: D12 | C290: Interactive eBooks — Technical Manuals Digitization | D290: Build | E290: P2 | F290: COR | G290: M9 | H290: SQ2 Learning Tools | I290: QA Lead | J290: — | O290: 2 | P290: M9 data, security, operations, and handoff | Q290: Documentation | R290: Exit-gate evidence bundle assembled and reviewed for task COR-14 (M9 data, security, operations, and handoff) | S290: - | T290: Reviewed evidence bundle in program repository | V290: Bundle links evidence for every item in the task and review sign-off is recorded | W290: All | X290: LOOP 2 exit-gate rule | Y290: Not started
A291: SMT-01.1.01 | B291: D18 | C291: Analytics Dashboard Suite (incl. TLA) — All Roles | D291: Build | E291: P1 | F291: SMT | G291: M10 | H291: SQ2 Learning Tools | I291: Platform Architect | J291: — | O291: 0 | P291: M10 teacher-view layer on unified analytics | Q291: Scope and contracts | R291: M6/M10 merge responsibility matrix recorded: dashboard construction owned by ANA-05, M10 delivers the teacher-experience layer and embedding hooks only, with no duplicate aggregation logic | S291: ANA-05.1.01 | T291: Signed responsibility matrix | V291: Matrix assigns every dashboard and aggregation to exactly one owner and is approved by architecture board | W291: All | X291: Review D-M10 required-changes; MOD merge; K | Y291: Not started | AB291: REVIEW: depends on later-stage item
A292: SMT-01.1.02 | B292: D18 | C292: Analytics Dashboard Suite (incl. TLA) — All Roles | D292: Build | E292: P1 | F292: SMT | G292: M10 | H292: SQ2 Learning Tools | I292: Platform Architect | J292: — | O292: 0 | P292: M10 teacher-view layer on unified analytics | Q292: Scope and contracts | R292: Teacher-view freshness and performance SLO recorded: p95 at or below 2 s for a 2000-learner class at 500 concurrent teachers with data staleness displayed on every view | S292: SMT-01.1.01 | T292: SLO document in architecture repo | V292: SLO document approved with both numeric targets and the staleness-display requirement | W292: All | X292: Review D-M10 required-changes; Loop 10 | Y292: Not started
A293: SMT-01.1.03 | B293: D18 | C293: Analytics Dashboard Suite (incl. TLA) — All Roles | D293: Build | E293: P1 | F293: SMT | G293: M10 | H293: SQ2 Learning Tools | I293: Platform Architect | J293: — | O293: 0 | P293: M10 teacher-view layer on unified analytics | Q293: Scope and contracts | R293: Cache design document approved defining every cached number as strictly derived with source query, TTL, tenant-scoped key, and rebuild job so Redis loss is a latency event only | S293: SMT-01.1.01 | T293: Approved cache design doc | V293: Every planned cache entry lists all four attributes; no cached value lacks a rebuild path | W293: All | X293: Review D-M10 gap cache; R-027; LOOP 5 | Y293: Not started
A294: SMT-01.2.01 | B294: D18 | C294: Analytics Dashboard Suite (incl. TLA) — All Roles | D294: Build | E294: P2 | F294: SMT | G294: M10 | H294: SQ2 Learning Tools | I294: Frontend Engineer | J294: — | O294: 2 | P294: M10 teacher-view layer on unified analytics | Q294: Embedding hooks and teacher-specific views | R294: Teacher dashboard embedding implemented in course-site teacher views via M7 launch context resolving to ANA signed-embed URLs | S294: ANA-06.1.03, COR-01.1.01 | T294: Embed integration test through Moodle | V294: Teacher launch opens the ANA teacher pack inside the LMS with tenant scope from server-side JWT only | W294: All | X294: PLAN M10 main-jobs; ANA-06 | Y294: Not started
A295: SMT-01.2.02 | B295: D18 | C295: Analytics Dashboard Suite (incl. TLA) — All Roles | D295: Build | E295: P1 | F295: SMT | G295: M10 | H295: SQ2 Learning Tools | I295: Frontend Engineer | J295: — | O295: 2 | P295: M10 teacher-view layer on unified analytics | Q295: Embedding hooks and teacher-specific views | R295: At-risk drill-down handoff implemented: teacher view links each flag to the M11 explanation panel showing factors, confidence, and data-completeness | S295: SMT-03.2.04, ANA-05.1.05 | T295: Drill-down E2E test | V295: Clicking a fixture flag renders factors, confidence, and completeness values matching engine output | W295: All | X295: PLAN M10; Review D-M11; Scenario 5 | Y295: Not started
A296: SMT-01.2.03 | B296: D18 | C296: Analytics Dashboard Suite (incl. TLA) — All Roles | D296: Build | E296: P1 | F296: SMT | G296: M10 | H296: SQ2 Learning Tools | I296: Frontend Engineer | J296: — | O296: 2 | P296: M10 teacher-view layer on unified analytics | Q296: Embedding hooks and teacher-specific views | R296: Undelivered-grades panel embedded in the teacher view fed by the M7 reconciliation feed | S296: COR-03.2.02 | T296: Panel E2E test | V296: Seeded failed passback appears in the teacher panel within 5 minutes | W296: All | X296: Scenario 3 required-change c | Y296: Not started
A297: SMT-01.2.04 | B297: D18 | C297: Analytics Dashboard Suite (incl. TLA) — All Roles | D297: Build | E297: P2 | F297: SMT | G297: M10 | H297: SQ2 Learning Tools | I297: Frontend Engineer | J297: — | O297: 2 | P297: M10 teacher-view layer on unified analytics | Q297: Embedding hooks and teacher-specific views | R297: Teacher export hook implemented delegating to the ANA governed export path with no separate M10 export pipeline | S297: SMT-01.2.01 | T297: Export hook code review plus test | V297: Export produced via ANA path with export audit log entry; no M10-local export code exists | W297: All | X297: PLAN M10 main-jobs; ANA-07 | Y297: Not started
A298: SMT-01.3.01 | B298: D18 | C298: Analytics Dashboard Suite (incl. TLA) — All Roles | D298: Build | E298: P2 | F298: SMT | G298: M10 | H298: SQ2 Learning Tools | I298: Backend Engineer | J298: — | O298: 2 | P298: M10 teacher-view layer on unified analytics | Q298: Cache build and validation | R298: Tenant-scoped cache keys implemented for all teacher-view cached numbers per the cache design | S298: SMT-01.1.03 | T298: Cache key implementation plus review | V298: Every cache key contains the tenant ID segment; static analysis finds zero unscoped keys | W298: All | X298: LOOP 8 cache tenancy; Review D-M10 | Y298: Not started
A299: SMT-01.3.02 | B299: D18 | C299: Analytics Dashboard Suite (incl. TLA) — All Roles | D299: Build | E299: P1 | F299: SMT | G299: M10 | H299: SQ2 Learning Tools | I299: QA Engineer | J299: — | O299: 2 | P299: M10 teacher-view layer on unified analytics | Q299: Cache build and validation | R299: Cache tenancy fuzz test executed: concurrent identical dashboard requests across tenants with zero cross-tenant cache hits | S299: SMT-01.3.01 | T299: Fuzz test report | V299: Zero cross-tenant hits across the full fuzz run | W299: All | X299: Review D-M10 tests; Scenario 2 | Y299: Not started
A300: SMT-01.3.03 | B300: D18 | C300: Analytics Dashboard Suite (incl. TLA) — All Roles | D300: Build | E300: P2 | F300: SMT | G300: M10 | H300: SQ2 Learning Tools | I300: Backend Engineer | J300: — | O300: 2 | P300: M10 teacher-view layer on unified analytics | Q300: Cache build and validation | R300: Cache rebuild job implemented and Redis FLUSHALL chaos test passed under load: views degrade to source reads or rebuilding states, numbers never change incorrectly, rebuild completes within SLO | S300: SMT-01.3.01 | T300: Chaos test report | V300: Zero incorrect numbers during flush recovery and rebuild inside the SLO window | W300: All | X300: Review D-M10 tests; R-027 | Y300: Not started
A301: SMT-01.3.04 | B301: D18 | C301: Analytics Dashboard Suite (incl. TLA) — All Roles | D301: Build | E301: P2 | F301: SMT | G301: M10 | H301: SQ2 Learning Tools | I301: QA Engineer | J301: — | O301: 2 | P301: M10 teacher-view layer on unified analytics | Q301: Cache build and validation | R301: Aggregate consistency check automated in CI: teacher-view aggregate equals mart-derived export for the same class and window exactly | S301: SMT-01.3.03, SMT-01.2.04 | T301: CI consistency job output | V301: Exact match on the fixture class across all compared aggregates in CI | W301: All | X301: Review D-M10 tests | Y301: Not started
A302: SMT-01.4.01 | B302: D18 | C302: Analytics Dashboard Suite (incl. TLA) — All Roles | D302: Build | E302: P2 | F302: SMT | G302: M10 | H302: SQ2 Learning Tools | I302: DevSecOps Engineer | J302: — | O302: 2 | P302: M10 teacher-view layer on unified analytics | Q302: Operations and handoff | R302: M10 observability implemented: embed load p95, cache hit ratio, and staleness age metrics with alerts and a runbook walked by a non-author | S302: SMT-01.2.01 | T302: Dashboards, alert rules, runbook sign-off | V302: All three metrics visible, alerts fired in test, and non-author completes the runbook walk | W302: All | X302: Review N; TST-STD 8 | Y302: Not started
A303: SMT-01.4.02 | B303: D18 | C303: Analytics Dashboard Suite (incl. TLA) — All Roles | D303: Build | E303: P1 | F303: SMT | G303: M10 | H303: SQ2 Learning Tools | I303: DevSecOps Engineer | J303: — | O303: 2 | P303: M10 teacher-view layer on unified analytics | Q303: Operations and handoff | R303: M10 teacher-view layer installed in the zero-egress enclave simulator against the enclave reporting replica with zero egress | S303: SMT-01.2.01 | T303: Enclave install log plus egress result | V303: Teacher views render from the enclave replica with zero outbound attempts | W303: Enclave | X303: MOD-015; A-014 | Y303: Not started
... A389: PER-03.1.04 | B389: D14 | C389: Personalized Learning Engine — Core | D389: Build | E389: P2 | F389: PER | G389: M13 | H389: SQ2 Learning Tools | I389: QA Engineer | J389: — | O389: 3 | P389: M13 data layer | Q389: Decision log and fixtures | R389: Decision-audit reconstruction test executed: for every path change in pilot fixtures, signal, rule version, and before/after path reconstructed from the log alone | S389: PER-03.1.01, PER-02.1.02 | T389: Reconstruction test report | V389: 100% of fixture path changes fully reconstructed | W389: All | X389: REV D1 M13 tests | Y389: Not started
A390: PER-03.1.05 | B390: D14 | C390: Personalized Learning Engine — Core | D390: Build | E390: P2 | F390: PER | G390: M13 | H390: SQ2 Learning Tools | I390: QA Lead | J390: — | O390: 2 | P390: M13 data layer | Q390: Decision log and fixtures | R390: Exit-gate evidence bundle assembled and reviewed for the M13 data task | S390: PER-03.1.04 | T390: Signed evidence bundle | V390: Bundle reviewed and signed by QA Lead | W390: All | X390: Brief exit-gate rule | Y390: Not started | AB390: REVIEW: depends on later-stage item
A391: PER-04.1.01 | B391: D14 | C391: Personalized Learning Engine — Core | D391: Build | E391: P2 | F391: PER | G391: M13 | H391: SQ2 Learning Tools | I391: Security Engineer | J391: — | O391: 3 | P391: M13 security | Q391: Authorization and audit | R391: Authorization negative tests passed: learner cannot read another learner's path; override restricted to instructor role | S391: PER-02.2.04 | T391: Negative test report | V391: Both negative tests green in CI | W391: All | X391: Brief lane 4 | Y391: Not started
A392: PER-04.1.02 | B392: D14 | C392: Personalized Learning Engine — Core | D392: Build | E392: P2 | F392: PER | G392: M13 | H392: SQ2 Learning Tools | I392: Backend Engineer | J392: — | O392: 3 | P392: M13 security | Q392: Authorization and audit | R392: Signal payload schema validation implemented with malformed-input rejection tests | S392: PER-01.1.01 | T392: Validation test report | V392: Malformed signals rejected with 4xx and logged; test green | W392: All | X392: Brief lane 4 | Y392: Not started
A393: PER-04.1.03 | B393: D14 | C393: Personalized Learning Engine — Core | D393: Build | E393: P1 | F393: PER | G393: M13 | H393: SQ2 Learning Tools | I393: Backend Engineer | J393: — | O393: 3 | P393: M13 security | Q393: Authorization and audit | R393: Path-change and override audit events emitted through the shared hash-chained audit service | S393: PLT-02.1.01 | T393: Audit query output | V393: Every path change and override retrievable from audit store | W393: All | X393: MOD-013 | Y393: Not started
A394: PER-04.1.04 | B394: D14 | C394: Personalized Learning Engine — Core | D394: Build | E394: P2 | F394: PER | G394: M13 | H394: SQ2 Learning Tools | I394: QA Lead | J394: — | O394: 3 | P394: M13 security | Q394: Authorization and audit | R394: Exit-gate evidence bundle assembled and reviewed for the M13 security task | S394: PER-04.1.03 | T394: Signed evidence bundle | V394: Bundle reviewed and signed by QA Lead | W394: All | X394: Brief exit-gate rule | Y394: Not started
A395: PER-05.1.01 | B395: D14 | C395: Personalized Learning Engine — Core | D395: Build | E395: P2 | F395: PER | G395: M13 | H395: SQ2 Learning Tools | I395: Backend Engineer | J395: — | O395: 3 | P395: M13 observability | Q395: Metrics alerts and SLO | R395: Structured logs with correlation IDs propagating from signal receipt to path decision | S395: PER-02.1.01 | T395: Log trace sample | V395: One correlation ID traces a signal to its path change end to end | W395: All | X395: Brief lane 5 | Y395: Not started
A396: PER-05.1.02 | B396: D14 | C396: Personalized Learning Engine — Core | D396: Build | E396: P2 | F396: PER | G396: M13 | H396: SQ2 Learning Tools | I396: Backend Engineer | J396: — | O396: 3 | P396: M13 observability | Q396: Metrics alerts and SLO | R396: Metrics dashboard live: path-change rate, override rate, oscillation-guard triggers, signal staleness | S396: PER-02.2.07 | T396: Dashboard URL | V396: All four metrics render with live data in staging | W396: All | X396: Brief lane 5 | Y396: Not started
A397: PER-05.1.03 | B397: D14 | C397: Personalized Learning Engine — Core | D397: Build | E397: P2 | F397: PER | G397: M13 | H397: SQ2 Learning Tools | I397: DevSecOps Engineer | J397: — | O397: 3 | P397: M13 observability | Q397: Metrics alerts and SLO | R397: Alerts configured for sequencing oscillation and signal-feed silence; runbook written and walked by a non-author | S397: PER-05.1.02 | T397: Alert config and runbook walkthrough record | V397: Both alerts fired in test; runbook walked by non-author | W397: All | X397: Brief lane 5 | Y397: Not started
A398: PER-05.1.04 | B398: D14 | C398: Personalized Learning Engine — Core | D398: Build | E398: P2 | F398: PER | G398: M13 | H398: SQ2 Learning Tools | I398: DevSecOps Engineer | J398: — | O398: 3 | P398: M13 observability | Q398: Metrics alerts and SLO | R398: Path-decision latency SLO defined and measured in staging | S398: PER-05.1.02 | T398: SLO document and staging measurement | V398: SLO documented; staging p95 within target | W398: All | X398: Brief lane 5 | Y398: Not started
A399: PER-05.1.05 | B399: D14 | C399: Personalized Learning Engine — Core | D399: Build | E399: P2 | F399: PER | G399: M13 | H399: SQ2 Learning Tools | I399: QA Lead | J399: — | O399: 3 | P399: M13 observability | Q399: Metrics alerts and SLO | R399: Exit-gate evidence bundle assembled and reviewed for the M13 observability task | S399: PER-05.1.04 | T399: Signed evidence bundle | V399: Bundle reviewed and signed by QA Lead | W399: All | X399: Brief exit-gate rule | Y399: Not started
A400: PER-06.1.01 | B400: D14 | C400: Personalized Learning Engine — Core | D400: Build | E400: P2 | F400: PER | G400: M13 | H400: SQ2 Learning Tools | I400: DevSecOps Engineer | J400: — | O400: 3 | P400: M13 deployment | Q400: CI and enclave install | R400: CI pipeline live: container build, contract conformance gate, unit and integration suites blocking | S400: PER-01.1.08 | T400: CI pipeline run | V400: Pipeline green and blocking on main branch | W400: All | X400: Brief lane 6 | Y400: Not started
A401: PER-06.1.02 | B401: D14 | C401: Personalized Learning Engine — Core | D401: Build | E401: P1 | F401: PER | G401: M13 | H401: SQ2 Learning Tools | I401: DevSecOps Engineer | J401: — | O401: 3 | P401: M13 deployment | Q401: CI and enclave install | R401: Enclave install from release bundle verified zero-egress: sequencing runs with no external calls | S401: PER-06.1.01 | T401: Zero-egress test log from enclave simulator | V401: Zero outbound connections observed during full sequencing cycle | W401: Enclave | X401: MOD-015 | Y401: Not started
A402: PER-06.1.03 | B402: D14 | C402: Personalized Learning Engine — Core | D402: Build | E402: P2 | F402: PER | G402: M13 | H402: SQ2 Learning Tools | I402: DevSecOps Engineer | J402: — | O402: 3 | P402: M13 deployment | Q402: CI and enclave install | R402: Rollback of a sequencing release rehearsed; kill-switch reverting to static paths verified | S402: PER-06.1.01 | T402: Rollback rehearsal record | V402: Rollback completed; kill-switch freezes paths within one session | W402: All | X402: Brief lane 6 | Y402: Not started
... A406: PER-07.1.03 | B406: D14 | C406: Personalized Learning Engine — Core | D406: Build | E406: P2 | F406: PER | G406: M13 | H406: SQ2 Learning Tools | I406: Technical Writer | J406: — | O406: 4 | P406: M13 documentation and handoff | Q406: Docs and training | R406: P4 instructor training notes on override and path explanations delivered | S406: PER-07.1.02 | T406: Training notes in P4 pack | V406: Notes accepted by P4 curriculum owner | W406: All | X406: Brief lane 7 | Y406: Not started
A407: PER-07.1.04 | B407: D14 | C407: Personalized Learning Engine — Core | D407: Build | E407: P2 | F407: PER | G407: M13 | H407: SQ2 Learning Tools | I407: QA Lead | J407: — | O407: 3 | P407: M13 documentation and handoff | Q407: Docs and training | R407: Exit-gate evidence bundle assembled and reviewed for the M13 documentation task | S407: PER-07.1.03 | T407: Signed evidence bundle | V407: Bundle reviewed and signed by QA Lead | W407: All | X407: Brief exit-gate rule | Y407: Not started | AB407: REVIEW: depends on later-stage item
A408: PER-08.1.01 | B408: D23 | C408: Difference Training Application | D408: Build | E408: P1 | F408: PER | G408: M14 | H408: SQ2 Learning Tools | I408: Platform Architect | J408: — | O408: 0 | P408: M14 contracts and policies | Q408: Gap contracts | R408: Gap-computation contract drafted: inputs and outputs exclusively M19 registry IDs with zero free-text skill matching | S408: TLA-01.1.01 | T408: Contract registry entry | V408: Contract v1 published; conformance test rejects non-registry IDs | W408: All | X408: MOD-003; REV D1 M14 exit-criteria | Y408: Not started
A409: PER-08.1.02 | B409: D23 | C409: Difference Training Application | D409: Build | E409: P1 | F409: PER | G409: M14 | H409: SQ2 Learning Tools | I409: Instructional Designer | J409: — | O409: 0 | P409: M14 contracts and policies | Q409: Gap contracts | R409: Role-profile artifact defined as a versioned registry artifact with owner, import format, and approval flow | S409: TLA-01.1.01 | T409: Role-profile specification | V409: Specification approved; sample profile imported and versioned | W409: All | X409: REV D1 M14 required-changes | Y409: Not started
A410: PER-08.1.03 | B410: D23 | C410: Difference Training Application | D410: Build | E410: P1 | F410: PER | G410: M14 | H410: SQ2 Learning Tools | I410: Instructional Designer | J410: — | O410: 0 | P410: M14 contracts and policies | Q410: Gap contracts | R410: Held-skill evidence policy documented: record levels counted, recency and expiry rules for previously proven skills | S410: - | T410: Approved evidence policy document | V410: Policy approved with explicit expiry rules | W410: All | X410: REV D1 M14 gaps | Y410: Not started
A411: PER-08.1.04 | B411: D23 | C411: Difference Training Application | D411: Build | E411: P1 | F411: PER | G411: M14 | H411: SQ2 Learning Tools | I411: Product Manager | J411: — | O411: 0 | P411: M14 contracts and policies | Q411: Gap contracts | R411: Supervisor edit semantics decision recorded: per-learner override versus role-profile fork, with approval authority named | S411: PER-08.1.02 | T411: Decision record | V411: Decision recorded with named approval authority | W411: All | X411: REV D1 M14 gaps | Y411: Not started
A412: PER-08.1.05 | B412: D23 | C412: Difference Training Application | D412: Build | E412: P1 | F412: PER | G412: M14 | H412: SQ2 Learning Tools | I412: Platform Architect | J412: — | O412: 0 | P412: M14 contracts and policies | Q412: Gap contracts | R412: Audit-trail content specification for gap approvals defined: actor, action, versions of inputs, timestamp | S412: - | T412: Audit-trail specification | V412: Specification published; all four field groups mandatory | W412: All | X412: PLAN M14 main-jobs | Y412: Not started
A413: PER-08.1.06 | B413: D23 | C413: Difference Training Application | D413: Build | E413: P1 | F413: PER | G413: M14 | H413: SQ2 Learning Tools | I413: Platform Architect | J413: — | O413: 0 | P413: M14 contracts and policies | Q413: Gap contracts | R413: Official-record change subscription contract drafted for issue and revoke events driving gap recompute | S413: FND-07.1.01 | T413: Contract registry entry | V413: Contract v1 published with recompute trigger semantics | W413: All | X413: REV D1 M14 required-changes | Y413: Not started
A414: PER-08.1.07 | B414: D23 | C414: Difference Training Application | D414: Build | E414: P1 | F414: PER | G414: M14 | H414: SQ2 Learning Tools | I414: QA Engineer | J414: — | O414: 0 | P414: M14 contracts and policies | Q414: Gap contracts | R414: Contract conformance tests for M14 contracts wired into CI before implementation | S414: PER-08.1.01 | T414: CI job run | V414: Conformance suite blocking in CI | W414: All | X414: Brief lane 1 | Y414: Not started
A415: PER-08.1.08 | B415: D23 | C415: Difference Training Application | D415: Build | E415: P1 | F415: PER | G415: M14 | H415: SQ2 Learning Tools | I415: QA Lead | J415: — | O415: 0 | P415: M14 contracts and policies | Q415: Gap contracts | R415: Exit-gate evidence bundle assembled and reviewed for the M14 contracts task | S415: PER-08.1.07 | T415: Signed evidence bundle | V415: Bundle reviewed and signed by QA Lead | W415: All | X415: Brief exit-gate rule | Y415: Not started
A416: PER-09.1.01 | B416: D23 | C416: Difference Training Application | D416: Build | E416: P2 | F416: PER | G416: M14 | H416: SQ2 Learning Tools | I416: Backend Engineer | J416: — | O416: 2 | P416: M14 gap engine build | Q416: Gap computation | R416: Required-skills loader implemented from versioned role profiles in the M19 registry | S416: TLA-03.1.01, PER-08.1.02 | T416: Loader code and test run | V416: Fixture role profile loads with version recorded | W416: All | X416: PLAN M14 main-jobs | Y416: Not started
A417: PER-09.1.02 | B417: D23 | C417: Difference Training Application | D417: Build | E417: P2 | F417: PER | G417: M14 | H417: SQ2 Learning Tools | I417: Backend Engineer | J417: — | O417: 2 | P417: M14 gap engine build | Q417: Gap computation | R417: Held-skills loader implemented via M3/LRS per the evidence policy including expiry handling | S417: PER-08.1.03 | T417: Loader test run | V417: Expired fixture skill excluded per policy in test | W417: All | X417: PLAN M14 main-jobs | Y417: Not started
A418: PER-09.1.03 | B418: D23 | C418: Difference Training Application | D418: Build | E418: P2 | F418: PER | G418: M14 | H418: SQ2 Learning Tools | I418: Backend Engineer | J418: — | O418: 2 | P418: M14 gap engine build | Q418: Gap computation | R418: Gap computation engine implemented handling levels, partial competence, equivalences, and prerequisite structures | S418: PER-09.1.01, PER-09.1.02 | T418: Engine code and unit suite | V418: Unit suite covering all four structures green | W418: All | X418: PLAN M14 main-jobs; REV D1 M14 gaps | Y418: Not started
A419: PER-09.1.04 | B419: D23 | C419: Difference Training Application | D419: Build | E419: P2 | F419: PER | G419: M14 | H419: SQ2 Learning Tools | I419: QA Engineer | J419: — | O419: 2 | P419: M14 gap engine build | Q419: Gap computation | R419: Gap-correctness test executed against hand-computed fixture truth including level and expiry edge cases | S419: PER-09.1.03, PER-10.1.03 | T419: Test report | V419: Computed gaps match hand-computed truth on all fixtures | W419: All | X419: REV D1 M14 tests | Y419: Not started
... A443: PER-14.1.02 | B443: D23 | C443: Difference Training Application | D443: Build | E443: P2 | F443: PER | G443: M14 | H443: SQ2 Learning Tools | I443: Technical Writer | J443: — | O443: 4 | P443: M14 documentation and handoff | Q443: Docs and training | R443: Journey-9 walkthrough documented with audit evidence and P4 training notes for supervisors delivered | S443: PER-09.2.07 | T443: Walkthrough doc and P4 notes | V443: Accepted by P4 curriculum owner | W443: All | X443: Brief lane 7 | Y443: Not started
A444: PER-14.1.03 | B444: D23 | C444: Difference Training Application | D444: Build | E444: P2 | F444: PER | G444: M14 | H444: SQ2 Learning Tools | I444: QA Lead | J444: — | O444: 2 | P444: M14 documentation and handoff | Q444: Docs and training | R444: Exit-gate evidence bundle assembled and reviewed for the M14 documentation task | S444: PER-14.1.02 | T444: Signed evidence bundle | V444: Bundle reviewed and signed by QA Lead | W444: All | X444: Brief exit-gate rule | Y444: Not started | AB444: REVIEW: depends on later-stage item
A445: KNI-01.1.01 | B445: D01 | C445: AI SME Chatbot — Learner-Facing | D445: Build | E445: P1 | F445: KNI | G445: M15 | H445: SQ5 AI & Assessment | I445: Platform Architect | J445: — | O445: 0 | P445: M15 contracts and corpus lifecycle | Q445: Retrieval and lifecycle contracts | R445: Retrieval API contract published with mandatory tenant filter parameter and citation schema carrying doc ID, revision, and chunk ID | S445: - | T445: Contract registry entry | V445: Contract v1 published; conformance test green | W445: All | X445: REV D1 M15 required-changes | Y445: Not started
A446: KNI-01.1.02 | B446: D01 | C446: AI SME Chatbot — Learner-Facing | D446: Build | E446: P1 | F446: KNI | G446: M15 | H446: SQ5 AI & Assessment | I446: Platform Architect | J446: — | O446: 0 | P446: M15 contracts and corpus lifecycle | Q446: Retrieval and lifecycle contracts | R446: Corpus lifecycle contract defined: approval workflow, supersession handling, re-chunk and re-embed on update, embedding-model version pinned per index | S446: PLT-04.1.01 | T446: Lifecycle contract document | V446: All four lifecycle stages specified with owners | W446: All | X446: REV D1 M15 required-changes | Y446: Not started
A447: KNI-01.1.03 | B447: D01 | C447: AI SME Chatbot — Learner-Facing | D447: Build | E447: P1 | F447: KNI | G447: M15 | H447: SQ5 AI & Assessment | I447: Platform Architect | J447: — | O447: 0 | P447: M15 contracts and corpus lifecycle | Q447: Retrieval and lifecycle contracts | R447: Chat usage xAPI profile registered in the event contract: asked, answered, refused, quiz-taken | S447: FND-07.1.01 | T447: Profile entry in contract registry | V447: Profile v1 registered; sample statements validate | W447: All | X447: PLAN M15 main-jobs; MOD-002 | Y447: Not started
A448: KNI-01.1.04 | B448: D01 | C448: AI SME Chatbot — Learner-Facing | D448: Build | E448: P1 | F448: KNI | G448: M15 | H448: SQ5 AI & Assessment | I448: Program Manager | J448: — | O448: 0 | P448: M15 contracts and corpus lifecycle | Q448: Retrieval and lifecycle contracts | R448: Freshness ownership recorded: M25 and the lineage service own source currency; M15 honors tombstones with no duplicate revision-detection logic | S448: PLT-04.1.01 | T448: Responsibility matrix entry | V448: Matrix shows single owner for revision detection | W448: All | X448: MOD-006; REV D1 M15 gaps | Y448: Not started
A449: KNI-01.1.05 | B449: D01 | C449: AI SME Chatbot — Learner-Facing | D449: Build | E449: P1 | F449: KNI | G449: M15 | H449: SQ5 AI & Assessment | I449: Product Manager | J449: — | O449: 0 | P449: M15 contracts and corpus lifecycle | Q449: Retrieval and lifecycle contracts | R449: Practice-quiz feature ruling recorded: routed through the M8 item and event model or cut with [DEFERRED-Phase4] tag | S449: - | T449: Decision record | V449: Ruling recorded; no independent M15 item bank exists | W449: All | X449: REV D1 M15 required-changes | Y449: Not started
A450: KNI-01.1.06 | B450: D01 | C450: AI SME Chatbot — Learner-Facing | D450: Build | E450: P1 | F450: KNI | G450: M15 | H450: SQ5 AI & Assessment | I450: QA Engineer | J450: — | O450: 0 | P450: M15 contracts and corpus lifecycle | Q450: Retrieval and lifecycle contracts | R450: Contract conformance tests for retrieval and citation contracts wired into CI | S450: KNI-01.1.01 | T450: CI job run | V450: Conformance suite blocking in CI | W450: All | X450: Brief lane 1 | Y450: Not started
A451: KNI-01.1.07 | B451: D01 | C451: AI SME Chatbot — Learner-Facing | D451: Build | E451: P1 | F451: KNI | G451: M15 | H451: SQ5 AI & Assessment | I451: QA Lead | J451: — | O451: 0 | P451: M15 contracts and corpus lifecycle | Q451: Retrieval and lifecycle contracts | R451: Exit-gate evidence bundle assembled and reviewed for the M15 contracts task | S451: KNI-01.1.06 | T451: Signed evidence bundle | V451: Bundle reviewed and signed by QA Lead | W451: All | X451: Brief exit-gate rule | Y451: Not started
A452: KNI-02.1.01 | B452: D01 | C452: AI SME Chatbot — Learner-Facing | D452: Build | E452: P2 | F452: KNI | G452: M15 | H452: SQ5 AI & Assessment | I452: Backend Engineer | J452: — | O452: 3 | P452: M15 RAG pipeline build | Q452: Ingest and index | R452: Document upload and approval workflow implemented; only approved manuals enter the retrieval corpus | S452: KNI-01.1.02 | T452: Workflow test run | V452: Unapproved document not retrievable (negative test) | W452: All | X452: PLAN M15 main-jobs | Y452: Not started
A453: KNI-02.1.02 | B453: D01 | C453: AI SME Chatbot — Learner-Facing | D453: Build | E453: P1 | F453: KNI | G453: M15 | H453: SQ5 AI & Assessment | I453: AI/ML Engineer | J453: — | O453: 3 | P453: M15 RAG pipeline build | Q453: Ingest and index | R453: Chunking implemented with overlapping windows; every chunk carries doc ID, revision, effective date, and supersedes fields | S453: KNI-01.1.02 | T453: Chunk store sample | V453: 100% of chunks carry all four lifecycle fields | W453: All | X453: PLAN M15 main-jobs; Scenario 4 | Y453: Not started
A454: KNI-02.1.03 | B454: D01 | C454: AI SME Chatbot — Learner-Facing | D454: Build | E454: P1 | F454: KNI | G454: M15 | H454: SQ5 AI & Assessment | I454: AI/ML Engineer | J454: — | O454: 3 | P454: M15 RAG pipeline build | Q454: Ingest and index | R454: Embedding generation implemented via the shared inference service with embedding-model version pinned and recorded per index | S454: PLT-03.1.01 | T454: Index metadata record | V454: Index metadata shows pinned embedding-model version | W454: All | X454: MOD-009; REV D1 M15 gaps | Y454: Not started
A455: KNI-02.1.04 | B455: D01 | C455: AI SME Chatbot — Learner-Facing | D455: Build | E455: P1 | F455: KNI | G455: M15 | H455: SQ5 AI & Assessment | I455: AI/ML Engineer | J455: — | O455: 3 | P455: M15 RAG pipeline build | Q455: Ingest and index | R455: Tenant-scoped indexes implemented: per-tenant index or namespace with no shared cross-tenant vector store | S455: KNI-02.1.03 | T455: Index topology doc and test | V455: Each tenant's chunks physically separated; verified by inspection test | W455: All | X455: MOD-008; R-022 | Y455: Not started
A456: KNI-02.2.01 | B456: D01 | C456: AI SME Chatbot — Learner-Facing | D456: Build | E456: P2 | F456: KNI | G456: M15 | H456: SQ5 AI & Assessment | I456: AI/ML Engineer | J456: — | O456: 3 | P456: M15 RAG pipeline build | Q456: Retrieve and answer | R456: Retrieval implemented with mandatory tenant filter plus post-retrieval tenant assertion before prompt assembly | S456: KNI-02.1.04 | T456: Retrieval code and unit tests | V456: Assertion rejects any cross-tenant chunk before prompting; test green | W456: All | X456: REV D1 M15 required-changes | Y456: Not started
... A748: CNT-18.1.03 | B748: D10 | C748: PDFs & Technical Manuals Integration — Live TO Connection | D748: Build | E748: P2 | F748: CNT | G748: M25 | H748: SQ6 Content & Authoring | I748: Backend Engineer | J748: — | O748: 2 | P748: M25 revision and blast radius build | Q748: Detection propagation and drills | R748: Blast-radius computation implemented via the lineage service: affected eBooks, chunks, lessons, quiz items, chatbot indexes, and translations enumerated per revision | S748: PLT-04.1.01, CNT-11.1.05 | T748: Blast-radius report on fixture revision | V748: All six artifact classes enumerated for a fixture revision | W748: All | X748: REV D2 M25 gap 3 | Y748: Not started
A749: CNT-18.1.04 | B749: D10 | C749: PDFs & Technical Manuals Integration — Live TO Connection | D749: Build | E749: P1 | F749: CNT | G749: M25 | H749: SQ6 Content & Authoring | I749: Backend Engineer | J749: — | O749: 2 | P749: M25 revision and blast radius build | Q749: Detection propagation and drills | R749: Tombstone issuance implemented: superseded chunks non-retrievable by M15/M26 at query time before re-indexing completes | S749: CNT-18.1.03, KNI-02.2.03 | T749: Tombstone propagation test | V749: Superseded chunk blocked immediately on manifest application | W749: All | X749: Scenario 4; R-010 | Y749: Not started | AB749: REVIEW: depends on later-stage item
A750: CNT-18.1.05 | B750: D10 | C750: PDFs & Technical Manuals Integration — Live TO Connection | D750: Build | E750: P2 | F750: CNT | G750: M25 | H750: SQ6 Content & Authoring | I750: Backend Engineer | J750: — | O750: 2 | P750: M25 revision and blast radius build | Q750: Detection propagation and drills | R750: Re-publish workflow implemented with content-owner approval and a learner-visible transition state | S750: CNT-17.1.05 | T750: Workflow test run | V750: Re-publish requires approval; learners see transition state | W750: All | X750: REV D2 M25 gap 7 | Y750: Not started
A751: CNT-18.1.06 | B751: D10 | C751: PDFs & Technical Manuals Integration — Live TO Connection | D751: Build | E751: P1 | F751: CNT | G751: M25 | H751: SQ6 Content & Authoring | I751: Backend Engineer | J751: — | O751: 2 | P751: M25 revision and blast radius build | Q751: Detection propagation and drills | R751: Per-enclave and per-language supersession verification implemented: every deployment and every language variant confirms tombstone application within the SLA | S751: CNT-18.1.04, CNT-03.1.03 | T751: Verification report | V751: Report lists per-enclave per-language confirmation timestamps | W751: All | X751: Scenario 4; Scenario 16; REV W.13 | Y751: Not started
A752: CNT-18.1.07 | B752: D10 | C752: PDFs & Technical Manuals Integration — Live TO Connection | D752: Build | E752: P1 | F752: CNT | G752: M25 | H752: SQ6 Content & Authoring | I752: QA Lead | J752: — | O752: 2 | P752: M25 revision and blast radius build | Q752: Detection propagation and drills | R752: Scenario-4 supersession drill executed: injected revision flags 100% of affected artifacts within the detection SLA and superseded chunks become non-retrievable within the supersession SLA with an auditable trail, in connected mode and via simulated enclave media | S752: CNT-18.1.06 | T752: Drill report | V752: Both SLAs met; audit trail complete in both modes | W752: All | X752: REV D2 M25 acceptance; Scenario 4 | Y752: Not started
A753: CNT-18.1.08 | B753: D10 | C753: PDFs & Technical Manuals Integration — Live TO Connection | D753: Build | E753: P1 | F753: CNT | G753: M25 | H753: SQ6 Content & Authoring | I753: QA Lead | J753: — | O753: 2 | P753: M25 revision and blast radius build | Q753: Detection propagation and drills | R753: Scenario-16 bilingual drill executed: source revision flags the Hindi variant stale in the same propagation cycle, in-language currency warning shown, stale-linked quiz items blocked from official assessment, and the exposure audit query returns learner and record lists | S753: CNT-18.1.06 | T753: Bilingual drill report | V753: All four outcomes observed in one drill | W753: All | X753: Scenario 16 validation test | Y753: Not started
A754: CNT-18.1.09 | B754: D10 | C754: PDFs & Technical Manuals Integration — Live TO Connection | D754: Build | E754: P2 | F754: CNT | G754: M25 | H754: SQ6 Content & Authoring | I754: QA Engineer | J754: — | O754: 3 | P754: M25 revision and blast radius build | Q754: Detection propagation and drills | R754: Prolonged-disconnection drill executed: after a simulated 6-month gap the enclave visibly labels unverifiable-currency content to learners | S754: CNT-18.1.02 | T754: Drill report and UI capture | V754: Currency warning displayed on all affected content | W754: Enclave | X754: REV D2 M25 acceptance; LOOP 7 | Y754: Not started
A755: CNT-18.1.10 | B755: D10 | C755: PDFs & Technical Manuals Integration — Live TO Connection | D755: Build | E755: P2 | F755: CNT | G755: M25 | H755: SQ6 Content & Authoring | I755: QA Lead | J755: — | O755: 2 | P755: M25 revision and blast radius build | Q755: Detection propagation and drills | R755: Exit-gate evidence bundle assembled and reviewed for the M25 build task | S755: CNT-18.1.09 | T755: Signed evidence bundle | V755: Bundle reviewed and signed by QA Lead | W755: All | X755: Brief exit-gate rule | Y755: Not started | AB755: REVIEW: depends on later-stage item
A756: CNT-19.1.01 | B756: D10 | C756: PDFs & Technical Manuals Integration — Live TO Connection | D756: Build | E756: P1 | F756: CNT | G756: M25 | H756: SQ6 Content & Authoring | I756: Data Engineer | J756: — | O756: 2 | P756: M25 data and audit | Q756: Supersession records | R756: Supersession event and tombstone tables implemented append-only with audit trail of actor, action, timestamp, and manifest ID | S756: CNT-17.1.04, PLT-02.1.01 | T756: Schema and audit query | V756: Every supersession action reconstructable from the trail | W756: All | X756: Scenario 4; MOD-013 | Y756: Not started
A757: CNT-19.1.02 | B757: D10 | C757: PDFs & Technical Manuals Integration — Live TO Connection | D757: Build | E757: P1 | F757: CNT | G757: M25 | H757: SQ6 Content & Authoring | I757: Data Engineer | J757: — | O757: 2 | P757: M25 data and audit | Q757: Supersession records | R757: Currency state queryable per deployment and per language variant: content-as-of reporting | S757: CNT-18.1.06 | T757: Query output | V757: One query returns currency state for any enclave and language | W757: All | X757: Scenario 4 detection; Q28 | Y757: Not started
A758: CNT-19.1.03 | B758: D10 | C758: PDFs & Technical Manuals Integration — Live TO Connection | D758: Build | E758: P2 | F758: CNT | G758: M25 | H758: SQ6 Content & Authoring | I758: QA Lead | J758: — | O758: 2 | P758: M25 data and audit | Q758: Supersession records | R758: Exit-gate evidence bundle assembled and reviewed for the M25 data task | S758: CNT-19.1.02 | T758: Signed evidence bundle | V758: Bundle reviewed and signed by QA Lead | W758: All | X758: Brief exit-gate rule | Y758: Not started
A759: CNT-20.1.01 | B759: D10 | C759: PDFs & Technical Manuals Integration — Live TO Connection | D759: Build | E759: P2 | F759: CNT | G759: M25 | H759: SQ6 Content & Authoring | I759: DevSecOps Engineer | J759: — | O759: 2 | P759: M25 observability | Q759: Currency telemetry | R759: Metrics live: detection latency, propagation latency per enclave, tombstone application lag, stale-artifact count; alerts on SLA breach with runbook walked by a non-author | S759: CNT-18.1.06 | T759: Dashboard and walkthrough record | V759: All metrics render; SLA-breach alert fired in test; runbook walked | W759: All | X759: Brief lane 5 | Y759: Not started
A760: CNT-20.1.02 | B760: D10 | C760: PDFs & Technical Manuals Integration — Live TO Connection | D760: Build | E760: P1 | F760: CNT | G760: M25 | H760: SQ6 Content & Authoring | I760: BI Engineer | J760: — | O760: 2 | P760: M25 observability | Q760: Currency telemetry | R760: Fleet currency dashboard live: per-enclave corpus verified-as-of view | S760: CNT-19.1.02 | T760: Dashboard URL | V760: Every enclave shows its corpus as-of date | W760: All | X760: Scenario 4 detection | Y760: Not started
A761: CNT-20.1.03 | B761: D10 | C761: PDFs & Technical Manuals Integration — Live TO Connection | D761: Build | E761: P2 | F761: CNT | G761: M25 | H761: SQ6 Content & Authoring | I761: QA Lead | J761: — | O761: 2 | P761: M25 observability | Q761: Currency telemetry | R761: Exit-gate evidence bundle assembled and reviewed for the M25 observability task | S761: CNT-20.1.02 | T761: Signed evidence bundle | V761: Bundle reviewed and signed by QA Lead | W761: All | X761: Brief exit-gate rule | Y761: Not started
A762: CNT-21.1.01 | B762: D10 | C762: PDFs & Technical Manuals Integration — Live TO Connection | D762: Build | E762: P1 | F762: CNT | G762: M25 | H762: SQ6 Content & Authoring | I762: DevSecOps Engineer | J762: — | O762: 2 | P762: M25 deployment and docs | Q762: Release and runbooks | R762: CI pipeline live; enclave install path including media-manifest tooling verified zero-egress | S762: CNT-18.1.02 | T762: Zero-egress test log | V762: Manifest application in simulator with zero outbound connections | W762: Enclave | X762: MOD-015 | Y762: Not started
A763: CNT-21.1.02 | B763: D10 | C763: PDFs & Technical Manuals Integration — Live TO Connection | D763: Build | E763: P2 | F763: CNT | G763: M25 | H763: SQ6 Content & Authoring | I763: Technical Writer | J763: — | O763: 2 | P763: M25 deployment and docs | Q763: Release and runbooks | R763: Re-publish and supersession operator runbook published with P4 training notes | S763: CNT-18.1.05 | T763: Published runbook | V763: Non-author operator executes a supersession from the runbook | W763: All | X763: Brief lane 7 | Y763: Not started
A764: CNT-21.1.03 | B764: D10 | C764: PDFs & Technical Manuals Integration — Live TO Connection | D764: Build | E764: P2 | F764: CNT | G764: M25 | H764: SQ6 Content & Authoring | I764: QA Lead | J764: — | O764: 2 | P764: M25 deployment and docs | Q764: Release and runbooks | R764: Exit-gate evidence bundle assembled and reviewed for the M25 deployment and docs task | S764: CNT-21.1.02 | T764: Signed evidence bundle | V764: Bundle reviewed and signed by QA Lead | W764: All | X764: Brief exit-gate rule | Y764: Not started
A765: CNT-22.1.01 | B765: D04 | C765: Pedagogy Design Review Protocol | D765: Build | E765: P1 | F765: CNT | G765: P2 | H765: SQ6 Content & Authoring | I765: Instructional Designer | J765: — | O765: 0 | P765: P2 protocol definition | Q765: Stages roles and authority | R765: P2 protocol document drafted defining review stages with entry and exit criteria per stage | S765: - | T765: Protocol draft v1 | V765: Every stage has binary entry and exit criteria | W765: All | X765: REV D2 P2; LOOP 13 | Y765: Not started
A766: CNT-22.1.02 | B766: D04 | C766: Pedagogy Design Review Protocol | D766: Build | E766: P1 | F766: CNT | G766: P2 | H766: SQ6 Content & Authoring | I766: Instructional Designer | J766: — | O766: 0 | P766: P2 protocol definition | Q766: Stages roles and authority | R766: Reviewer roles and named block authority defined: who can stop a content or AI-behavior release | S766: CNT-22.1.01 | T766: Roles and authority section | V766: Block authority named as a role with escalation path | W766: All | X766: REV D2 P2 | Y766: Not started
A767: CNT-22.1.03 | B767: D04 | C767: Pedagogy Design Review Protocol | D767: Build | E767: P1 | F767: CNT | G767: P2 | H767: SQ6 Content & Authoring | I767: Instructional Designer | J767: — | O767: 0 | P767: P2 protocol definition | Q767: Stages roles and authority | R767: Sampling rate for AI-generated content set by risk tier with written rationale | S767: CNT-22.1.01 | T767: Sampling policy | V767: Numeric rate per risk tier approved | W767: All | X767: REV D2 P2; LOOP 27.5 | Y767: Not started
A768: CNT-22.1.04 | B768: D04 | C768: Pedagogy Design Review Protocol | D768: Build | E768: P1 | F768: CNT | G768: P2 | H768: SQ6 Content & Authoring | I768: Program Manager | J768: — | O768: 0 | P768: P2 protocol definition | Q768: Stages roles and authority | R768: Reviewer capacity sized against projected M22 and M24 throughput with an approved staffing plan | S768: CNT-22.1.03, CNT-13.1.03 | T768: Capacity plan | V768: Plan covers projected throughput with named reviewer pool | W768: All | X768: R-014 | Y768: Not started | AB768: REVIEW: depends on later-stage item
A769: CNT-22.1.05 | B769: D04 | C769: Pedagogy Design Review Protocol | D769: Build | E769: P1 | F769: CNT | G769: P2 | H769: SQ6 Content & Authoring | I769: Instructional Designer | J769: — | O769: 0 | P769: P2 protocol definition | Q769: Stages roles and authority | R769: Per-language review capability plan approved for the committed language matrix | S769: CNT-22.1.04 | T769: Language capability plan | V769: Each committed language has a named review capability | W769: All | X769: LOOP 31.3 | Y769: Not started
A770: CNT-22.1.06 | B770: D04 | C770: Pedagogy Design Review Protocol | D770: Build | E770: P1 | F770: CNT | G770: P2 | H770: SQ6 Content & Authoring | I770: Instructional Designer | J770: — | O770: 0 | P770: P2 protocol definition | Q770: Stages roles and authority | R770: Review SLAs defined per content class distinguishing safety-critical from general content | S770: CNT-22.1.01 | T770: SLA table in protocol | V770: Numeric SLA per content class approved | W770: All | X770: REV D2 P2 | Y770: Not started
A771: CNT-22.1.07 | B771: D04 | C771: Pedagogy Design Review Protocol | D771: Build | E771: P1 | F771: CNT | G771: P2 | H771: SQ6 Content & Authoring | I771: Product Manager | J771: — | O771: 0 | P771: P2 protocol definition | Q771: Stages roles and authority | R771: P2 protocol document approved with named roles and block authority | S771: CNT-22.1.02, CNT-22.1.06 | T771: Signed protocol document | V771: Approval signatures on file | W771: All | X771: REV D2 P2 acceptance | Y771: Not started
A772: CNT-22.1.08 | B772: D04 | C772: Pedagogy Design Review Protocol | D772: Build | E772: P1 | F772: CNT | G772: P2 | H772: SQ6 Content & Authoring | I772: QA Lead | J772: — | O772: 0 | P772: P2 protocol definition | Q772: Stages roles and authority | R772: Exit-gate evidence bundle assembled and reviewed for the P2 definition task | S772: CNT-22.1.07 | T772: Signed evidence bundle | V772: Bundle reviewed and signed by QA Lead | W772: All | X772: Brief exit-gate rule | Y772: Not started
A773: CNT-23.1.01 | B773: D04 | C773: Pedagogy Design Review Protocol | D773: Build | E773: P1 | F773: CNT | G773: P2 | H773: SQ6 Content & Authoring | I773: Backend Engineer | J773: — | O773: 2 | P773: P2 operation and measurement | Q773: Gate operation | R773: P2 integrated as a hard publish gate in the M22 workflow: publish impossible without a P2 record | S773: CNT-22.1.07, CNT-02.2.03 | T773: Blocking integration test | V773: Publish without P2 record rejected in production configuration | W773: All | X773: MOD-014; REV D2 P2 entry criteria | Y773: Not started
A774: CNT-23.1.02 | B774: D04 | C774: Pedagogy Design Review Protocol | D774: Build | E774: P2 | F774: CNT | G774: P2 | H774: SQ6 Content & Authoring | I774: QA Lead | J774: — | O774: 2 | P774: P2 operation and measurement | Q774: Gate operation | R774: Defect-escape-rate metric instrumented: production content defects traced back to the review stage that missed them | S774: CNT-23.1.01 | T774: Metric definition and dashboard | V774: Every logged content defect carries a review-stage attribution | W774: All | X774: LOOP 27.5 | Y774: Not started
A775: CNT-23.1.03 | B775: D04 | C775: Pedagogy Design Review Protocol | D775: Build | E775: P2 | F775: CNT | G775: P2 | H775: SQ6 Content & Authoring | I775: QA Lead | J775: — | O775: 4 | P775: P2 operation and measurement | Q775: Gate operation | R775: Pilot measurement executed: 100% of published lessons carry a P2 record and the measured defect-escape rate is below the agreed threshold | S775: CNT-23.1.02 | T775: Pilot measurement report | V775: Both conditions met over the Stage 4 pilot window | W775: All | X775: REV D2 P2 acceptance; REV T Stage 4 | Y775: Not started
A776: CNT-23.1.04 | B776: D04 | C776: Pedagogy Design Review Protocol | D776: Build | E776: P2 | F776: CNT | G776: P2 | H776: SQ6 Content & Authoring | I776: Instructional Designer | J776: — | O776: 4 | P776: P2 operation and measurement | Q776: Gate operation | R776: AI-content sampling audits executed at the defined rate with results feeding sampling-rate adjustment | S776: CNT-22.1.03, CNT-23.1.02 | T776: Audit records | V776: Audits executed at plan rate; adjustment decision recorded | W776: All | X776: REV D2 P2; LOOP 27.4 | Y776: Not started
A777: CNT-23.1.05 | B777: D04 | C777: Pedagogy Design Review Protocol | D777: Build | E777: P2 | F777: CNT | G777: P2 | H777: SQ6 Content & Authoring | I777: QA Lead | J777: — | O777: 4 | P777: P2 operation and measurement | Q777: Gate operation | R777: Exit-gate evidence bundle assembled and reviewed for the P2 operation task | S777: CNT-23.1.04 | T777: Signed evidence bundle | V777: Bundle reviewed and signed by QA Lead | W777: All | X777: Brief exit-gate rule | Y777: Not started
A778: AIA-01.1.01 | B778: E04 | C778: Shared Local AI Inference Platform (enabler) | D778: Build | E778: P1 | F778: AIA | G778: SVC | H778: SQ5 AI & Assessment | I778: Platform Architect | J778: — | O778: 0 | P778: Inference platform contracts | Q778: Serving and registry contracts | R778: Inference API contract v1 drafted covering completion, embedding, and tokenize endpoints with mandatory tenant ID, command ID, priority class, pinned model reference, and correlation ID fields, and published to the contract registry | S778: PLT-05.1.02 | T778: Contract registry entry v1 | V778: Contract v1 published; review sign-off by two consuming module leads recorded | W778: All | X778: MOD-009; REV S.2c | Y778: Not started
...

Sheet Sprint Calendar
A1: Sprint Calendar
A2: Fill one row per sprint. TargetSprint on the Master Checklist must match a Sprint ID here. Without this sheet no item can be given a date.
A4: Sprint ID | B4: Start date | C4: End date | D4: Working days | E4: Stage | F4: Sprint goal | G4: Scope freeze date | H4: Demo date | I4: Notes
A5: PROVISIONAL: S01 | D5: 10 | E5: 0 | F5: PROVISIONAL: Freeze event envelope + competency schema contracts

Sheet Capacity Plan
A1: Capacity Plan
A2: One row per person per sprint. Allocated days pulls from EstDays where Assignee and TargetSprint match. This is the sheet that turns the checklist into a plan.
A4: Person | B4: Role | C4: Squad | D4: Test team | E4: Cost centre | F4: Sprint ID | G4: Available days | H4: Allocated days (from EstDays) | I4: Over-allocated? | J4: Notes
A5: PROVISIONAL: <name> | B5: PROVISIONAL: Backend Engineer | C5: SQ1 Platform Core | D5: — | F5: PROVISIONAL: S01 | G5: 8 | H5: =SUMIFS('Master Checklist'!$M:$M,'Master Checklist'!$L:$L,$A5,'Master Checklist'!$N:$N,$F5) -> 0 | I5: =IF(H5>G5,"YES","")

Sheet Stage Gates
A1: Stage Gates
A2: A stage closes on evidence, not opinion. Gate status is computed; entry/exit criteria and the gate owner are yours to complete.
A4: Stage | B4: Scope | C4: Gate owner | D4: Target date | E4: Items | F4: Done | G4: P0 open | H4: Gate status | I4: Entry criteria | J4: Exit criteria evidence
A5: Stage 0 | B5: Stage 0 — Contracts, schemas & decisions | E5: =COUNTIF('Master Checklist'!$O:$O,0) -> 292 | F5: =COUNTIFS('Master Checklist'!$O:$O,0,'Master Checklist'!$Y:$Y,"Done") -> 0 | G5: =COUNTIFS('Master Checklist'!$O:$O,0,'Master Checklist'!$E:$E,"P0",'Master Checklist'!$Y:$Y,"<>Done") -> 25 | H5: =IF(AND(E5>0,F5=E5),"PASS","OPEN") -> OPEN
A6: Stage 1 | B6: Stage 1 — Slice A validation | E6: =COUNTIF('Master Checklist'!$O:$O,1) -> 498 | F6: =COUNTIFS('Master Checklist'!$O:$O,1,'Master Checklist'!$Y:$Y,"Done") -> 0 | G6: =COUNTIFS('Master Checklist'!$O:$O,1,'Master Checklist'!$E:$E,"P0",'Master Checklist'!$Y:$Y,"<>Done") -> 13 | H6: =IF(AND(E6>0,F6=E6),"PASS","OPEN") -> OPEN
A7: Stage 2 | B7: Stage 2 — Content & competency | E7: =COUNTIF('Master Checklist'!$O:$O,2) -> 496 | F7: =COUNTIFS('Master Checklist'!$O:$O,2,'Master Checklist'!$Y:$Y,"Done") -> 0 | G7: =COUNTIFS('Master Checklist'!$O:$O,2,'Master Checklist'!$E:$E,"P0",'Master Checklist'!$Y:$Y,"<>Done") -> 6 | H7: =IF(AND(E7>0,F7=E7),"PASS","OPEN") -> OPEN
A8: Stage 3 | B8: Stage 3 — AI & field slices | E8: =COUNTIF('Master Checklist'!$O:$O,3) -> 513 | F8: =COUNTIFS('Master Checklist'!$O:$O,3,'Master Checklist'!$Y:$Y,"Done") -> 0 | G8: =COUNTIFS('Master Checklist'!$O:$O,3,'Master Checklist'!$E:$E,"P0",'Master Checklist'!$Y:$Y,"<>Done") -> 6 | H8: =IF(AND(E8>0,F8=E8),"PASS","OPEN") -> OPEN
A9: Stage 4 | B9: Stage 4 — Controlled pilot | E9: =COUNTIF('Master Checklist'!$O:$O,4) -> 212 | F9: =COUNTIFS('Master Checklist'!$O:$O,4,'Master Checklist'!$Y:$Y,"Done") -> 0 | G9: =COUNTIFS('Master Checklist'!$O:$O,4,'Master Checklist'!$E:$E,"P0",'Master Checklist'!$Y:$Y,"<>Done") -> 0 | H9: =IF(AND(E9>0,F9=E9),"PASS","OPEN") -> OPEN
A10: Stage 5 | B10: Stage 5 — Production & scale | E10: =COUNTIF('Master Checklist'!$O:$O,5) -> 109 | F10: =COUNTIFS('Master Checklist'!$O:$O,5,'Master Checklist'!$Y:$Y,"Done") -> 0 | G10: =COUNTIFS('Master Checklist'!$O:$O,5,'Master Checklist'!$E:$E,"P0",'Master Checklist'!$Y:$Y,"<>Done") -> 0 | H10: =IF(AND(E10>0,F10=E10),"PASS","OPEN") -> OPEN

Sheet Defect Log
A1: Defect Log
A2: Every failed test lands here. Fix item ID links the rework back to the Master Checklist so a defect cannot be closed without work being done.
A4: Defect ID | B4: Raised date | C4: Found in item ID | D4: Product | E4: Environment | F4: Test team | G4: Severity (S1-S4) | H4: Summary | I4: Status | J4: Fix item ID | K4: Retest result | L4: Closed date | M4: Owner
A5: PROVISIONAL: DEF-001 | C5: PROVISIONAL: TST-07.1.04 | D5: PROVISIONAL: D12 | E5: PROVISIONAL: Staging | F5: QA-A11Y | G5: S2 | H5: PROVISIONAL: eBook page-turn control unreachable by keyboard | I5: Open

Sheet Environment Register
A1: Environment Register
A2: An item whose environment does not exist is unschedulable. Assign an owner and a readiness date to every row before planning the stage that needs it.
A4: Environment | B4: Purpose | C4: Deployment class served | D4: Owner | E4: Readiness date | F4: Status | G4: Cost basis (INR) | H4: Dependent items | I4: Blocking? | J4: Notes
A5: Enclave simulator | B5: Zero-egress build/test of every Enclave-class item | C5: Enclave | F5: Not funded | H5: =COUNTIF('Master Checklist'!$W:$W,"Enclave") -> 102 | I5: YES | J5: PROVISIONAL: 96+ items cannot be scheduled until this exists
A6: LMS certification | B6: Moodle / Canvas / Open edX conformance runs | C6: All | F6: Not started
A7: Lab edge (reference site) | B7: Edge server + device fleet for D20 | C7: On-prem | F7: Not started
A8: Staging | B8: Pre-production integration and UAT | C8: Cloud | F8: Not started
A9: Demo / pre-sales | B9: Synthetic-data demo estate (no customer data) | C9: Cloud | F9: Not started

Sheet Procurement & Long-Lead
A1: Procurement & Long-Lead
A2: Long-lead hardware sits on the critical path. Order-by date = stage start date minus lead time minus customs allowance. Fill unit costs in INR.
A4: Item | B4: Product | C4: Qty | D4: Unit cost (INR) | E4: Total (INR) | F4: Lead time (weeks) | G4: Needed by stage | H4: Order-by date | I4: Customs/duty allowance | J4: Vendor | K4: Status | L4: Owner
A5: PROVISIONAL: GPU inference server (AI appliance) | B5: E04 | G5: 3 | J5: PROVISIONAL: TBD | K5: Not started
A6: PROVISIONAL: XR headsets — reference site fleet | B6: D20 | G6: 3 | J6: PROVISIONAL: TBD | K6: Not started
A7: PROVISIONAL: Edge server + local package cache | B7: D20 | G7: 3 | J7: PROVISIONAL: TBD | K7: Not started
A8: PROVISIONAL: UPS + voltage stabilisation (lab) | B8: D20 | G8: 3 | J8: PROVISIONAL: TBD | K8: Not started
A9: PROVISIONAL: Replication-site fleet | B9: D21 | G9: 5 | J9: PROVISIONAL: TBD | K9: Not started

Sheet Risk & Issue Register
A1: Risk & Issue Register
A2: Carried from the architecture review so risks live where the work lives. Add issues as they arise; review on a fixed cadence.
A4: ID | B4: Type | C4: Risk / issue | D4: Affected products | E4: Probability | F4: Impact | G4: Severity | H4: Response | I4: Owner | J4: Review date | K4: Status | L4: Linked items
A5: R-001 | B5: Risk | C5: Competency-dependent work starts before the registry schema is frozen | D5: D08, D15, D23 | E5: High | F5: High | G5: P0 | H5: Freeze schema in Stage 0 before any assessment build | K5: Open | L5: TLA-01.1.01
A6: R-002 | B6: Risk | C6: Tenant isolation enforced in application code only, not at database level | D6: D18, E01 | E6: High | F6: High | G6: P0 | H6: RLS on every mart plus negative-test kit in CI | K6: Open | L6: PLT-01.3.03
A7: R-003 | B7: Risk | C7: Local open-weight models miss the hosted-model quality bar in enclaves | D7: D01, D02, E04 | E7: High | F7: High | G7: P0 | H7: GPU sizing spike with measured quality delta before commitment | K7: Open | L7: AIA-04.2.05
A8: R-004 | B8: Risk | C8: Enclave test environment unfunded and unowned | D8: All Enclave-class items | E8: High | F8: High | G8: P0 | H8: Name an owner and fund the simulator before Stage 1 exit | K8: Open | L8: —
A9: R-005 | B9: Risk | C9: GPU and XR hardware lead times exceed the stage that needs them | D9: E04, D19, D20 | E9: Medium | F9: High | G9: P1 | H9: Procurement register with order-by dates derived from stage start | K9: Open | L9: AIA-02.1.07
A10: R-006 | B10: Risk | C10: No named owners on any item — delivery cannot be tracked to a person | D10: All | E10: High | F10: High | G10: P0 | H10: Assign Stage 0–1 items this week | K10: Open | L10: —

Sheet Acceptance & Sign-off
A1: Acceptance & Sign-off
A2: One row per product. This is the record the final acceptance event and the Final Report are assembled from.
A4: ProductID | B4: Product | C4: Acceptance criteria ref | D4: Evidence bundle link | E4: Reviewer | F4: Approver | G4: Sign-off date | H4: Waivers | I4: Status
A5: D01 | B5: AI SME Chatbot — Learner-Facing | C5: See Master Checklist exit-gate items | I5: Not started
A6: D02 | B6: AI Assessment Tools & Test Banks + Auto Grader | C6: See Master Checklist exit-gate items | I6: Not started
A7: D03 | B7: Security Accreditation & Authorisation to Operate — Initiation | C7: See Master Checklist exit-gate items | I7: Not started
A8: D04 | B8: Pedagogy Design Review Protocol | C8: See Master Checklist exit-gate items | I8: Not started
A9: D05 | B9: TLA CMM Level 2 — Microservices | C9: See Master Checklist exit-gate items | I9: Not started
A10: D06 | B10: TLA Experience-Index (ELRR) | C10: See Master Checklist exit-gate items | I10: Not started
A11: D07 | B11: TLA Course Catalogue (ECC) | C11: See Master Checklist exit-gate items | I11: Not started
A12: D08 | B12: TLA Competency-Registry | C12: See Master Checklist exit-gate items | I12: Not started
A13: D09 | B13: TLA CMM Level 3 | C13: See Master Checklist exit-gate items | I13: Not started
A14: D10 | B14: PDFs & Technical Manuals Integration — Live TO Connection | C14: See Master Checklist exit-gate items | I14: Not started
A15: D11 | B15: DCT — Content Authoring & Lesson Planner | C15: See Master Checklist exit-gate items | I15: Not started
A16: D12 | B16: Interactive eBooks — Technical Manuals Digitization | C16: See Master Checklist exit-gate items | I16: Not started
... A47: E13 | B47: Internal Enablement & Knowledge Continuity | C47: See Master Checklist exit-gate items | I47: Not started

Sheet Skills Matrix
A1: Skills Matrix
A2: Rate 0–3 per capability. Any capability with a single person at level 2+ is a bus-factor risk — flag it and pair someone.
A4: Person | B4: Squad | C4: LTI 1.3 | D4: xAPI / LRS | E4: Metabase / BI | F4: PostgreSQL + RLS | G4: Model ops (vLLM) | H4: XR / Unity | I4: React Native | J4: Indic NLP | K4: Accessibility | L4: Security | M4: Instructional design | N4: Bus factor risk
A5: PROVISIONAL: <name> | B5: SQ1 Platform Core

Sheet Weekly Snapshot
A1: Weekly Snapshot
A2: Paste values (not formulas) every Friday. Without history there is no trend, no velocity and no forecast.
A4: Week ending | B4: Total items | C4: Done | D4: In progress | E4: Blocked | F4: % done | G4: P0 open | H4: Defects open | I4: Notes
A5: PROVISIONAL: <date> | B5: =2120 -> 2120 | I5: PROVISIONAL: paste values each Friday — do not link, this sheet is history

Sheet Coverage Register
A1: Source item | B1: Type | C1: Items | D1: Status / implementing IDs | E1: Product name
A2: D01 | B2: Client deliverable | C2: 103 | D2: Covered | E2: AI SME Chatbot — Learner-Facing
A3: D02 | B3: Client deliverable | C3: 98 | D3: Covered | E3: AI Assessment Tools & Test Banks + Auto Grader
A4: D03 | B4: Client deliverable | C4: 17 | D4: Covered | E4: Security Accreditation & Authorisation to Operate — Initiation
A5: D04 | B5: Client deliverable | C5: 13 | D5: Covered | E5: Pedagogy Design Review Protocol
A6: D05 | B6: Client deliverable | C6: 13 | D6: Covered | E6: TLA CMM Level 2 — Microservices
A7: D06 | B7: Client deliverable | C7: 36 | D7: Covered | E7: TLA Experience-Index (ELRR)
A8: D07 | B8: Client deliverable | C8: 32 | D8: Covered | E8: TLA Course Catalogue (ECC)
A9: D08 | B9: Client deliverable | C9: 62 | D9: Covered | E9: TLA Competency-Registry
A10: D09 | B10: Client deliverable | C10: 5 | D10: Covered | E10: TLA CMM Level 3
A11: D10 | B11: Client deliverable | C11: 32 | D11: Covered | E11: PDFs & Technical Manuals Integration — Live TO Connection
A12: D11 | B12: Client deliverable | C12: 44 | D12: Covered | E12: DCT — Content Authoring & Lesson Planner
A13: D12 | B13: Client deliverable | C13: 76 | D13: Covered | E13: Interactive eBooks — Technical Manuals Digitization
... A44: E13 | B44: Enabling programme | C44: 12 | D44: Covered | E44: Internal Enablement & Knowledge Continuity
A45: M1 | B45: Module | C45: 37 | D45: Covered
A46: M2 | B46: Module | C46: 39 | D46: Covered
A47: M3 | B47: Module | C47: 47 | D47: Covered
A48: M4 | B48: Module | C48: 37 | D48: Covered
A49: M5 | B49: Module | C49: 27 | D49: Covered
A50: M6 | B50: Module | C50: 94 | D50: Covered
A51: M7 | B51: Module | C51: 51 | D51: Covered
A52: M8 | B52: Module | C52: 52 | D52: Covered
A53: M9 | B53: Module | C53: 41 | D53: Covered
A54: M10 | B54: Module | C54: 21 | D54: Covered
A55: M11 | B55: Module | C55: 39 | D55: Covered
A56: M12 | B56: Module | C56: 35 | D56: Covered
... A122: MOD-016 | B122: Review modification | C122: 11 | D122: Covered
A123: Loop 6 — India re-basing | B123: Audit remediation | C123: — | D123: 150 items added across D20/D21/E12/D08/E10/E06/D17/D03
A124: Loop 8 — scope gaps | B124: Audit remediation | C124: — | D124: 140 items added across E08/E09/E10/E11/E13/D25/D29
A125: HS-9 (accreditation authority) | B125: Audit remediation | C125: — | D125: Deferred by direction; product renamed market-neutral, authority is a Human-Input entry
A126: HS-10 (replication gating) | B126: Audit remediation | C126: — | D126: Structural: D21 items depend on the D20 reference-validation gate

Sheet Open Questions
A1: Open Questions
A2: An unanswered question older than 30 days is a decision failure, not a research task. Assign an owner and a due date to each.
A4: # | B4: Area | C4: Question | D4: Blocks (products) | E4: Owner | F4: Due | G4: Status
A5: 1 | B5: Ownership | C5: Who are the nine squad and test-team leads, and who owns each of the 43 products? | D5: All — no item can be assigned without this | G5: Open
A6: 2 | B6: Scheduling | C6: What is the sprint cadence and start date, so TargetSprint resolves to real dates? | D6: All | G6: Open
A7: 3 | B7: Environments | C7: Who owns and funds the zero-egress enclave simulator? | D7: All Enclave-class items | G7: Open
A8: 4 | B8: Localization | C8: What is the committed language tier matrix (UI / content / AI / assessment / support)? | D8: E06, D12, D19, D24, D01, D02 | G8: Open
A9: 5 | B9: Competency | C9: Which Indian frameworks (NSQF levels, NCVET packs, SSC job roles) are in scope, and with what usage rights? | D9: D08, D15, D23 | G9: Open
A10: 6 | B10: Legal | C10: Data-fiduciary vs processor role per engagement model, and DPA template review by Indian counsel? | D10: E10, D16, D17 | G10: Open
A11: 7 | B11: Hosting | C11: Is an India-hosted / MeitY-empanelled deployment option required, and for which customers? | D11: E10, E01 | G11: Open
A12: 8 | B12: Sites | C12: Which physical sites are the reference and replication labs, and who funds them? | D12: D20, D21, E12 | G12: Open
A13: 9 | B13: Procurement | C13: Who owns the GPU and XR hardware budget, and what are the actual lead times? | D13: E04, D19, D20, D21 | G13: Open
A14: 10 | B14: Commercial | C14: What is the pricing and licence model per Indian buyer segment? | D14: E10 | G14: Open
A15: 11 | B15: Content | C15: Which authoritative technical-manual repository backs the Live TO connection? | D15: D10, D12 | G15: Open
A16: 12 | B16: Content | C16: What supersession SLA and maximum enclave content staleness applies, set by which authority? | D16: D10, D01 | G16: Open
... A24: 20 | B24: Accreditation | C24: Which authority and control baseline apply (deferred by direction — reopen when ready)? | D24: D03 | G24: Open

Sheet Change Log
A1: Change Log
A2: Every modification applied in v3. Add a row for every future scope change, with requester and approver in the description.
A4: Change ID | B4: Type | C4: Description | D4: Before | E4: After | F4: Affected
A5: CHG-D03 | B5: Rename | C5: Product D03 re-based for the India market / market-neutral naming | D5: ATO Initiation — AFGSC | E5: Security Accreditation & Authorisation to Operate — Initiation | F5: all D03 rows
A6: CHG-D17 | B6: Rename | C6: Product D17 re-based for the India market / market-neutral naming | D6: Cross-Command Data Pipeline | E6: Cross-Organisation / Cross-Command Data Pipeline | F6: all D17 rows
A7: CHG-D20 | B7: Rename | C7: Product D20 re-based for the India market / market-neutral naming | D7: Hardware Immersive Labs — Site A (Barksdale AFB) | E7: Immersive Lab — Reference Site (India) | F7: all D20 rows
A8: CHG-D21 | B8: Rename | C8: Product D21 re-based for the India market / market-neutral naming | D8: Hardware Immersive Labs — Site B (Minot AFB) | E8: Immersive Lab — Replication Site (India) | F8: all D21 rows
A9: CHG-E08 | B9: New product | C9: Enabling product created to hold previously unplanned scope | D9: (did not exist) | E9: Customer Onboarding, Tenant Provisioning & Data Migration | F9: see new items
A10: CHG-E09 | B10: New product | C10: Enabling product created to hold previously unplanned scope | D10: (did not exist) | E10: Support, Service Management & Operational Handover | F10: see new items
A11: CHG-E10 | B11: New product | C11: Enabling product created to hold previously unplanned scope | D11: (did not exist) | E11: Commercial, Legal & Compliance (India) | F11: see new items
A12: CHG-E11 | B12: New product | C12: Enabling product created to hold previously unplanned scope | D12: (did not exist) | E12: Vendor, Third-Party & Content-Rights Management | F12: see new items
A13: CHG-E12 | B13: New product | C13: Enabling product created to hold previously unplanned scope | D13: (did not exist) | E13: Site Deployment Kit — Repeatable Immersive Lab (India) | F13: see new items
A14: CHG-E13 | B14: New product | C14: Enabling product created to hold previously unplanned scope | D14: (did not exist) | E14: Internal Enablement & Knowledge Continuity | F14: see new items
A15: CHG-ITEMS | B15: New items | C15: India re-basing items added (audit Loop 6) | D15: 1830 items | E15: +150 | F15: FLD/TLA/PRG/FED 90-series
A16: CHG-ITEMS2 | B16: New items | C16: Scope-gap items added (audit Loop 8) | E16: +140 | F16: PRG/PLT/CNT/FLD/ANA 90-series
A17: CHG-DEP | B17: Data fix | C17: Mis-pointed symbolic dependency references corrected to the true contract-freeze items (FND-03.1.01→FND-07.1.01 M3 event envelope; TLA-03.1.01→TLA-01.1.01 competency object model) | D17: 22 inverted refs | E17: 22 repointed | F17: FND/TLA dependents
A18: CHG-COL | B18: New columns | C18: Priority (derived: HS→P0, MOD/Scenario→P1, Stage0→P1, else P2), EvidenceLink, TestCaseID, Waiver, LastUpdated, SeqFlag, Notes appended | D18: 22 columns | E18: 29 columns | F18: all rows
A19: CHG-ID | B19: Data fix | C19: ID collision between two new-item sets resolved before issue (benefits-realisation task renumbered) | D19: PRG-93.x used twice | E19: PRG-89.x | F19: 9 new items
A20: CHG-SEQ | B20: Data quality | C20: Remaining stage-sequence exceptions flagged for squad-lead resolution | D20: 53 inversions | E20: 40 flagged | F20: SeqFlag column
A21: CHG-VAL | B21: Control | C21: Data validation added on Squad, OwnerRole, TestTeam, DeploymentClass, Status, Priority, WorkType via named ranges on a new Lists sheet | D21: Status only | E21: 7 validated columns + Lists sheet | F21: Master Checklist
A22: CHG-CF | B22: Control | C22: Conditional formatting: Blocked=red, Done=green, unassigned Stage 0-1=amber, sequence exception=orange | D22: none | E22: 4 rules | F22: Master Checklist
A23: CHG-PROT | B23: Control | C23: Sheet protection enabled (no password): ID column locked, all other cells editable, filter and sort allowed | D23: none | E23: ID column immutable | F23: Master Checklist

Sheet Lists
A1: Controlled vocabularies (named ranges) — edit here, dropdowns update everywhere
A3: SquadList | B3: RoleList | C3: TestTeamList | D3: DeployList | E3: StatusList | F3: PriorityList | G3: WorkTypeList | H3: SeverityList | I3: YesNoList
A4: SQ1 Platform Core | B4: AI/ML Engineer | C4: QA-FUNC | D4: All | E4: Not started | F4: P0 | G4: Build | H4: S1 | I4: Yes
A5: SQ2 Learning Tools | B5: Accessibility Specialist | C5: QA-AUTO | D5: Cloud | E5: In progress | F5: P1 | G5: Test | H5: S2 | I5: No
A6: SQ3 Data & Analytics | B6: BI Engineer | C6: QA-DATA | D6: On-prem | E6: Done | F6: P2 | H6: S3 | I6: N/A
A7: SQ4 TLA & Federation | B7: Backend Engineer | C7: QA-PERF | D7: Enclave | E7: Blocked | F7: P3 | H7: S4
A8: SQ5 AI & Assessment | B8: Content Engineer | C8: QA-SEC | E8: Superseded
A9: SQ6 Content & Authoring | B9: Data Engineer | C9: QA-A11Y
A10: SQ7 Field & Immersive | B10: DevSecOps Engineer | C10: QA-AI
A11: SQ8 Program & Governance | B11: Frontend Engineer | C11: QA-OPS
A12: QA Guild | B12: Instructional Designer | C12: UAT
B13: Mobile/XR Engineer | C13: —
B14: Platform Architect
B15: Product Manager
B16: Program Manager
B17: QA Engineer
B18: QA Lead
B19: SME Lead
B20: Security Engineer
B21: Site Engineer
B22: Technical Writer

Sheet How to use & improve
A1: v3 — what changed, how to run it, what you must fill in
A3: WHAT CHANGED IN v3
A4: India re-basing | B4: The two lab deliverables are no longer named foreign installations. D20 is the Immersive Lab — Reference Site (India), built to a documented reference design and validated; D21 is the Replication Site, deliverable only as a controlled replication. E12 (Site Deployment Kit) makes lab number three a repeatable product: site survey, bill of materials, install runbook, commissioning checklist, handover pack, AMC and spares. 150 India items added — power quality and UPS/generator cutover, thermal/humidity/dust protection, customs and duty lead times, GST and interstate logistics, four deployment contexts (enterprise, ITI/polytechnic, university, secure site), NSQF/NCVET competency fixtures, DPDP obligations, India-hosting option, and the language tier matrix.
A5: Market-neutral naming | B5: D03 is now Security Accreditation & Authorisation to Operate — Initiation (no foreign command named; the authority is an open decision, deferred by direction). D17 is Cross-Organisation / Cross-Command Data Pipeline so it serves multi-campus and multi-plant federations as well as command structures.
A6: Scope nobody had planned | B6: 140 items added under six new enabling products: E08 onboarding/provisioning/data migration, E09 support and operational handover, E10 commercial and legal (India), E11 vendor and content-rights management, E12 site deployment kit, E13 internal enablement. Also BCDR exercises as recurring scheduled work, content IP clearance gates, benefits realisation, and pilot-to-production cutover.
A7: Delivery machinery | B7: Eleven new sheets: Sprint Calendar, Capacity Plan, Defect Log, Environment Register, Stage Gates, Risk & Issue Register, Procurement & Long-Lead, Weekly Snapshot, Acceptance & Sign-off, Skills Matrix, Change Log — plus a Lists sheet driving controlled vocabularies.
A8: Columns and controls | B8: Seven new columns (Priority, TestCaseID, EvidenceLink, Waiver, LastUpdated, SeqFlag, Notes). Dropdown validation on seven columns. Conditional formatting: Blocked red, Done green, unassigned Stage 0–1 amber, sequence exception orange. ID column locked; everything else editable; no password.
A9: Data fixes | B9: 22 mis-pointed dependency references corrected to the true contract-freeze items. Remaining stage-sequence exceptions are flagged in SeqFlag for squad-lead resolution rather than silently rewritten.
A11: WHAT YOU MUST FILL IN — IN THIS ORDER
A12: 1. Owners | B12: Assignee on every Stage 0 and Stage 1 row; the nine squad/test-team leads on Teams & Roster; product owner, tech lead and QA lead on Product Index. Until this is done the Summary 'Unassigned' column is your only honest status.
A13: 2. Sprint calendar | B13: One row per sprint with real dates. Then TargetSprint on Stage 0 items. This is what turns the checklist into a schedule.
A14: 3. Estimates | B14: EstDays on Stage 0–1 items first. Capacity Plan then shows over-allocation before it happens.
A15: 4. Environments | B15: Owner and readiness date on every Environment Register row — starting with the enclave simulator, which currently blocks every Enclave-class item.
A16: 5. Procurement | B16: Lead times and INR costs on the long-lead register, then order-by dates. GPU and XR hardware must be ordered well before the stage that needs them.
A17: 6. Open questions | B17: Assign an owner and due date to each. The top five block work that is already in Stage 0.
A19: OPERATING RHYTHM
A20: Monday | B20: Squad leads filter by Squad + Stage, set TargetSprint, clear Blocked rows.
A21: Wednesday | B21: QA leads filter by TestTeam; review the Defect Log; check retest results.
A22: Friday | B22: PMO pastes a Weekly Snapshot row, reviews Stage Gates and Product Index, and reviews any row where SeqFlag is set.
A23: Monthly | B23: Risk review, open-question ageing, coverage re-check after any scope change, and a Change Log entry for every scope movement.
A25: WHEN TO LEAVE THE WORKBOOK
A26: Migration trigger | B26: Move to Jira/Azure DevOps when more than three people need to edit concurrently, or when defect volume passes roughly fifty open items, or when an auditor asks for change history the workbook cannot prove. Map ProductID→Epic, Task→Story, Item→Sub-task, Squad→Team, TestTeam→Component, DependsOn→Issue link, Stage→Fix version. Keep this workbook as the source of record for acceptance criteria and coverage.
