Workbook

Sheet Summary
A1: EdVidura Builder Clarification Bank — the questions the team needs answered to build
A2: 2,703 clarifications · 41 products + cross-cutting concerns · 17 roles (incl. UI/UX Designer) · 4 levels · 12 lifecycle stages
A3: Written in the builder's voice: every row asks outward for a decision, names the work it blocks, and carries a proposed default so silence does not stop the sprint.
A4: YELLOW columns are yours: AnsweredBy, AnswerDate, DecisionRecord. Change Status as answers arrive.
A6: Headline
A7: Total clarifications | B7: 2703
A8: Blockers — work cannot start | B8: 1132
A9: Hard blockers — no default is possible | B9: 163
A10: Questions nobody currently owns | B10: 139
A11: Needed before sprint 0 | B11: 246
A12: Needed before first code | B12: 839
A13: UI/UX clarifications | B13: 383
A14: Second-wave / seam questions | B14: 1084
A17: By role (live)
A18: Code | B18: Role | C18: Total | D18: L1 | E18: L2 | F18: L3 | G18: L4 | H18: Blockers | I18: Before sprint 0 | J18: Answered
A19: FE | B19: Front-End Developer | C19: =COUNTIF('Clarification Bank'!$D:$D,$A19) -> 156 | D19: =COUNTIFS('Clarification Bank'!$D:$D,$A19,'Clarification Bank'!$F:$F,"L1 Junior") -> 33 | E19: =COUNTIFS('Clarification Bank'!$D:$D,$A19,'Clarification Bank'!$F:$F,"L2 Mid") -> 81 | F19: =COUNTIFS('Clarification Bank'!$D:$D,$A19,'Clarification Bank'!$F:$F,"L3 Senior") -> 21 | G19: =COUNTIFS('Clarification Bank'!$D:$D,$A19,'Clarification Bank'!$F:$F,"L4 Architect") -> 21 | H19: =COUNTIFS('Clarification Bank'!$D:$D,$A19,'Clarification Bank'!$H:$H,"Blocker") -> 55 | I19: =COUNTIFS('Clarification Bank'!$D:$D,$A19,'Clarification Bank'!$I:$I,"Before sprint 0") -> 6 | J19: =COUNTIFS('Clarification Bank'!$D:$D,$A19,'Clarification Bank'!$S:$S,"Answered") -> 0
A20: BE | B20: Back-End Developer | C20: =COUNTIF('Clarification Bank'!$D:$D,$A20) -> 342 | D20: =COUNTIFS('Clarification Bank'!$D:$D,$A20,'Clarification Bank'!$F:$F,"L1 Junior") -> 33 | E20: =COUNTIFS('Clarification Bank'!$D:$D,$A20,'Clarification Bank'!$F:$F,"L2 Mid") -> 197 | F20: =COUNTIFS('Clarification Bank'!$D:$D,$A20,'Clarification Bank'!$F:$F,"L3 Senior") -> 79 | G20: =COUNTIFS('Clarification Bank'!$D:$D,$A20,'Clarification Bank'!$F:$F,"L4 Architect") -> 33 | H20: =COUNTIFS('Clarification Bank'!$D:$D,$A20,'Clarification Bank'!$H:$H,"Blocker") -> 179 | I20: =COUNTIFS('Clarification Bank'!$D:$D,$A20,'Clarification Bank'!$I:$I,"Before sprint 0") -> 16 | J20: =COUNTIFS('Clarification Bank'!$D:$D,$A20,'Clarification Bank'!$S:$S,"Answered") -> 0
A21: DE | B21: Data Engineer | C21: =COUNTIF('Clarification Bank'!$D:$D,$A21) -> 164 | D21: =COUNTIFS('Clarification Bank'!$D:$D,$A21,'Clarification Bank'!$F:$F,"L1 Junior") -> 21 | E21: =COUNTIFS('Clarification Bank'!$D:$D,$A21,'Clarification Bank'!$F:$F,"L2 Mid") -> 74 | F21: =COUNTIFS('Clarification Bank'!$D:$D,$A21,'Clarification Bank'!$F:$F,"L3 Senior") -> 48 | G21: =COUNTIFS('Clarification Bank'!$D:$D,$A21,'Clarification Bank'!$F:$F,"L4 Architect") -> 21 | H21: =COUNTIFS('Clarification Bank'!$D:$D,$A21,'Clarification Bank'!$H:$H,"Blocker") -> 93 | I21: =COUNTIFS('Clarification Bank'!$D:$D,$A21,'Clarification Bank'!$I:$I,"Before sprint 0") -> 7 | J21: =COUNTIFS('Clarification Bank'!$D:$D,$A21,'Clarification Bank'!$S:$S,"Answered") -> 0
A22: BI | B22: BI / Analytics Developer (Metabase) | C22: =COUNTIF('Clarification Bank'!$D:$D,$A22) -> 92 | D22: =COUNTIFS('Clarification Bank'!$D:$D,$A22,'Clarification Bank'!$F:$F,"L1 Junior") -> 21 | E22: =COUNTIFS('Clarification Bank'!$D:$D,$A22,'Clarification Bank'!$F:$F,"L2 Mid") -> 29 | F22: =COUNTIFS('Clarification Bank'!$D:$D,$A22,'Clarification Bank'!$F:$F,"L3 Senior") -> 21 | G22: =COUNTIFS('Clarification Bank'!$D:$D,$A22,'Clarification Bank'!$F:$F,"L4 Architect") -> 21 | H22: =COUNTIFS('Clarification Bank'!$D:$D,$A22,'Clarification Bank'!$H:$H,"Blocker") -> 22 | I22: =COUNTIFS('Clarification Bank'!$D:$D,$A22,'Clarification Bank'!$I:$I,"Before sprint 0") -> 6 | J22: =COUNTIFS('Clarification Bank'!$D:$D,$A22,'Clarification Bank'!$S:$S,"Answered") -> 0
A23: DA | B23: Data Analyst | C23: =COUNTIF('Clarification Bank'!$D:$D,$A23) -> 100 | D23: =COUNTIFS('Clarification Bank'!$D:$D,$A23,'Clarification Bank'!$F:$F,"L1 Junior") -> 21 | E23: =COUNTIFS('Clarification Bank'!$D:$D,$A23,'Clarification Bank'!$F:$F,"L2 Mid") -> 32 | F23: =COUNTIFS('Clarification Bank'!$D:$D,$A23,'Clarification Bank'!$F:$F,"L3 Senior") -> 26 | G23: =COUNTIFS('Clarification Bank'!$D:$D,$A23,'Clarification Bank'!$F:$F,"L4 Architect") -> 21 | H23: =COUNTIFS('Clarification Bank'!$D:$D,$A23,'Clarification Bank'!$H:$H,"Blocker") -> 35 | I23: =COUNTIFS('Clarification Bank'!$D:$D,$A23,'Clarification Bank'!$I:$I,"Before sprint 0") -> 9 | J23: =COUNTIFS('Clarification Bank'!$D:$D,$A23,'Clarification Bank'!$S:$S,"Answered") -> 0
A24: AI | B24: AI/ML Engineer | C24: =COUNTIF('Clarification Bank'!$D:$D,$A24) -> 146 | D24: =COUNTIFS('Clarification Bank'!$D:$D,$A24,'Clarification Bank'!$F:$F,"L1 Junior") -> 21 | E24: =COUNTIFS('Clarification Bank'!$D:$D,$A24,'Clarification Bank'!$F:$F,"L2 Mid") -> 44 | F24: =COUNTIFS('Clarification Bank'!$D:$D,$A24,'Clarification Bank'!$F:$F,"L3 Senior") -> 55 | G24: =COUNTIFS('Clarification Bank'!$D:$D,$A24,'Clarification Bank'!$F:$F,"L4 Architect") -> 26 | H24: =COUNTIFS('Clarification Bank'!$D:$D,$A24,'Clarification Bank'!$H:$H,"Blocker") -> 95 | I24: =COUNTIFS('Clarification Bank'!$D:$D,$A24,'Clarification Bank'!$I:$I,"Before sprint 0") -> 17 | J24: =COUNTIFS('Clarification Bank'!$D:$D,$A24,'Clarification Bank'!$S:$S,"Answered") -> 0
A25: AIG | B25: AI Generalist | C25: =COUNTIF('Clarification Bank'!$D:$D,$A25) -> 84 | D25: =COUNTIFS('Clarification Bank'!$D:$D,$A25,'Clarification Bank'!$F:$F,"L1 Junior") -> 21 | E25: =COUNTIFS('Clarification Bank'!$D:$D,$A25,'Clarification Bank'!$F:$F,"L2 Mid") -> 21 | F25: =COUNTIFS('Clarification Bank'!$D:$D,$A25,'Clarification Bank'!$F:$F,"L3 Senior") -> 21 | G25: =COUNTIFS('Clarification Bank'!$D:$D,$A25,'Clarification Bank'!$F:$F,"L4 Architect") -> 21 | H25: =COUNTIFS('Clarification Bank'!$D:$D,$A25,'Clarification Bank'!$H:$H,"Blocker") -> 38 | I25: =COUNTIFS('Clarification Bank'!$D:$D,$A25,'Clarification Bank'!$I:$I,"Before sprint 0") -> 6 | J25: =COUNTIFS('Clarification Bank'!$D:$D,$A25,'Clarification Bank'!$S:$S,"Answered") -> 0
A26: MXR | B26: Mobile & XR Developer | C26: =COUNTIF('Clarification Bank'!$D:$D,$A26) -> 92 | D26: =COUNTIFS('Clarification Bank'!$D:$D,$A26,'Clarification Bank'!$F:$F,"L1 Junior") -> 21 | E26: =COUNTIFS('Clarification Bank'!$D:$D,$A26,'Clarification Bank'!$F:$F,"L2 Mid") -> 29 | F26: =COUNTIFS('Clarification Bank'!$D:$D,$A26,'Clarification Bank'!$F:$F,"L3 Senior") -> 21 | G26: =COUNTIFS('Clarification Bank'!$D:$D,$A26,'Clarification Bank'!$F:$F,"L4 Architect") -> 21 | H26: =COUNTIFS('Clarification Bank'!$D:$D,$A26,'Clarification Bank'!$H:$H,"Blocker") -> 47 | I26: =COUNTIFS('Clarification Bank'!$D:$D,$A26,'Clarification Bank'!$I:$I,"Before sprint 0") -> 12 | J26: =COUNTIFS('Clarification Bank'!$D:$D,$A26,'Clarification Bank'!$S:$S,"Answered") -> 0
A27: DEVOPS | B27: DevSecOps / Platform Engineer | C27: =COUNTIF('Clarification Bank'!$D:$D,$A27) -> 168 | D27: =COUNTIFS('Clarification Bank'!$D:$D,$A27,'Clarification Bank'!$F:$F,"L1 Junior") -> 21 | E27: =COUNTIFS('Clarification Bank'!$D:$D,$A27,'Clarification Bank'!$F:$F,"L2 Mid") -> 56 | F27: =COUNTIFS('Clarification Bank'!$D:$D,$A27,'Clarification Bank'!$F:$F,"L3 Senior") -> 70 | G27: =COUNTIFS('Clarification Bank'!$D:$D,$A27,'Clarification Bank'!$F:$F,"L4 Architect") -> 21 | H27: =COUNTIFS('Clarification Bank'!$D:$D,$A27,'Clarification Bank'!$H:$H,"Blocker") -> 59 | I27: =COUNTIFS('Clarification Bank'!$D:$D,$A27,'Clarification Bank'!$I:$I,"Before sprint 0") -> 16 | J27: =COUNTIFS('Clarification Bank'!$D:$D,$A27,'Clarification Bank'!$S:$S,"Answered") -> 0
A28: SEC | B28: Security Engineer | C28: =COUNTIF('Clarification Bank'!$D:$D,$A28) -> 172 | D28: =COUNTIFS('Clarification Bank'!$D:$D,$A28,'Clarification Bank'!$F:$F,"L1 Junior") -> 21 | E28: =COUNTIFS('Clarification Bank'!$D:$D,$A28,'Clarification Bank'!$F:$F,"L2 Mid") -> 44 | F28: =COUNTIFS('Clarification Bank'!$D:$D,$A28,'Clarification Bank'!$F:$F,"L3 Senior") -> 83 | G28: =COUNTIFS('Clarification Bank'!$D:$D,$A28,'Clarification Bank'!$F:$F,"L4 Architect") -> 24 | H28: =COUNTIFS('Clarification Bank'!$D:$D,$A28,'Clarification Bank'!$H:$H,"Blocker") -> 102 | I28: =COUNTIFS('Clarification Bank'!$D:$D,$A28,'Clarification Bank'!$I:$I,"Before sprint 0") -> 8 | J28: =COUNTIFS('Clarification Bank'!$D:$D,$A28,'Clarification Bank'!$S:$S,"Answered") -> 0
A29: QA | B29: QA / Test Engineer | C29: =COUNTIF('Clarification Bank'!$D:$D,$A29) -> 134 | D29: =COUNTIFS('Clarification Bank'!$D:$D,$A29,'Clarification Bank'!$F:$F,"L1 Junior") -> 21 | E29: =COUNTIFS('Clarification Bank'!$D:$D,$A29,'Clarification Bank'!$F:$F,"L2 Mid") -> 65 | F29: =COUNTIFS('Clarification Bank'!$D:$D,$A29,'Clarification Bank'!$F:$F,"L3 Senior") -> 27 | G29: =COUNTIFS('Clarification Bank'!$D:$D,$A29,'Clarification Bank'!$F:$F,"L4 Architect") -> 21 | H29: =COUNTIFS('Clarification Bank'!$D:$D,$A29,'Clarification Bank'!$H:$H,"Blocker") -> 32 | I29: =COUNTIFS('Clarification Bank'!$D:$D,$A29,'Clarification Bank'!$I:$I,"Before sprint 0") -> 2 | J29: =COUNTIFS('Clarification Bank'!$D:$D,$A29,'Clarification Bank'!$S:$S,"Answered") -> 0
A30: SDET | B30: Test Architect / SDET | C30: =COUNTIF('Clarification Bank'!$D:$D,$A30) -> 124 | D30: =COUNTIFS('Clarification Bank'!$D:$D,$A30,'Clarification Bank'!$F:$F,"L1 Junior") -> 21 | E30: =COUNTIFS('Clarification Bank'!$D:$D,$A30,'Clarification Bank'!$F:$F,"L2 Mid") -> 30 | F30: =COUNTIFS('Clarification Bank'!$D:$D,$A30,'Clarification Bank'!$F:$F,"L3 Senior") -> 52 | G30: =COUNTIFS('Clarification Bank'!$D:$D,$A30,'Clarification Bank'!$F:$F,"L4 Architect") -> 21 | H30: =COUNTIFS('Clarification Bank'!$D:$D,$A30,'Clarification Bank'!$H:$H,"Blocker") -> 40 | I30: =COUNTIFS('Clarification Bank'!$D:$D,$A30,'Clarification Bank'!$I:$I,"Before sprint 0") -> 2 | J30: =COUNTIFS('Clarification Bank'!$D:$D,$A30,'Clarification Bank'!$S:$S,"Answered") -> 0
... A35: UXD | B35: UI/UX Designer | C35: =COUNTIF('Clarification Bank'!$D:$D,$A35) -> 315 | D35: =COUNTIFS('Clarification Bank'!$D:$D,$A35,'Clarification Bank'!$F:$F,"L1 Junior") -> 31 | E35: =COUNTIFS('Clarification Bank'!$D:$D,$A35,'Clarification Bank'!$F:$F,"L2 Mid") -> 172 | F35: =COUNTIFS('Clarification Bank'!$D:$D,$A35,'Clarification Bank'!$F:$F,"L3 Senior") -> 91 | G35: =COUNTIFS('Clarification Bank'!$D:$D,$A35,'Clarification Bank'!$F:$F,"L4 Architect") -> 21 | H35: =COUNTIFS('Clarification Bank'!$D:$D,$A35,'Clarification Bank'!$H:$H,"Blocker") -> 102 | I35: =COUNTIFS('Clarification Bank'!$D:$D,$A35,'Clarification Bank'!$I:$I,"Before sprint 0") -> 8 | J35: =COUNTIFS('Clarification Bank'!$D:$D,$A35,'Clarification Bank'!$S:$S,"Answered") -> 0
B36: TOTAL | C36: =SUM(C19:C35) -> 2703 | D36: =SUM(D19:D35) -> 391 | E36: =SUM(E19:E35) -> 1092 | F36: =SUM(F19:F35) -> 810 | G36: =SUM(G19:G35) -> 410 | H36: =SUM(H19:H35) -> 1132 | I36: =SUM(I19:I35) -> 246 | J36: =SUM(J19:J35) -> 0
A38: By answerer — this is your meeting list
A39: Addressed to | B39: Questions | C39: Blockers | D39: Hard blockers | E39: Before sprint 0
A40: Solution Architect | B40: 598 | C40: 276 | D40: 2 | E40: 41
A41: Product Owner | B41: 564 | C41: 162 | D41: 4 | E41: 48
A42: Programme Manager | B42: 422 | C42: 108 | D42: 10 | E42: 73
A43: Security/Accreditation | B43: 243 | C43: 127 | D43: 7 | E43: 9
A44: Legal & Compliance | B44: 195 | C44: 105 | D44: 9 | E44: 13
A45: Client SME | B45: 151 | C45: 84 | D45: 29 | E45: 26
A46: Instructional Designer | B46: 150 | C46: 57 | D46: 0 | E46: 3
A47: Data Owner | B47: 149 | C47: 63 | D47: 1 | E47: 0
A48: NOBODY OWNS THIS | B48: 139 | C48: 120 | D48: 101 | E48: 30
A49: Another squad | B49: 91 | C49: 30 | D49: 0 | E49: 3
A50: Vendor | B50: 1 | C50: 0 | D50: 0 | E50: 0

Sheet Critical Answer Path
A1: Critical Answer Path
A2: The hard blockers, in the order they are needed. These cannot be defaulted — you cannot invent a customer's LMS, a competency framework, a GPU budget or an accrediting authority. Answer these and the largest amount of blocked work moves. Ordered by when it is needed, then by product.
A4: # | B4: Needed by | C4: ProductID | D4: Product | E4: Question — no default is possible | F4: Who must answer | G4: What it blocks | H4: Answer must arrive as | I4: CQID | J4: Answered? | K4: Date
A5: 1 | B5: Before sprint 0 | C5: D01 | D5: AI SME Chatbot — Learner-Facing | E5: What GPU hardware will actually be in the enclave appliance - count, model and VRAM - because I cannot size batch, context window or resident model count without it? | F5: NOBODY OWNS THIS | G5: I cannot size anything: context length, concurrency, resident models, or whether chat and grading co-reside | H5: signed document | I5: CQC0012
A6: 2 | B6: Before sprint 0 | C6: D02 | D6: AI Assessment Tools & Test Banks + Auto Grader | E6: Should grading run on a larger model than the chatbot on the same appliance, or must both share one model - because this decision drives VRAM and therefore procurement? | F6: NOBODY OWNS THIS | G6: I cannot write the sizing memo, and procurement with a two-quarter lead time cannot start | H6: decision record | I6: CQC0045
A7: 3 | B7: Before sprint 0 | C7: D03 | D7: Security Accreditation & Authorisation to Operate — Initiation | E7: Which organisation actually issues the Authorisation to Operate for EdVidura at customer one - name the accrediting body and the role title of the officer who signs it - because until I have that name I cannot tell you which control catalogue, which templates or which submission route the package must use? | F7: NOBODY OWNS THIS | G7: Every artefact in D03 - I cannot start the System Security Plan, the risk assessment or the evidence index without knowing whose format they must be in | H7: named person | I7: CQF0001
A8: 4 | B8: Before sprint 0 | C8: D03 | D8: Security Accreditation & Authorisation to Operate — Initiation | E8: Which control baseline are we assessed against - ISO/IEC 27001:2022 Annex A, NIST SP 800-53 Rev 5 at Moderate, CERT-In plus MeitY guidance, or a customer-specific catalogue - and is that choice ours or theirs? | F8: NOBODY OWNS THIS | G8: The control-to-evidence mapping spreadsheet, the SSP structure and the scope of the gap assessment | H8: signed document | I8: CQF0002
A9: 5 | B9: Before sprint 0 | C9: D04 | D9: Pedagogy Design Review Protocol | E9: Who is the assessor - a named instructional designer, a panel, or the customer training authority - because a protocol with no named reviewer is a document nobody executes? | F9: NOBODY OWNS THIS | G9: The whole operating model of the protocol and the queue design behind it | H9: named person | I9: CQD0171
A10: 6 | B10: Before sprint 0 | C10: D05 | D10: TLA CMM Level 2 — Microservices | E10: Who is the assessor - an EdVidura independent reviewer, a customer body, or an external accreditation authority - and have they been engaged or is that name still blank? | F10: NOBODY OWNS THIS | G10: the assessment date, the evidence deadline and the whole L2 critical path | H10: named person | I10: CQA0111
A11: 7 | B11: Before sprint 0 | C11: D05 | D11: TLA CMM Level 2 — Microservices | E11: Which published version of the TLA Capability Maturity Model are we being assessed against, and can somebody send me the document - because I cannot write conformance criteria against a model I have not read. | F11: Client SME | G11: every criterion, every evidence item and the scoring rubric | H11: link to existing spec | I11: CQA0110
A12: 8 | B12: Before sprint 0 | C12: D07 | D12: TLA Course Catalogue (ECC) | E12: How many courses are in customer one catalogue today and how many organisations own them - because ten owners and two hundred courses is a very different product from two hundred owners and twenty thousand? | F12: Client SME | G12: the search design, the governance model and the onboarding plan | H12: number with units | I12: CQB0055
A13: 9 | B13: Before sprint 0 | C13: D08 | D13: TLA Competency-Registry | E13: Who at the customer is the competency authority - the person who can say this competency exists and this is what it means - because every rule in this product needs their name against it? | F13: Client SME | G13: the approval workflows, the deprecation process and the adjudication path | H13: named person | I13: CQB0094
A14: 10 | B14: Before sprint 0 | C14: D08 | D14: TLA Competency-Registry | E14: Which competency framework are we implementing - a customer framework, an existing published one, or one we author - because I cannot design the registry schema until a framework is named and licensed? | F14: Client SME | G14: the schema, every API, the catalogue integration, the assessment tool and the whole product estimate | H14: signed document | I14: CQB0072
A15: 11 | B15: Before sprint 0 | C15: D09 | D15: TLA CMM Level 3 | E15: Who is the assessor for Level 3 - an internal panel, the client authority, or an accredited external body - and are they booked? | F15: Client SME | G15: the assessment date, the evidence deadline and the whole plan backward from it | H15: named person | I15: CQB0181
A16: 12 | B16: Before sprint 0 | C16: D09 | D16: TLA CMM Level 3 | E16: Which published capability maturity model are we being assessed against for TLA Level 3 - is there a named document with numbered practices, and can I have the current version of it? | F16: Client SME | G16: the entire attainment plan, the evidence schedule and the estimate | H16: signed document | I16: CQB0178
... A64: 60 | B64: Before sprint 0 | C64: XCUT | D64: Cross-cutting concern / Whole Product | E64: Give me the actual environment list - dev, integration, staging, enclave-representative, demo, production - with a named owner for each, because squads are currently creating their own and calling them staging? | F64: NOBODY OWNS THIS | G64: Every deployment target decision and every conversation that starts with which staging do you mean | H64: named person | I64: CQF0198

Sheet Escalation — nobody owns this
A1: Escalation — nobody owns this
A2: Decisions with no current owner. These are not meetings — they are a governance finding. Each needs a name attached before it can even be scheduled. This sheet is the shortest route to the programme's real risk.
A4: ProductID | B4: Product | C4: Blocking | D4: Hard? | E4: Needed by | F4: Asked by | G4: Question | H4: Proposed default | I4: Cost if wrong | J4: CQID | K4: Owner assigned | L4: Date
A5: D01 | B5: AI SME Chatbot — Learner-Facing | C5: Blocker | D5: HARD | E5: Before sprint 0 | F5: AI | G5: What GPU hardware will actually be in the enclave appliance - count, model and VRAM - because I cannot size batch, context window or resident model count without it? | H5: HARD BLOCKER - no default possible | I5: every latency, concurrency and quality number we publish is unfounded, and procurement lead time is quoted at two quarters | J5: CQC0012
A6: D02 | B6: AI Assessment Tools & Test Banks + Auto Grader | C6: Blocker | D6: HARD | E6: Before sprint 0 | F6: AI | G6: Should grading run on a larger model than the chatbot on the same appliance, or must both share one model - because this decision drives VRAM and therefore procurement? | H6: HARD BLOCKER - no default possible | I6: one model may be too weak for grading and two may not fit; either way the appliance is bought wrong and cannot be changed for two quarters | J6: CQC0045
A7: D03 | B7: Security Accreditation & Authorisation to Operate — Initiation | C7: Blocker | D7: HARD | E7: Before sprint 0 | F7: SEC | G7: Which organisation actually issues the Authorisation to Operate for EdVidura at customer one - name the accrediting body and the role title of the officer who signs it - because until I have that name I cannot tell you which control catalogue, which templates or which submission route the package must use? | H7: HARD BLOCKER - no default possible | I7: Writing the package to the wrong authority means the whole submission is rejected on format alone and rebuilt from scratch - six to ten weeks and a missed go-live | J7: CQF0001
A8: D03 | B8: Security Accreditation & Authorisation to Operate — Initiation | C8: Blocker | D8: HARD | E8: Before sprint 0 | F8: SEC | G8: Which control baseline are we assessed against - ISO/IEC 27001:2022 Annex A, NIST SP 800-53 Rev 5 at Moderate, CERT-In plus MeitY guidance, or a customer-specific catalogue - and is that choice ours or theirs? | H8: HARD BLOCKER - no default possible | I8: A baseline swap after evidence collection starts is a full re-index of every artefact plus new controls we never implemented - a quarter of engineering effort in the worst case | J8: CQF0002
A9: D04 | B9: Pedagogy Design Review Protocol | C9: Blocker | D9: HARD | E9: Before sprint 0 | F9: ID | G9: Who is the assessor - a named instructional designer, a panel, or the customer training authority - because a protocol with no named reviewer is a document nobody executes? | H9: HARD BLOCKER - no default possible | I9: A protocol with no staffed reviewer role is written, signed and never executed; content ships unreviewed and the gate exists only on paper | J9: CQD0171
A10: D05 | B10: TLA CMM Level 2 — Microservices | C10: Blocker | D10: HARD | E10: Before sprint 0 | F10: PM | G10: Who is the assessor - an EdVidura independent reviewer, a customer body, or an external accreditation authority - and have they been engaged or is that name still blank? | H10: HARD BLOCKER - no default possible | I10: An assessment date that never gets booked, so a contractual maturity claim is made with nobody having assessed it. | J10: CQA0111
A11: D09 | B11: TLA CMM Level 3 | C11: Blocker | D11: HARD | E11: Before sprint 0 | F11: PM | G11: Which external organisation are we demonstrating interoperability with for Level 3 - because the practices require a real external partner and none has been named? | H11: HARD BLOCKER - no default possible | I11: The attainment cannot be achieved at all - no substitute demonstration will satisfy an assessor who asks who you interoperated with | J11: CQB0180
A12: D14 | B12: Personalized Learning Engine — Core | C12: Blocker | D12: HARD | E12: Before sprint 0 | F12: DE | G12: Where do content metadata and the competency framework come from - the ECC catalogue and M19 registry - and do those schemas exist today in any version I can build against? | H12: HARD BLOCKER - no default possible | I12: building sequencing before the content and competency schemas exist is the classic adaptive-learning-without-an-ontology failure | J12: CQC0114
A13: D22 | B13: AI/ML Procedural Walkthrough Engine | C13: Blocker | D13: HARD | E13: Before sprint 0 | F13: MXR | G13: What is the capture stack - headset hand tracking, external cameras, instrumented tools, or a mix - because the whole engine design follows from it? | H13: HARD BLOCKER - no default possible | I13: every downstream decision - confidence metadata, occlusion handling, data volume, privacy posture - depends on hardware nobody has selected | J13: CQC0133
A14: D23 | B14: Difference Training Application | C14: Blocker | D14: HARD | E14: Before sprint 0 | F14: DE | G14: Which system of record tells me that a named learner is assigned to a named piece of equipment at a named variant - I cannot find one, and without it there is no such thing as a difference for a person? | H14: HARD BLOCKER - no default possible | I14: Every gap is computed against an invented assignment model; when the real source appears with different granularity - by role, by unit, by serial number - the model, the feed and the screens are all rebuilt | J14: CQD0138
A15: D25 | B15: Accelerate Upgrade Readiness Measurement Plan | C15: Blocker | D15: HARD | E15: Before sprint 0 | F15: DA | G15: Where does the pre-rollout baseline come from - existing training records in a client system, paper registers at the site, or an SME recollection - and does that source contain per-trainee dates or only cohort totals? | H15: HARD BLOCKER - no default possible | I15: There is no recovery - once rollout starts at a site, the pre-rollout state of that site cannot be reconstructed and the acceleration claim for it is dead | J15: CQF0038
A16: D25 | B16: Accelerate Upgrade Readiness Measurement Plan | C16: Blocker | D16: HARD | E16: Before sprint 0 | F16: DA | G16: Who accepts the measurement definitions as fair before we start collecting - a client SME, an independent evaluator, or nobody - because a definition accepted only by us is worthless the moment the client disputes the result? | H16: HARD BLOCKER - no default possible | I16: An unaccepted definition means the client rejects the result at the end of a twelve-month measurement period and there is no second baseline to redo it against | J16: CQF0037
... A38: D02 | B38: AI Assessment Tools & Test Banks + Auto Grader | C38: Blocker | D38: HARD | E38: Before first code | F38: AI | G38: What is the grading evaluation dataset - scored answers with human gold grades - and how many items per language do I need before any threshold can be argued? | H38: HARD BLOCKER - no default possible | I38: without it the 100 percent review default is permanent by default rather than by decision, and no gate can ever be passed | J38: CQC0043
A39: D18 | B39: Analytics Dashboard Suite (incl. TLA) — All Roles | C39: Blocker | E39: Before first code | F39: SEC | G39: Who owns the row-level security policies on the analytics marts - my squad, the data platform squad, or the security team - because right now three groups each assume another one writes them and none exist? | H39: The data platform squad authors the policies, security reviews and signs them, and no policy change merges without both approvals recorded in the mart repository | I39: Unowned policies drift, a tenant sees another tenant's learners, and we take an accreditation finding that stops the release rather than a bug we can patch | J39: CQE0002
A40: D18 | B40: Analytics Dashboard Suite (incl. TLA) — All Roles | C40: Blocker | E40: Before first code | F40: UXD | G40: Do the five surfaces in this group - dashboards, XR store, microlearning app, MOE AR capture and the lab console - share one component library, and who owns and versions it? | H40: One shared token set - colour, type scale, spacing, iconography - owned by the design squad, with separate component implementations per platform because web, Unity and native mobile cannot share code | I40: Five surfaces that look like five products from different vendors, then a costly visual harmonisation pass late, plus duplicated accessibility work | J40: CQE0019
A41: D22 | B41: AI/ML Procedural Walkthrough Engine | C41: Blocker | D41: HARD | E41: Before first code | F41: MXR | G41: What confidence value is too low to score - below what number does a step go to human review instead of being marked failed? | H41: HARD BLOCKER - no default possible | I41: auto-failing a step on degraded sensor data creates a false finding against a trainee that is very hard to reverse | J41: CQC0135
A42: D23 | B42: Difference Training Application | C42: Blocker | E42: Before first code | F42: DE | G42: Who owns the equipment and variant identifiers - is there a controlled taxonomy of variants I map to, or do I mint my own identifiers and hope everyone agrees? | H42: Mint EdVidura variant identifiers from the applicability metadata carried on manuals, and keep a mapping table that a human can correct | I42: Two products minting different variant identifiers means the manual applicability and the assignment feed never join, and every gap is wrong or missing | J42: CQD0140
A43: D28 | B43: TLA CMM Level 5 — Enterprise Competency Mapping | C43: Blocker | D43: HARD | E43: Before first code | F43: ID | G43: For enterprise competency mapping, who has the authority to declare that a role requires a given competency - the unit, a central authority, or a joint board? | H43: HARD BLOCKER - no default possible | I43: We produce a mapping dataset with no authority behind it, which an assessor will correctly treat as an unsanctioned spreadsheet | J43: CQB0216
A44: E08 | B44: Customer Onboarding, Tenant Provisioning & Data Migration | C44: Blocker | D44: HARD | E44: Before first code | F44: DE | G44: What evidence level must a migrated completion record carry - self-asserted, an extract signed by the source system owner, or full underlying evidence artefacts? | H44: HARD BLOCKER - no default possible | I44: If migrated records are later judged inadmissible, every certificate and competency claim derived from them is withdrawn and the customer relationship goes with it | J44: CQG0040
A45: XCUT | B45: Cross-cutting concern / Whole Product | C45: Blocker | D45: HARD | E45: Before first code | F45: PM | G45: Which licence metering model must the product actually enforce - per learner per month, per seat perpetual with maintenance, per site, or per headset? | H45: HARD BLOCKER - no default possible | I45: Implementing per-seat metering when the commercial model turns out to be per-site means the entitlement service, the licence file and every admin screen are rebuilt after the first contract is signed | J45: CQG0269
A46: XCUT | B46: Cross-cutting concern / Whole Product | C46: Blocker | D46: HARD | E46: Before first code | F46: SDET | G46: Who owns and maintains the register of published interfaces, and is it a document, a repository or a service - because the conformance suite has to be generated from it and it does not exist yet? | H46: HARD BLOCKER - no default possible | I46: Without a register the conformance suite scope is guesswork, deprecation notices go to nobody, and each squad decides unilaterally what it owes the outside world | J46: CQF0240
A47: XCUT | B47: Cross-cutting concern / Whole Product | C47: Blocker | D47: HARD | E47: Before first code | F47: DE | G47: Who owns the event envelope every product publishes into - the fields, the versioning, the correlation identifier - because three squads have each invented their own envelope and they are already incompatible? | H47: HARD BLOCKER - no default possible | I47: Three incompatible envelopes means no cross-product correlation, no shared consumer tooling and a migration touching every producer once someone finally decides | J47: CQF0241
A48: XCUT | B48: Cross-cutting concern / Whole Product | C48: Blocker | D48: HARD | E48: Before first code | F48: AI | G48: Which embedding model do we use, is it enclave-legal by licence, and who approved it? | H48: HARD BLOCKER - no default possible | I48: choosing an embedding model that turns out to be licence-incompatible with the enclave means re-embedding the entire corpus | J48: CQC0202
A49: XCUT | B49: Cross-cutting concern / Whole Product | C49: Blocker | E49: Before first code | F49: SEC | G49: Who writes, reviews and owns the row-level security policies - I need a named owner and a change process, because a policy edited by anyone with database access is not a control? | H49: Policies live as migrations in the mart repository, authored by the data platform squad, requiring a security approver on every pull request, with direct production edits blocked | I49: Unowned and unreviewed policies are the single most likely cause of a cross-tenant leak, and there is no audit trail to prove otherwise afterwards | J49: CQE0194
A50: XCUT | B50: Cross-cutting concern / Whole Product | C50: Blocker | D50: HARD | E50: Before first code | F50: SDET | G50: Who owns the shared synthetic dataset - its content, its volume, its Indic text coverage and its refresh - because every squad has now built a different one and integration tests fail on data shape not defects? | H50: HARD BLOCKER - no default possible | I50: Per-squad datasets mean cross-product tests fail for data reasons weekly, teams stop trusting integration results and the platform gate becomes noise | J50: CQF0210
A51: XCUT | B51: Cross-cutting concern / Whole Product | C51: Blocker | D51: HARD | E51: Before first code | F51: AI | G51: How fast must a tombstoned chunk stop being retrievable - do I check tombstones at query time on every request, or wait for the next re-index? | H51: HARD BLOCKER - no default possible | I51: query-time checking costs latency on every request forever; re-index-only leaves a window in which withdrawn safety content is still answerable | J51: CQC0207
A52: XCUT | B52: Cross-cutting concern / Whole Product | C52: Blocker | D52: HARD | E52: Before first code | F52: DE | G52: Who may add an xAPI verb or activity type to the platform vocabulary, what is the approval process, and what do I do today when I need one that does not exist? | H52: HARD BLOCKER - no default possible | I52: Squads inventing verbs privately means the records store fills with near-duplicate vocabulary and every analytics query has to know all the variants forever | J52: CQF0242
A53: XCUT | B53: Cross-cutting concern / Whole Product | C53: Blocker | E53: Before first code | F53: DA | G53: Who owns a metric definition once it is in the semantic layer - can a squad add a new definition of completion, or must every metric go through one owner? | H53: One metric catalogue with a single named owner; squads propose definitions by pull request and no dashboard may use a metric that is not in the catalogue | I53: Without a single owner, four squads each define active learner differently and the customer sees four different numbers for the same thing | J53: CQE0198
A54: XCUT | B54: Cross-cutting concern / Whole Product | C54: Blocker | D54: HARD | E54: Before first code | F54: AI | G54: Who authors the retrieval evaluation set - the query, the gold chunks, the gold answer - and how many items per language do we need? | H54: HARD BLOCKER - no default possible | I54: the evaluation set is the single artefact that makes every AI quality claim testable, and nobody is funded to write it | J54: CQC0211
A55: D06 | B55: TLA Experience-Index (ELRR) | C55: Blocker | D55: HARD | E55: Before first integration | F55: DA | G55: When two sources report the same completion with different dates and different results, which wins - most recent, most authoritative source, or the record with an assertion attached? | H55: HARD BLOCKER - no default possible | I55: Every conflicting record is resolved by whichever rule an engineer picked, with no authority behind it, and the first disputed record exposes that | J55: CQB0027
A56: D08 | B56: TLA Competency-Registry | C56: Blocker | D56: HARD | E56: Before first integration | F56: BE | G56: If two organisations both assert the same person holds the same competency at different proficiency levels, does my registry store both, keep the higher, or refuse to store the second? | H56: HARD BLOCKER - no default possible | I56: The registry silently picks a winner with no authority behind the choice, and a person capability record differs depending on which system you ask | J56: CQB0104
A57: D15 | B57: Competency Assessment Tool | C57: Blocker | D57: HARD | E57: Before first integration | F57: ID | G57: If an assessment result influences somebody's job assignment, does that raise the psychometric standard we must meet - and who here is qualified to certify that we meet it? | H57: HARD BLOCKER - no default possible | I57: using an instrument built to formative standards for a consequential decision is challengeable by the individual affected, and we have no qualified signatory to defend it | J57: CQU0132
A58: D16 | B58: TLA Profile Management — Initial Deployment | C58: Blocker | D58: HARD | E58: Before first integration | F58: BE | G58: How do I decide that a person in enclave A and a person in enclave B are the same human when the two have separate identity realms and no shared identifier? | H58: HARD BLOCKER - no default possible | I58: Either we never link a person across enclaves and the enterprise view is fiction, or we match on weak attributes and attach one person records to another - which is the worst failure this platform can have | J58: CQB0112
A59: D17 | B59: Cross-Organisation / Cross-Command Data Pipeline | C59: Blocker | D59: HARD | E59: Before first integration | F59: DA | G59: When a federated record and a local record describe the same completion, does the local one always win, or does the issuing organisation always win regardless of who is reading? | H59: HARD BLOCKER - no default possible | I59: The same person appears differently qualified depending on which organisation system you look at, with no rule anyone can point to | J59: CQB0167
A60: D17 | B60: Cross-Organisation / Cross-Command Data Pipeline | C60: Blocker | D60: HARD | E60: Before first integration | F60: BE | G60: When two organisations send conflicting records about the same person and the same event, who adjudicates - is there a precedence rule, an authority ranking, or a human queue with a named owner? | H60: HARD BLOCKER - no default possible | I60: The pipeline picks a winner by an engineering rule with no authority behind it, and the first time a person qualification is disputed we cannot say who decided or why | J60: CQB0148
A61: D29 | B61: Full Multiverse Platform Integration & Acceptance | C61: Blocker | D61: HARD | E61: Before first integration | F61: PM | G61: What is the pass criterion - zero critical and zero major defects, or a defect budget such as no criticals and up to five majors with agreed workarounds - and who set that number? | H61: HARD BLOCKER - no default possible | I61: Assuming a defect budget when the client expects zero defects means we walk into the event with five open majors and are rejected on the first one | J61: CQF0103
A62: D29 | B62: Full Multiverse Platform Integration & Acceptance | C62: Blocker | D62: HARD | E62: Before first integration | F62: SDET | G62: Do we demonstrate performance and load at acceptance, and against which numbers - because the concurrency, latency and volume targets the tests would execute against have never been published anywhere I can find? | H62: HARD BLOCKER - no default possible | I62: Demonstrating performance against numbers we invented means the client can reject the result by naming different numbers, and we have no basis to argue | J62: CQF0118
A63: D29 | B63: Full Multiverse Platform Integration & Acceptance | C63: Blocker | D63: HARD | E63: Before first integration | F63: SDET | G63: Which environment does acceptance run in - the live enclave at a site, a representative staging clone, or a demonstration environment - and who provides and funds it, because we do not currently have an enclave-representative environment at all? | H63: HARD BLOCKER - no default possible | I63: Discovering three weeks out that the enclave scenarios cannot be demonstrated anywhere means removing them from the ATP and accepting a platform whose enclave behaviour was never proven | J63: CQF0106
A64: D29 | B64: Full Multiverse Platform Integration & Acceptance | C64: Blocker | D64: HARD | E64: Before first integration | F64: SDET | G64: D29 has no test assets at all - who writes the acceptance test procedure, from which requirement baseline, and by when, because writing a full platform ATP is a two-month job on its own? | H64: HARD BLOCKER - no default possible | I64: Arriving at the acceptance window with no procedure means the event is improvised, the client writes the tests on the day, and we fail against criteria we never saw | J64: CQF0101
A65: E05 | B65: MOSA Conformance Program (enabler) | C65: Blocker | D65: HARD | E65: Before first integration | F65: SDET | G65: Who may waive a failed conformance assertion, for how long, and does the waiver appear in the published report - because a hidden waiver is a lie to a third party? | H65: HARD BLOCKER - no default possible | I65: Undisclosed waivers mean a third party builds against a documented behaviour we do not implement, and the failure surfaces in their production not ours | J65: CQF0148
... A70: E07 | B70: Test & Release Quality System (enabler) | C70: Blocker | D70: HARD | E70: Before first integration | F70: AI | G70: For AI features, what evaluation set does the release gate run and what is the pass mark - and who owns that evaluation set, because if the team that builds the model also owns the exam the gate means nothing? | H70: HARD BLOCKER - no default possible | I70: A model gate owned by the model team is a self-graded exam; a regression in answer quality ships and is discovered by learners | J70: CQF0180
A71: XCUT | B71: Cross-cutting concern / Whole Product | C71: Blocker | E71: Before first integration | F71: DE | G71: Who is allowed to add a new xAPI verb to EdVidura - any engineer, the spine squad, an instructional design lead, or a governance board - because right now anyone can emit anything. | H71: The spine squad maintains the vocabulary with a named instructional design reviewer; new terms need both signatures. | I71: A vocabulary that grows organically until no two modules mean the same thing by completed. | J71: CQA0180
A72: XCUT | B72: Cross-cutting concern / Whole Product | C72: Blocker | D72: HARD | E72: Before first integration | F72: QA | G72: Is there a real LMS instance I can run LTI launch tests against, whose is it, and can I break it - because a mocked LTI launch has never once caught the problems a real Moodle finds? | H72: HARD BLOCKER - no default possible | I72: Mock-only LTI testing means the first real launch at a customer fails on a certificate, a clock skew or a claim we never saw, in front of the customer | J72: CQF0206
A73: XCUT | B73: Cross-cutting concern / Whole Product | C73: Blocker | D73: HARD | E73: Before first integration | F73: BE | G73: Is there an authority ranking between organisations - is a record from the issuing organisation always preferred over one from a receiving organisation, for every payload type? | H73: HARD BLOCKER - no default possible | I73: Each product implements its own ranking, so the same person appears differently qualified depending on which screen you open | J73: CQB0253
A74: XCUT | B74: Cross-cutting concern / Whole Product | C74: Blocker | D74: HARD | E74: Before first integration | F74: SDET | G74: When a test section fails and a release is urgent, who is the waiver authority for that specific section - is it different for security, accessibility, performance and functional - and where is the waiver visible afterwards? | H74: HARD BLOCKER - no default possible | I74: With no named authority the waiver decision defaults to whoever is loudest at 6pm on a Friday and leaves no record for the assessor to find | J74: CQF0203
A75: XCUT | B75: Cross-cutting concern / Whole Product | C75: Blocker | D75: HARD | E75: Before first integration | F75: BE | G75: What is the rule for deciding that a subject in one organisation is the same person as a subject in another when the two identity realms share no identifier? | H75: HARD BLOCKER - no default possible | I75: Either no cross-organisation view is possible at all, or we match on weak attributes and attribute one person qualifications to another - the worst possible failure of a record system | J75: CQB0247
A76: XCUT | B76: Cross-cutting concern / Whole Product | C76: Blocker | D76: HARD | E76: Before first integration | F76: BE | G76: When two organisations send conflicting assertions about the same subject and the same competency, who adjudicates - a precedence rule, a named authority, or a human queue? | H76: HARD BLOCKER - no default possible | I76: Engineers pick a winner with no authority behind the choice, and the first disputed qualification exposes that nobody decided and nobody can | J76: CQB0251
A77: XCUT | B77: Cross-cutting concern / Whole Product | C77: Blocker | D77: HARD | E77: Before first integration | F77: QA | G77: Is there a performance test rig with production-like sizing, who funds it, and how do I generate a realistic load profile when nobody has told me how many concurrent learners to expect? | H77: HARD BLOCKER - no default possible | I77: Performance testing against a laptop-sized environment with an invented load profile tells us nothing, and the first real peak is at a customer site | J77: CQF0215
A78: XCUT | B78: Cross-cutting concern / Whole Product | C78: Blocker | E78: Before first integration | F78: SEC | G78: When the journey crosses a trust boundary, which side owns the seam - the sending enclave, the receiving enterprise, or a named third party - because today neither side has agreed to be responsible for what does not arrive. | H78: The sending side owns delivery and publishes a manifest per transfer; the receiving side owns acknowledgement, and unacknowledged manifests alarm on the sending side | I78: An unowned trust-boundary seam means data can stop flowing for weeks with both sides believing the other is watching | J78: CQH0072
A79: XCUT | B79: Cross-cutting concern / Whole Product | C79: Blocker | D79: HARD | E79: Before first integration | F79: MXR | G79: Where do XR and mobile tests physically run - is there a device lab with headsets and Android devices, who owns it, and can a pipeline reach it or is every device test manual? | H79: HARD BLOCKER - no default possible | I79: No device lab means all XR and mobile testing is manual on someone desk, does not gate a release, and regressions ship to headsets in the field | J79: CQF0204
A80: XCUT | B80: Cross-cutting concern / Whole Product | C80: Blocker | D80: HARD | E80: Before first integration | F80: SDET | G80: The conformance suite is itself software - who owns its repository, its release cadence and its own tests, because a broken suite blocks every squads pipeline the moment we gate on it? | H80: HARD BLOCKER - no default possible | I80: An unowned suite rots, breaks pipelines and gets bypassed within a month, and the conformance gate becomes decorative | J80: CQF0261
A81: XCUT | B81: Cross-cutting concern / Whole Product | C81: Blocker | D81: HARD | E81: Before first integration | F81: SDET | G81: Where is the single published table of numeric thresholds my tests assert against - AI confidence floors, grading variance bounds, OCR character accuracy, supersession propagation SLA - because I cannot find one and every squad has invented its own? | H81: HARD BLOCKER - no default possible | I81: Different squads asserting different numbers for the same quality property means the platform has no coherent quality definition and the first client question exposes it | J81: CQF0202
A82: XCUT | B82: Cross-cutting concern / Whole Product | C82: Blocker | D82: HARD | E82: Before first integration | F82: AI | G82: For the AI features, is there a held-out evaluation set that gates a release, who curates it, and is it kept away from whoever tunes the prompts and the retrieval? | H82: HARD BLOCKER - no default possible | I82: Evaluating a model against a set the same team tuned on measures memorisation, and a genuine quality regression reaches learners undetected | J82: CQF0207
A83: XCUT | B83: Cross-cutting concern / Whole Product | C83: Blocker | D83: HARD | E83: Before first integration | F83: QA | G83: Where exactly is the boundary between a contract test and an integration test when both are offered as MOSA conformance evidence - will an assessor accept a passing contract test alone, or does conformance require a real run against a real partner? | H83: HARD BLOCKER - no default possible | I83: if the assessor rejects contract tests as evidence, every published interface needs a witnessed live run against a partner system we may not have access to, which is months of unplanned work near the end of the programme | J83: CQU0032
A84: XCUT | B84: Cross-cutting concern / Whole Product | C84: Blocker | D84: HARD | E84: Before first integration | F84: SDET | G84: Can automated evidence satisfy an external assessor at all, or does an assessor require a witnessed manual run - has anybody actually asked one? | H84: HARD BLOCKER - no default possible | I84: building a fully automated evidence pipeline that an assessor will not accept wastes the investment and leaves us running witnessed manual sessions we never scheduled or staffed | J84: CQU0071
A85: D01 | B85: AI SME Chatbot — Learner-Facing | C85: Blocker | D85: HARD | E85: Before first release | F85: AI | G85: What quality delta between the hosted model used in the demo and an enclave-legal open-weight model is acceptable, and who accepts it in writing? | H85: HARD BLOCKER - no default possible | I85: we either promise demo quality air-gapped and fail acceptance, or silently ship a worse product to enclave customers | J85: CQC0014
A86: D02 | B86: AI Assessment Tools & Test Banks + Auto Grader | C86: Blocker | D86: HARD | E86: Before first release | F86: PRODM | G86: Who has the authority to end 100 percent human confirmation of semantic grades, and what evidence package do they need to see to do it? | H86: HARD BLOCKER - no default possible | I86: the control either stays forever and the product never pays back, or it is dropped informally by someone with no authority | J86: CQC0037
A87: D03 | B87: Security Accreditation & Authorisation to Operate — Initiation | C87: Blocker | D87: HARD | E87: Before first release | F87: SEC | G87: When the assessment leaves a residual High finding, who is allowed to accept that risk and on what record - a customer security officer, our programme manager, or nobody below the accrediting authority? | H87: HARD BLOCKER - no default possible | I87: If we assume our own programme manager can accept residual risk and the authority disagrees, every accepted item reopens and the submission is returned | J87: CQF0009
A88: D03 | B88: Security Accreditation & Authorisation to Operate — Initiation | C88: Blocker | D88: HARD | E88: Before first release | F88: SEC | G88: Who assesses the package - an independent assessor the customer appoints, a third-party auditor we procure, or the authority itself - and are they engaged yet, because their lead time sits directly on the critical path to release? | H88: HARD BLOCKER - no default possible | I88: Assuming a four-week assessment when the real assessor has a twelve-week queue moves go-live by two months and we find out too late to compress anything else | J88: CQF0004
A89: D04 | B89: Pedagogy Design Review Protocol | C89: Blocker | E89: Before first release | F89: PRODM | G89: What is the review turnaround service level - how many working days from submission to outcome - because without a number the queue has no target and authors cannot plan? | H89: Five working days for a standard review and two for an expedited one, measured from submission to outcome recorded | I89: With no service level the queue grows without anybody being accountable, authors route around the protocol, and the gate quietly stops functioning | J89: CQD0174
A90: D05 | B90: TLA CMM Level 2 — Microservices | C90: Blocker | D90: HARD | E90: Before first release | F90: PM | G90: How long must the demonstration period be, and does it have to use real learner traffic at a customer site or is a synthetic load acceptable? | H90: HARD BLOCKER - no default possible | I90: A demonstration built on synthetic traffic that the assessor rejects, requiring a live customer window we have not negotiated. | J90: CQA0117
A91: D05 | B91: TLA CMM Level 2 — Microservices | C91: Blocker | D91: HARD | E91: Before first release | F91: PM | G91: What is the pass threshold on the maturity rubric - is L2 all-or-nothing per criterion, or a weighted score, and what score do we have to reach? | H91: HARD BLOCKER - no default possible | I91: Preparing for a score we do not need, or discovering at assessment that a criterion we deprioritised was mandatory. | J91: CQA0112
A92: D05 | B92: TLA CMM Level 2 — Microservices | C92: Blocker | D92: HARD | E92: Before first release | F92: DEVOPS | G92: Does the L2 demonstration have to run in a production environment at a customer site, in our staging, or in the enclave rig - because enclave evidence and cloud evidence are different pieces of work. | H92: HARD BLOCKER - no default possible | I92: Preparing a cloud demonstration for an assessor who requires enclave evidence, or vice versa. | J92: CQA0135
A93: D07 | B93: TLA Course Catalogue (ECC) | C93: Blocker | D93: HARD | E93: Before first release | F93: ID | G93: When a course claims it develops a competency, is that claim self-asserted by the course owner or must it be approved by a competency authority before it appears in search? | H93: HARD BLOCKER - no default possible | I93: Either an unmoderated catalogue where anyone can claim any competency, or an approval queue with no approver, which stalls publication entirely | J93: CQB0063
A94: D08 | B94: TLA Competency-Registry | C94: Blocker | D94: HARD | E94: Before first release | F94: BE | G94: When a competency is deprecated, what happens to an official record already asserting a person holds it - does the assertion stand, get remapped to a successor, or become invalid? | H94: HARD BLOCKER - no default possible | I94: Either we silently invalidate qualifications people were told they held, or we keep asserting competencies that the authority has withdrawn - both are defensible-record failures with no engineering fix | J94: CQB0075
A95: D10 | B95: PDFs & Technical Manuals Integration — Live TO Connection | C95: Blocker | E95: Before first release | F95: BE | G95: What is the maximum acceptable staleness, in hours, between a revision publishing in the technical-manual repository and it being visible to a learner in EdVidura - I need a number I can put in a monitor and an SLO? | H95: 24 hours end to end for connected sites and next media drop for enclave sites, published as a target not a guarantee | I95: If the real requirement is safety-driven and measured in minutes, the entire poll-and-batch design is wrong and becomes an event-driven pipeline - a full re-architecture of D10 plus the lineage cascade | J95: CQD0005
A96: D13 | B96: SME Chatbot — Content Authoring Support | C96: Blocker | D96: HARD | E96: Before first release | F96: AI | G96: What acceptance rate on the enclave-approved local model counts as good enough to ship the authoring assistant, and who ratified that number? | H96: HARD BLOCKER - no default possible | I96: we either ship an assistant authors ignore while it consumes GPU capacity grading needs, or we cut a sold feature late | J96: CQC0078
A97: D14 | B97: Personalized Learning Engine — Core | C97: Blocker | D97: HARD | E97: Before first release | F97: PRODM | G97: What evidence will prove personalisation actually improved outcomes, and is anyone designing that study before we build the thing? | H97: HARD BLOCKER - no default possible | I97: we ship a personalisation engine with no way to show it helps, and the first sceptical customer question ends the conversation | J97: CQC0118
A98: D18 | B98: Analytics Dashboard Suite (incl. TLA) — All Roles | C98: Blocker | E98: Before first release | F98: FE | G98: Nobody has given me a concurrency number or a p95 target for the embedded dashboards - how many simultaneous viewers must a signed-embed dashboard support and what page-ready time am I committing to? | H98: 200 concurrent dashboard viewers per tenant, p95 first meaningful render of 3 seconds and p95 full dashboard load of 6 seconds on a 10 Mbps campus link | I98: Discovering at customer scale that the real number is ten times higher means re-architecting to pre-aggregated cubes and a caching tier after the design is frozen | J98: CQE0005
A99: D22 | B99: AI/ML Procedural Walkthrough Engine | C99: Blocker | D99: HARD | E99: Before first release | F99: ID | G99: If this engine cannot write official records, who actually reads the walkthrough evidence and decides the competency was demonstrated - and is that person funded? | H99: HARD BLOCKER - no default possible | I99: an unfunded review step means the boundary rule quietly becomes automatic acceptance of machine scores | J99: CQC0148
A100: D22 | B100: AI/ML Procedural Walkthrough Engine | C100: Blocker | D100: HARD | E100: Before first release | F100: AI | G100: What agreement with SME judgement would have to be demonstrated before a walkthrough score could count as certification evidence rather than practice feedback? | H100: HARD BLOCKER - no default possible | I100: certifying on machine step-compliance without a validity argument is a finding a certification body will make for us | J100: CQC0143
A101: D22 | B101: AI/ML Procedural Walkthrough Engine | C101: Blocker | D101: HARD | E101: Before first release | F101: AI | G101: What missed-action and phantom-action rates are acceptable, measured against what ground truth - and does a blinded SME set exist? | H101: HARD BLOCKER - no default possible | I101: without measured fidelity we are scoring competency evidence with an unquantified error rate, which no assessor will accept | J101: CQC0142
A102: D23 | B102: Difference Training Application | C102: Blocker | E102: Before first release | F102: SUP | G102: When the assignment feed silently stops, who notices and who is accountable for restarting it - us, the customer data owner, or nobody? | H102: We monitor arrival and alert our own operations plus a named customer contact within 24 hours of a missed drop | I102: With no accountable owner the feed stops, gaps quietly go stale, and the failure is discovered months later by an audit rather than by a monitor | J102: CQD0166
A103: D27 | B103: Train the Trainer — Embedded SME Service | C103: Blocker | D103: HARD | E103: Before first release | F103: ID | G103: Who actually awards the certification and who can revoke it - EdVidura, the client training authority, or jointly - and is the certificate recognised formally inside the client organisation or is it a nice piece of paper? | H103: HARD BLOCKER - no default possible | I103: Issuing a certificate no client authority recognises means trainers hold a credential that does not let them do anything, and the service has delivered nothing operationally useful | J103: CQF0071
A104: D27 | B104: Train the Trainer — Embedded SME Service | C104: Blocker | D104: HARD | E104: Before first release | F104: PM | G104: Who signs acceptance of a delivered cohort - name the client role - because a milestone with no named signatory is a milestone we cannot invoice against? | H104: HARD BLOCKER - no default possible | I104: Delivering cohorts against a milestone nobody is authorised to accept means unbillable work accumulating for months before anyone notices | J104: CQF0082
A105: D28 | B105: TLA CMM Level 5 — Enterprise Competency Mapping | C105: Blocker | D105: HARD | E105: Before first release | F105: BE | G105: If a competency in an approved mapping is later deprecated in the registry, does the mapping become invalid, auto-remap to the successor, or flag for review? | H105: HARD BLOCKER - no default possible | I105: Approved enterprise mappings silently citing withdrawn competencies, which makes the whole dataset untrustworthy as evidence | J105: CQB0233
A106: E04 | B106: Shared Local AI Inference Platform (enabler) | C106: Blocker | D106: HARD | E106: Before first release | F106: SEC | G106: Who approves a specific model version for a specific enclave, and what evidence must accompany that approval? | H106: HARD BLOCKER - no default possible | I106: without a named approver no model is legally servable in the enclave, and the whole AI programme stops at that boundary | J106: CQC0180
A107: E09 | B107: Support, Service Management & Operational Handover | C107: Blocker | D107: HARD | E107: Before first release | F107: SUP | G107: For an enclave customer we cannot reach remotely, what is the support model - a resident engineer, escorted site visits, or the customer running second line with our telephone advice? | H107: HARD BLOCKER - no default possible | I107: Every SLA number, every support price and every hiring decision for enclave customers depends on this; guessing wrong means either an unstaffable promise or an unsellable service | J107: CQG0065
A108: E11 | B108: Vendor, Third-Party & Content-Rights Management | C108: Blocker | E108: Before first release | F108: PM | G108: Who owns vendor renewals and receives the alarm, because right now the register has no named owner and renewals are silent? | H108: The programme manager owns the register and a 90-day alarm until a named owner exists, with the alarm going to a shared mailbox rather than an individual | I108: An unowned renewal calendar means a licence lapses without anyone noticing until a build fails or a customer install stops | J108: CQG0153
A109: E13 | B109: Internal Enablement & Knowledge Continuity | C109: Blocker | E109: Before first release | F109: PM | G109: Which components currently have exactly one person who understands them, and is anyone tracking that number? | H109: I will publish a bus-factor register derived from commit history and on-call records, and it stays my working document until somebody accepts ownership of acting on it | I109: An untracked bus factor means the programme discovers its single points of failure when one of them resigns, mid-deployment | J109: CQG0165
A110: E13 | B110: Internal Enablement & Knowledge Continuity | C110: Blocker | E110: Before first release | F110: PM | G110: When the one person who knows a customer engagement is unavailable, who is the named deputy - and is a deputy recorded anywhere today? | H110: A named deputy per customer recorded on the account record and refreshed quarterly, defaulting to the delivery manager where no deputy exists | I110: One person on leave during a customer incident means the incident is handled by somebody with no context, on a site they have never seen | J110: CQG0175
A111: E13 | B111: Internal Enablement & Knowledge Continuity | C111: Blocker | E111: Before first release | F111: PM | G111: Who keeps enablement material current as the product changes, and is that in anybody objectives today? | H111: Each squad updates its own material as part of the definition of done for a release, with a quarterly audit by the service manager | I111: Unmaintained enablement material becomes actively misleading within two releases and is then worse than nothing | J111: CQG0184
A112: XCUT | B112: Cross-cutting concern / Whole Product | C112: Blocker | D112: HARD | E112: Before first release | F112: BE | G112: If an official record cites a competency that the issuing authority later retires, does the record stay valid, get marked historical, or become invalid? | H112: HARD BLOCKER - no default possible | I112: We either invalidate qualifications people were told they held, or continue asserting competencies the authority has withdrawn - both are indefensible and neither is an engineering choice | J112: CQB0294
A113: XCUT | B113: Cross-cutting concern / Whole Product | C113: Blocker | E113: Before first release | F113: PM | G113: Who owns the unit economics - the cost per learner per month including inference and storage - and where is that model held? | H113: Finance owns the model and engineering supplies measured infrastructure cost per tenant monthly, until an owner is named the engineering figures are published unowned | I113: Pricing without unit economics means we discover the margin position after several signed contracts, when it cannot be changed | J113: CQG0280
A114: XCUT | B114: Cross-cutting concern / Whole Product | C114: Blocker | D114: HARD | E114: Before first release | F114: ID | G114: When a partner asserts a competency from a framework we do not hold, do we display it as an external qualification, hide it, or attempt an equivalence mapping? | H114: HARD BLOCKER - no default possible | I114: Either we discard qualifications people genuinely hold, or we invent equivalences nobody is authorised to declare | J114: CQB0293
A115: XCUT | B115: Cross-cutting concern / Whole Product | C115: Blocker | D115: HARD | E115: Before first release | F115: BE | G115: What is the supersession service level - how many hours from a source revision being declared authoritative to every derivative being withdrawn or refreshed? | H115: HARD BLOCKER - no default possible | I115: Designing for overnight when the real requirement is minutes means the cascade architecture is wrong; designing for minutes when overnight suffices costs compute nobody approved | J115: CQD0201
A116: XCUT | B116: Cross-cutting concern / Whole Product | C116: Blocker | E116: Before first release | F116: BE | G116: A translated variant can outlive the English source it was derived from and nothing currently detects it - whose job is it to detect an orphaned translation, and what does the detector do when it finds one? | H116: A nightly job compares every translation lineage parent against the current authoritative revision, flags mismatches and marks the translation stale | I116: With nothing detecting it, Hindi learners can be reading a procedure withdrawn in English months earlier, and we would only find out from an incident | J116: CQD0207
A117: XCUT | B117: Cross-cutting concern / Whole Product | C117: Blocker | D117: HARD | E117: Before first release | F117: AI | G117: Who produces the per-language evaluation set - we need a native speaker with domain knowledge per language, and I do not have one for any language? | H117: HARD BLOCKER - no default possible | I117: Without native domain reviewers we either ship unevaluated AI in Indic languages or we never ship it at all, and both outcomes are decided by default rather than by choice | J117: CQG0204
A118: XCUT | B118: Cross-cutting concern / Whole Product | C118: Blocker | D118: HARD | E118: Before first release | F118: AI | G118: What is the measured quality gap between the hosted model used in the demo and any local open-weight candidate, on any metric at all? | H118: HARD BLOCKER - no default possible | I118: every enclave commitment we have made assumes parity nobody has measured; if the gap is large the whole enclave AI proposition changes | J118: CQC0245
A119: XCUT | B119: Cross-cutting concern / Whole Product | C119: Blocker | D119: HARD | E119: Before first release | F119: DE | G119: How long does a full re-embed of the corpus take on the target hardware, because that number is the real floor on the supersession SLA? | H119: HARD BLOCKER - no default possible | I119: without hardware the re-embed window is unknowable, and every freshness commitment we make is unbacked | J119: CQC0225
A120: XCUT | B120: Cross-cutting concern / Whole Product | C120: Blocker | E120: Before first release | F120: BI | G120: What query concurrency must the mart database sustain, given every embedded dashboard fires several queries per load - I need a number to size connection pooling against? | H120: Size for 60 concurrent mart queries with a 100 connection pool, derived from an assumed 200 concurrent dashboard viewers at 5 queries per dashboard and a 3 second average | I120: An undersized pool queues queries and dashboards time out under exactly the load we designed the product for, discovered at the customer demo | J120: CQE0209
A121: XCUT | B121: Cross-cutting concern / Whole Product | C121: Blocker | D121: HARD | E121: Before first release | F121: AI | G121: What retrieval metrics gate a release - recall at k, precision, or groundedness of the final answer - and what are the numeric thresholds? | H121: HARD BLOCKER - no default possible | I121: without thresholds every retrieval change is shipped on intuition and regressions are invisible until users complain | J121: CQC0210
A122: XCUT | B122: Cross-cutting concern / Whole Product | C122: Blocker | D122: HARD | E122: Before first release | F122: AI | G122: What is the full metric table a model must pass before activation - groundedness, citation correctness, hallucination, refusal correctness, false refusal, recall and precision - and what are the numbers? | H122: HARD BLOCKER - no default possible | I122: a harness with no ratified thresholds produces a report nobody can act on, so activation decisions stay subjective | J122: CQC0247
A123: XCUT | B123: Cross-cutting concern / Whole Product | C123: Blocker | E123: Before first release | F123: PM | G123: Who is the named grievance contact for a learner complaint, where is that published, and within how many days must they respond? | H123: A named individual with a published address linked from the in-product privacy screen, responding within 30 days, defaulting to the security lead until somebody is appointed | I123: Publishing a grievance route with nobody behind it produces unanswered complaints that escalate directly to the regulator | J123: CQG0265
A124: XCUT | B124: Cross-cutting concern / Whole Product | C124: Blocker | E124: Before first release | F124: PM | G124: Who owns the sync specification and its conformance suite after this programme - because four clients depending on an unowned protocol is a slow-motion failure? | H124: The platform squad owns the specification, the reference implementations and the conformance suite, with a documented change process requiring all four client owners to sign off a protocol change | I124: An unowned protocol drifts into four incompatible dialects and the first cross-client data defect has no responsible team | J124: CQE0276
A125: D20 | B125: Immersive Lab — Reference Site (India) | C125: Shaper | E125: Before first code | F125: UXD | G125: Does the technician console reuse the shared design system or is it its own thing - it is a wall display viewed from three metres, which the dashboard component library was never sized for? | H125: Reuse the shared colour and status tokens but define a distinct large-format type scale with a 24 pixel minimum, documented as a wall-display variant of the design system | I125: Reusing dashboard-sized type on a wall display makes the console unreadable from the room and it gets replaced by a spreadsheet on a laptop | J125: CQE0097
A126: D24 | B126: Microlearning Mobile Application | C126: Shaper | E126: Before first code | F126: UXD | G126: Does the mobile app reuse the shared design system tokens, and if the dashboards and the app disagree on a colour or a status meaning, who decides? | H126: Consume the shared token set and implement components natively per platform, with the design squad as the arbiter of any token conflict | I126: Divergent tokens mean amber means stale on one surface and warning on another, which confuses users and needs a harmonisation pass across five products | J126: CQE0128
...

Sheet Product Kickoff Packs
A1: Product Kickoff Packs
A2: Filter to one ProductID and this is the squad's kickoff agenda: every question that product needs answered, grouped by lifecycle stage (Understand → Scope → Interfaces → Data → Rules → UI/UX → Failure → Non-functionals → BuildEnv → Test&Acceptance → Deploy&Operate → Handover), blockers first within each stage.
A4: ProductID | B4: Product | C4: Lifecycle stage | D4: # | E4: Blocking | F4: Needed by | G4: Role | H4: Level | I4: Question | J4: Proposed default | K4: Ask | L4: CQID | M4: Answer / decision
A5: D01 | B5: AI SME Chatbot — Learner-Facing | C5: Understand | D5: 1 | E5: Blocker | F5: Before first code | G5: AI | H5: L1 Junior | I5: Which document set is the learner chatbot allowed to answer from on day one - only manuals approved in the M25 lineage service, or also DCT-authored lessons and course pages? | J5: approved technical manuals only; DCT lessons excluded until a separate corpus decision is recorded | K5: Product Owner | L5: CQC0001
A6: D01 | B6: AI SME Chatbot — Learner-Facing | C6: Understand | D6: 2 | E6: Blocker | F6: Before first code | G6: AIG | H6: L1 Junior | I6: Who is the named owner of the guardrail policy - the person I go to when a case is not covered - because right now the answer to a novel case is whatever the engineer on the ticket decides? | J6: A named guardrail policy owner in the product team, with a decision log where each novel case and its ruling is recorded and becomes an evaluation case | K6: Programme Manager | L6: CQT0146
A7: D01 | B7: AI SME Chatbot — Learner-Facing | C7: Understand | D7: 3 | E7: Blocker | F7: Before first code | G7: AIG | H7: L4 Architect | I7: Do we run one assistant serving learners and authors with role-based prompts and corpus filters, or three separate deployments - and what do we permanently give up in each case: shared improvement in the first, or three times the evaluation and governance load in the second? | J7: Three separate deployments sharing the inference platform and the evaluation harness but not the corpus, prompts or guardrail configuration | K7: Solution Architect | L7: CQT0183
A8: D01 | B8: AI SME Chatbot — Learner-Facing | C8: Scope | D8: 1 | E8: Blocker | F8: Before first code | G8: AI | H8: L4 Architect | I8: There are three chatbots on the programme - M15 learner-facing, M23 authoring support and the M27 assessment assistant. Which components do they share as one deployed service and which are duplicated per bot? | J8: share the E04 inference service and one embedding pipeline; keep retrieval, prompts, guardrails and corpora separate per bot | K8: Solution Architect | L8: CQC0010
A9: D01 | B9: AI SME Chatbot — Learner-Facing | C9: Scope | D9: 2 | E9: Blocker | F9: Before sprint 0 | G9: PRODM | H9: L4 Architect | I9: Is practice quiz generation part of the learner chatbot at all, or does every quiz item come from M8 and M27 - because I keep being asked for it in demos? | J9: out of scope for M15; the chatbot may only link to existing M8 items, never generate them | K9: Product Owner | L9: CQC0024
A10: D01 | B10: AI SME Chatbot — Learner-Facing | C10: Scope | D10: 3 | E10: Shaper | F10: Before first release | G10: ID | H10: L1 Junior | I10: Is the learner-facing assistant instructional content subject to the pedagogy gate, or is it a tool that sits outside instructional review entirely? | J10: the assistant is in scope for instructional review of its system prompt, its guidance wording and its refusal messages, but individual generated answers are governed by the AI quality gate instead | K10: Instructional Designer | L10: CQU0127
A11: D01 | B11: AI SME Chatbot — Learner-Facing | C11: Interfaces | D11: 1 | E11: Blocker | F11: Before first code | G11: BE | H11: L1 Junior | I11: Do I call the shared inference service at E04 through the published OpenAI-compatible contract, or does M15 get its own direct model handle on the appliance? | J11: E04 published contract only, with priority class chat on every call and no direct model handle | K11: Solution Architect | L11: CQC0002
A12: D01 | B12: AI SME Chatbot — Learner-Facing | C12: Interfaces | D12: 2 | E12: Blocker | F12: Before first code | G12: BE | H12: L3 Senior | I12: How long do I retain a learner conversation, and is the transcript readable by an instructor, by support, or by nobody? | J12: 90 day retention, learner and support readable with an audit record, instructor access denied by default | K12: Legal & Compliance | L12: CQC0026
A13: D01 | B13: AI SME Chatbot — Learner-Facing | C13: Interfaces | D13: 3 | E13: Shaper | F13: Before first integration | G13: PRODM | H13: L1 Junior | I13: Is the learner-facing chatbot sold as something learners reach directly, or only inside the customer's LMS - because that changes who we are contracting with about learner accounts? | J13: delivered through the customer LMS by default with the customer as controller of learner identity, and a direct-access mode only where a customer has no LMS and accepts the separate terms | K13: Product Owner | L13: CQU0100
A14: D01 | B14: AI SME Chatbot — Learner-Facing | C14: Interfaces | D14: 4 | E14: Shaper | F14: Before first integration | G14: AI | H14: L2 Mid | I14: If E04 activates a new embedding model version, does my index become invalid immediately and who tells me - or do I pin the embedding version per index and refuse mismatched queries? | J14: pin the embedding model version in index metadata and hard-fail any query whose serving version differs, with an operator alert | K14: Another squad | L14: CQC0027
A15: D01 | B15: AI SME Chatbot — Learner-Facing | C15: Data | D15: 1 | E15: Blocker | F15: Before first code | G15: DE | H15: L2 Mid | I15: What are the mandatory fields on every chunk - I have doc ID, revision, effective date and supersedes - and is there anything else retrieval or the UI needs, like page anchor or classification? | J15: doc ID, revision, effective date, supersedes, page anchor, section path, tenant ID and classification marking on every chunk | K15: Data Owner | L15: CQC0015
A16: D01 | B16: AI SME Chatbot — Learner-Facing | C16: Data | D16: 2 | E16: Blocker | F16: Before first code | G16: AI | H16: L2 Mid | I16: When a manual revision is withdrawn, how many minutes or hours may pass before its chunks stop being retrievable - what is the supersession SLA? | J16: HARD BLOCKER - no default possible | K16: NOBODY OWNS THIS | L16: CQC0016
... A2707: XCUT | B2707: Cross-cutting concern / Whole Product | C2707: Handover | D2707: 43 | E2707: Refiner | F2707: Before first release | G2707: SUP | H2707: L4 Architect | I2707: Is there one artefact that documents the whole journey with an owner per hop, and who keeps it current - because I am inheriting support for something described in four separate architecture decks. | J2707: One maintained journey map per major journey listing hops, owning squads, SLOs and runbook links, updated as part of every interface change | K2707: Programme Manager | L2707: CQH0076

Sheet Role Packs
A1: Role Packs
A2: Filter to your role. Work the 'Before sprint 0' block first, then 'Before first code'. Blockers are listed first inside each block.
A4: Role | B4: Role name | C4: Needed by | D4: # | E4: Blocking | F4: Level | G4: ProductID | H4: Stage | I4: Question | J4: Proposed default | K4: Ask | L4: CQID | M4: Answer / decision
A5: FE | B5: Front-End Developer | C5: Before sprint 0 | D5: 1 | E5: Blocker | F5: L1 Junior | G5: E03 | H5: BuildEnv | I5: Do I have a local Moodle with LTI configured that I can develop against, or do I have to book time on a shared instance - because launch work is untestable without one. | J5: A docker-compose Moodle with a pre-registered EdVidura tool and seeded courses, committed to the repository and maintained by the E03 squad. | K5: Another squad | L5: CQA0103
A6: FE | B6: Front-End Developer | C6: Before sprint 0 | D6: 2 | E6: Blocker | F6: L1 Junior | G6: XCUT | H6: Rules | I6: When I am blocked, who do I ask - is there a named technical lead for my squad, or do I post in a channel and wait? | J6: A named squad lead as first point of contact, with a daily standup blocker slot and a visible blocked column on the board | K6: Programme Manager | L6: CQH0241
A7: FE | B7: Front-End Developer | C7: Before sprint 0 | D7: 3 | E7: Blocker | F7: L4 Architect | G7: D24 | H7: Scope | I7: Which platforms does the microlearning app ship on - Android only, Android plus iOS, or a progressive web app - because iOS appears on the platform list for this product but not for the XR store and I need one consistent answer? | J7: One cross-platform client built once and shipped to Android and iOS, with a progressive web fallback explicitly out of scope | K7: Product Owner | L7: CQE0098
A8: FE | B8: Front-End Developer | C8: Before sprint 0 | D8: 4 | E8: Blocker | F8: L4 Architect | G8: E01 | H8: Understand | I8: Which front-end framework are we permanently committing the client's own team to maintain after handover - React, Angular or Vue - and has anyone actually asked what their engineers already know, because this is the single hardest decision to reverse? | J8: React with TypeScript, on the LTS-style release train, because it has the deepest Indian hiring pool - subject to confirmation that the client's team is not an Angular shop | K8: Client SME | L8: CQT0010
A9: FE | B9: Front-End Developer | C9: Before sprint 0 | D9: 5 | E9: Blocker | F9: L4 Architect | G9: E01 | H9: BuildEnv | I9: Do all web surfaces live in one monorepo with a single build and release pipeline, or one repo per product with independent releases - and if separate, do we run micro-frontends behind one shell or entirely separate applications? | J9: One monorepo with independently versioned packages and per-app deploy pipelines; no runtime micro-frontend composition in release one | K9: Solution Architect | L9: CQT0011
A10: FE | B10: Front-End Developer | C10: Before sprint 0 | D10: 6 | E10: Shaper | F10: L1 Junior | G10: XCUT | H10: Understand | I10: What should my first two weeks produce - a running local environment and one merged pull request, or a design document - because I would like to know what good looks like. | J10: Week one: environment running, code checked out, one small merged change. Week two: one real story delivered to the definition of done | K10: Programme Manager | L10: CQH0244
A11: FE | B11: Front-End Developer | C11: Before first code | D11: 1 | E11: Blocker | F11: L1 Junior | G11: D01 | H11: UI/UX | I11: Do I build the chat UI from our own component library or reuse an existing chat component, and where is the design system I am supposed to be using? | J11: build on the EdVidura component library if one exists; otherwise Radix primitives plus our tokens, no third-party chat widget | K11: Product Owner | L11: CQC0029
A12: FE | B12: Front-End Developer | C12: Before first code | D12: 2 | E12: Blocker | F12: L1 Junior | G12: D02 | H12: UI/UX | I12: Where does the grader queue actually live - inside the LMS via an LTI launch, in our own web app, or both - because that changes the whole navigation model? | J12: our own web app with an LTI deep link from the LMS into a specific queue, single sign-on via the platform identity service | K12: Product Owner | L12: CQC0065
A13: FE | B13: Front-End Developer | C13: Before first code | D13: 3 | E13: Blocker | F13: L1 Junior | G13: D11 | H13: Understand | I13: What block types exist in a lesson for slice A - I propose text, image, video, table, procedure step, knowledge check and embedded eBook section - and which of those are actually in scope now? | J13: Those seven block types in slice A, with a registry that allows new types without a schema migration | K13: Instructional Designer | L13: CQD0035
A14: FE | B14: Front-End Developer | C14: Before first code | D14: 4 | E14: Blocker | F14: L1 Junior | G14: D11 | H14: BuildEnv | I14: Which design system and component library do I build the authoring canvas from - is there an EdVidura component library I reuse, or do I build the editor components from scratch? | J14: Reuse the platform component library for chrome and forms, and build only the canvas and block components bespoke on a documented rich-text editor | K14: Solution Architect | L14: CQD0036
A15: FE | B15: Front-End Developer | C15: Before first code | D15: 5 | E15: Blocker | F15: L1 Junior | G15: D12 | H15: BuildEnv | I15: Does the reader ship as a web app, a progressive web app or a native Android and Windows application - because offline reading and encryption at rest push in different directions? | J15: A progressive web app with an installable Android wrapper for offline and encrypted storage | K15: Solution Architect | L15: CQD0089
A16: FE | B16: Front-End Developer | C16: Before first code | D16: 6 | E16: Blocker | F16: L1 Junior | G16: D13 | H16: UI/UX | I16: Does the assistant panel reuse the DCT design system, or does it get its own components - and if the DCT does not have a design system yet, what do I build against? | J16: reuse DCT tokens and primitives; where the DCT has none, define panel-local tokens in a file that can be replaced wholesale later | K16: Product Owner | L16: CQC0100
... A2707: UXD | B2707: UI/UX Designer | C2707: Before first release | D2707: 145 | E2707: Refiner | F2707: L3 Senior | G2707: XCUT | H2707: Handover | I2707: Who owns the design system documentation, and where does a new front-end joiner read how to use it in their first week? | J2707: A published Storybook with usage, do and do not guidance, accessibility notes and token reference, owned by the design system maintainer | K2707: Another squad | L2707: CQH0136

Sheet Decision Agenda
A1: Decision Agenda
A2: One agenda per answerer, ordered by urgency. Run the meeting as a review of the proposed defaults: for each row the answerer says CONFIRM or gives the correction. Rows marked HARD have no default — those must be decided, not defaulted. Rows under 'NOBODY OWNS THIS' are not a meeting; they are an escalation.
A4: Addressed to | B4: # | C4: Needed by | D4: Blocking | E4: Hard? | F4: ProductID | G4: Asked by | H4: Question | I4: Proposed default — confirm or correct | J4: Answer must arrive as | K4: CQID | L4: Decision | M4: Date
A5: Solution Architect | B5: 1 | C5: Before sprint 0 | D5: Blocker | F5: D03 | G5: SEC | H5: Where exactly does the accreditation boundary sit - does it include the cloud build pipeline, the Metabase analytics stack and the local model serving host, or only the enclave runtime - and who draws that line? | I5: Boundary is the enclave runtime plus the media-drop ingest path; the cloud build pipeline is an external connected system documented as an interconnection | J5: decision record | K5: CQF0007
A6: Solution Architect | B6: 2 | C6: Before sprint 0 | D6: Blocker | F6: D06 | G6: DE | H6: Is there one ELRR per enclave that later federates upward, or one central ELRR that enclaves write into - because that choice fixes our network, our identity model and our exit path? | I6: One ELRR per enclave as the authoritative local store, federating summaries upward to an enterprise index | J6: decision record | K6: CQB0025
A7: Solution Architect | B7: 3 | C7: Before sprint 0 | D7: Blocker | F7: D07 | G7: DE | H7: Is the catalogue one enterprise instance or one per organisation with federation between them - and if federated, is a course record copied or referenced across the boundary? | I7: One catalogue per organisation, federating course summaries with a stable global course URI, never copying full records | J7: decision record | K7: CQB0058
A8: Solution Architect | B8: 4 | C8: Before sprint 0 | D8: Blocker | F8: D08 | G8: BE | H8: Is the registry a service other products call at runtime, or a library plus data bundle each product embeds - because the enclave and offline cases push hard toward embedding? | I8: A service with a published embeddable snapshot bundle, so online consumers call it and offline consumers embed it | J8: decision record | K8: CQB0103
A9: Solution Architect | B9: 5 | C9: Before sprint 0 | D9: Blocker | F9: D10 | G9: DEVOPS | H9: Which repository and pipeline do I create the connector in, and which environment names exist for it - I currently have no repo, no pipeline and no environment to deploy to? | I9: New repo edvidura-to-connector in the platform organisation, standard three environments dev, staging, prod, reusing the platform pipeline template | J9: link to existing spec | K9: CQD0016
A10: Solution Architect | B10: 6 | C10: Before sprint 0 | D10: Blocker | F10: D12 | G10: BE | H10: Does D12 own the conversion from source PDF to structured eBook, or does D10 hand me an already-structured document and I only build the reader? | I10: D10 owns acquisition and raw storage; D12 owns OCR, structuring, chunking and the reader | J10: decision record | K10: CQD0070
A11: Solution Architect | B11: 7 | C11: Before sprint 0 | D11: Blocker | F11: D13 | G11: AI | H11: Should the authoring assistant use a different model from the learner chatbot on the same appliance, or must all three assistants share one resident model? | I11: one shared instruction-tuned model for all three assistants until measurement proves a task-specific model is needed | J11: decision record | K11: CQC0079
A12: Solution Architect | B12: 8 | C12: Before sprint 0 | D12: Blocker | F12: D13 | G12: AI | H12: Which parts of M23 are genuinely separate from M15 rather than a different prompt over the same machinery - do I get a shared retrieval library or do I write my own? | I12: M23 reuses the M15 retrieval library as a versioned internal package and owns only its corpus, prompts and guardrails | J12: decision record | K12: CQC0080
A13: Solution Architect | B13: 9 | C13: Before sprint 0 | D13: Blocker | F13: D14 | G13: AI | H13: Is any model inference involved in sequencing at all, or is this purely a rules engine - because that decides whether I am a consumer of the GPU appliance or not? | I13: deterministic rules engine only in v1; no model inference, so no dependency on the shared appliance | J13: decision record | K13: CQC0116
A14: Solution Architect | B14: 10 | C14: Before sprint 0 | D14: Blocker | F14: D15 | G14: DEVOPS | H14: Which repository and which service template do I start D15 in, and does it share a database with the competency registry or have its own? | I14: Own repository, own database, communicating with the registry only over its API | J14: decision record | K14: CQD0129
A15: Solution Architect | B15: 11 | C15: Before sprint 0 | D15: Blocker | F15: D16 | G15: PM | H15: Does profile management own authentication and session, or does Core Platform Identity own that and I only hold the profile record? | I15: Core Platform owns authentication and session; profile management holds the record and its access rules only | J15: decision record | K15: CQB0128
A16: Solution Architect | B16: 12 | C16: Before sprint 0 | D16: Blocker | F16: D16 | G16: BE | H16: Is there one profile store per enclave with an enterprise index above, or one central store all enclaves read - and if central, how does an enclave function when disconnected? | I16: One authoritative profile store per enclave, with an enterprise index holding only pseudonymous keys and coarse summaries | J16: decision record | K16: CQB0130
A17: Solution Architect | B17: 13 | C17: Before sprint 0 | D17: Blocker | E17: HARD | F17: D17 | G17: DE | H17: What unit of data actually crosses the boundary in this pipeline - full xAPI statements, aggregated summaries, or signed assertions - because that single choice determines the schema, the volume, the privacy position and the trust model? | I17: HARD BLOCKER - no default possible | J17: decision record | K17: CQB0143
A18: Solution Architect | B18: 14 | C18: Before sprint 0 | D18: Blocker | F18: D17 | G18: PM | H18: Does this pipeline carry only learning records, or is it the general cross-organisation transport for profiles, catalogue and competency data as well? | I18: One general transport with typed payloads for records, catalogue and competency data; profile data only if the DPDP position permits | J18: decision record | K18: CQB0165
A19: Solution Architect | B19: 15 | C19: Before sprint 0 | D19: Blocker | F19: D17 | G19: BE | H19: Is the pipeline a hub with a central broker, or point-to-point between organisation pairs - because a hub needs an owner nobody has named and point-to-point scales as the square of partners? | I19: Point-to-point for the first three partners with a hub option designed but not built, since a hub requires an owning authority that does not yet exist | J19: decision record | K19: CQB0172
A20: Solution Architect | B20: 16 | C20: Before sprint 0 | D20: Blocker | F20: D18 | G20: BI | H20: We are on Metabase OSS, which has no paid data sandboxing, so per-tenant and per-command isolation has to be enforced in the database rather than in the BI tool - has that been decided, and is anyone still expecting me to buy Metabase Pro instead? | I20: Metabase OSS stays, isolation is enforced by Postgres row-level security on the mart schemas, and Metabase connects as a per-tenant database role rather than one superuser | J20: decision record | K20: CQE0001
A21: Solution Architect | B21: 17 | C21: Before sprint 0 | D21: Blocker | F21: D19 | G21: MXR | H21: Which engine and which version are we building on - Unity or Unreal, and which LTS release - because it is not written anywhere I can find and I cannot set up a build machine without it? | I21: Unity on the current LTS release, pinned in the repo, with the version recorded in the build configuration and upgraded only as a planned activity | J21: decision record | K21: CQT0207
A22: Solution Architect | B22: 18 | C22: Before sprint 0 | D22: Blocker | F22: D22 | G22: AI | H22: Does step scoring run on the device, on the shared inference appliance, or after the session - because that decides whether I am a fourth GPU consumer? | I22: post-session batch scoring on the shared appliance at the lowest priority class; no in-session model inference | J22: decision record | K22: CQC0152
A23: Solution Architect | B23: 19 | C23: Before sprint 0 | D23: Blocker | F23: D23 | G23: PRODM | H23: Is difference training a module inside the authoring tool, a feature of the learning engine, or a standalone application - because right now three products could all plausibly own it? | I23: Standalone service with its own screens, consuming content and assignment data and publishing completions - it owns the gap concept and nothing else does | J23: decision record | K23: CQD0156
A24: Solution Architect | B24: 20 | C24: Before sprint 0 | D24: Blocker | F24: D23 | G24: DEVOPS | H24: Which repository does D23 live in, and can I get a test fixture of equipment and assignment data seeded into a dev environment, because I have neither today? | I24: Own repository with a seeding script generating 500 synthetic learners across 20 variants, run on every environment refresh | J24: decision record | K24: CQD0160
A25: Solution Architect | B25: 21 | C25: Before sprint 0 | D25: Blocker | F25: E01 | G25: DEVOPS | H25: Which secrets manager am I building against - HashiCorp Vault, sealed-secrets in git, or the customer's existing store - and does the answer change inside an air-gapped enclave? | I25: HashiCorp Vault OSS deployed as part of the platform bundle, with a file-based unseal procedure for enclaves. | J25: decision record | K25: CQA0013
A26: Solution Architect | B26: 22 | C26: Before sprint 0 | D26: Blocker | F26: E01 | G26: FE | H26: Do all web surfaces live in one monorepo with a single build and release pipeline, or one repo per product with independent releases - and if separate, do we run micro-frontends behind one shell or entirely separate applications? | I26: One monorepo with independently versioned packages and per-app deploy pipelines; no runtime micro-frontend composition in release one | J26: decision record | K26: CQT0011
A27: Solution Architect | B27: 23 | C27: Before sprint 0 | D27: Blocker | F27: E02 | G27: PRODM | H27: What is explicitly NOT the spine's job - do I own competency inference, grade calculation, or aggregation, or am I purely a validated write-and-store layer? | I27: The spine validates, stores, dedups and serves; it never computes a grade, infers a competency or aggregates a metric. | J27: decision record | K27: CQA0075
A28: Solution Architect | B28: 24 | C28: Before sprint 0 | D28: Blocker | F28: E02 | G28: DEVOPS | H28: Which LRS product and pinned version am I deploying, and is it in our release bundle or does the customer supply it - the checklist says xAPI-conformant but never names one. | I28: A named open-source xAPI-conformant LRS pinned at a specific minor version, shipped in our bundle, with a documented replacement path. | J28: decision record | K28: CQA0070
A29: Solution Architect | B29: 25 | C29: Before sprint 0 | D29: Blocker | F29: E04 | G29: AI | H29: Is E04 one shared service for all AI consumers, or does each product get its own serving process on the same box? | I29: one shared service with admission control across all consumers; per-product processes are not supported | J29: decision record | K29: CQC0167
... A32: Solution Architect | B32: 28 | C32: Before sprint 0 | D32: Blocker | F32: XCUT | G32: BE | H32: Who owns the event envelope contract - the spine squad, the platform squad, or an architecture board - because two documents currently imply different owners and I need one name before I can propose a field. | I32: The spine squad owns it, with an architecture board approving breaking changes only. | J32: named person | K32: CQA0139
A33: Solution Architect | B33: 29 | C33: Before sprint 0 | D33: Blocker | E33: HARD | F33: XCUT | G33: BE | H33: Across the whole platform, do we federate raw xAPI statements, derived summaries, or signed assertions - and is that one answer for everyone or negotiated per partner? | I33: HARD BLOCKER - no default possible | J33: decision record | K33: CQB0242
A34: Solution Architect | B34: 30 | C34: Before sprint 0 | D34: Blocker | F34: XCUT | G34: AI | H34: Which serving stack are we standardising on - vLLM, Ollama, or something else - and was that decision recorded anywhere? | I34: vLLM-class serving for continuous batching and admission control, behind an OpenAI-compatible contract so the stack can be replaced | J34: decision record | K34: CQC0243
A35: Solution Architect | B35: 31 | C35: Before sprint 0 | D35: Blocker | F35: XCUT | G35: BI | H35: Is Metabase OSS the committed BI tool across the whole programme, or is it a starting point we may replace - because building the semantic layer inside Metabase questions versus in the warehouse are irreversible choices? | I35: Metabase OSS is committed for three years, and all metric logic lives in warehouse views and models so the BI tool holds presentation only and can be replaced in weeks not quarters | J35: decision record | K35: CQE0192
A36: Solution Architect | B36: 32 | C36: Before sprint 0 | D36: Blocker | F36: XCUT | G36: BE | H36: Is offline-first a platform capability we build once - one sync library, one queue format, one conflict policy - or does each client team implement its own, because right now four clients are each about to invent it? | I36: One shared sync specification with a reference implementation per platform, owned by the platform squad, with the wire protocol frozen before any client ships | J36: decision record | K36: CQE0235
A37: Solution Architect | B37: 33 | C37: Before sprint 0 | D37: Blocker | F37: XCUT | G37: BE | H37: What actually makes an interface published rather than internal - is it external consumption, a contractual listing, or a decision we make - and who approves promoting an interface to published status? | I37: Published means listed in the interface register and approved by the architecture function, triggering versioning, deprecation and conformance obligations from that moment | J37: decision record | K37: CQF0239
A38: Solution Architect | B38: 34 | C38: Before sprint 0 | D38: Blocker | F38: XCUT | G38: DEVOPS | H38: Do we build our own observability stack or buy one, and does the enclave requirement force us to self-host everything anyway - because that decides the operating cost per customer. | I38: Self-host one open stack everywhere, accepting the operational cost, because a second stack for enclaves doubles the support procedures | J38: decision record | K38: CQH0204
A39: Solution Architect | B39: 35 | C39: Before sprint 0 | D39: Blocker | F39: XCUT | G39: PM | H39: Is federation a shared platform capability one squad owns, or does each product build its own federation path - because right now every product plan assumes someone else owns it? | I39: One squad owns a shared federation library and console; products own only their payload transforms | J39: decision record | K39: CQB0282
A40: Solution Architect | B40: 36 | C40: Before sprint 0 | D40: Blocker | F40: XCUT | G40: AI | H40: Is retrieval a shared service that all three chatbots call, or a library each embeds - and what does that choice cost us later? | I40: a versioned internal library in v1 with a service-shaped interface, so extraction later is mechanical rather than architectural | J40: decision record | K40: CQC0219
A41: Solution Architect | B41: 37 | C41: Before sprint 0 | D41: Blocker | F41: XCUT | G41: BE | H41: Which components are we actually claiming are replaceable - could a customer really swap out the learning records store, the authoring tool or the inference platform - and has anyone checked that the interfaces support it? | I41: Claim replaceability only for the inference platform, the records store and the LMS integration, and state explicitly that the authoring and sequencing components are not independently replaceable | J41: decision record | K41: CQF0257
A42: Solution Architect | B42: 38 | C42: Before sprint 0 | D42: Blocker | F42: XCUT | G42: DE | H42: Which warehouse are the marts built in - the same Postgres as the transactional services, a separate analytical Postgres, or something else - because RLS, cost and enclave portability all depend on it? | I42: A separate Postgres instance for marts, chosen because it supports row-level security natively and can be packaged into an enclave, with no managed cloud analytics service | J42: decision record | K42: CQE0195
A43: Solution Architect | B43: 39 | C43: Before sprint 0 | D43: Blocker | F43: XCUT | G43: BE | H43: Is EdVidura one monorepo or a repository per product - which repository does my first commit go into, and who grants me access to it? | I43: A repository per deployable service plus one shared libraries repository, with access granted by squad membership | J43: link to existing spec | K43: CQH0205
A44: Solution Architect | B44: 40 | C44: Before sprint 0 | D44: Blocker | F44: XCUT | G44: DEVOPS | H44: Which environments exist - development, test, staging, pre-production, production - and which one do I develop against on my first day? | I44: Local, a shared integration environment, staging and production, with staging the only pre-production environment that mirrors real integrations | J44: link to existing spec | K44: CQH0224
A45: Solution Architect | B45: 41 | C45: Before sprint 0 | D45: Shaper | F45: D11 | G45: DEVOPS | H45: Which repository do the authoring front end and its backend live in, and is there a preview environment where an instructional designer can try a build before release? | I45: One repo with front end and service together, plus an always-on preview environment refreshed from main every night | J45: decision record | K45: CQD0063
... A632: Product Owner | B632: 30 | C632: Before sprint 0 | D632: Blocker | F632: E10 | G632: PRODM | H632: What exactly are we selling in India - a platform licence, a services engagement, a delivered site, or all three as one bundle - I need the actual list of sellable items? | I632: a platform subscription per learner plus a separately priced site deployment package plus optional professional services, listed as three line items rather than one bundled price | J632: decision record | K632: CQU0091
A633: Product Owner | B633: 31 | C633: Before sprint 0 | D633: Blocker | E633: HARD | F633: E10 | G633: PRODM | H633: Who is the buyer in India - which customer types are we actually targeting, and who signs the purchase order in each of them? | I633: HARD BLOCKER - no default possible | J633: decision record | K633: CQU0092
A634: Product Owner | B634: 32 | C634: Before sprint 0 | D634: Blocker | F634: E12 | G634: PM | H634: What artefacts actually constitute the deployment kit - is it a bill of materials, a site survey template, an installation runbook, a commissioning checklist, a signage pack and a training package, or something smaller? | I634: Six artefacts - bill of materials, site survey template, installation runbook, commissioning and acceptance checklist, signage and wayfinding pack, and technician training package - each versioned and released together as a kit version | J634: decision record | K634: CQE0161
A635: Product Owner | B635: 33 | C635: Before sprint 0 | D635: Blocker | F635: E12 | G635: PM | H635: How many sites is this kit designed to be used for and over what period, because a kit for three sites and a kit for thirty are different levels of investment in tooling and standardisation? | I635: Design for ten sites over three years - fully templated documents and a scripted software build, but manual site survey and manual fit-out coordination | J635: decision record | K635: CQE0162
A636: Product Owner | B636: 34 | C636: Before sprint 0 | D636: Blocker | F636: E13 | G636: PRODM | H636: What is the enablement deliverable - an internal academy, a set of runbooks, or a certification for our own staff - because they are three different pieces of work? | I636: A role-based onboarding path plus maintained runbooks; no internal certification scheme in year one | J636: decision record | K636: CQG0157
A637: Product Owner | B637: 35 | C637: Before sprint 0 | D637: Blocker | F637: XCUT | G637: ID | H637: As a content designer, do I author once for all tenants or per tenant - because that decides whether I am building a shared library or a per-customer deliverable. | I637: Author once into a shared library, with tenant-specific overlays for local procedure variations. | J637: decision record | K637: CQA0299
A638: Product Owner | B638: 36 | C638: Before sprint 0 | D638: Blocker | F638: XCUT | G638: ID | H638: What does supported actually mean per tier - interface only, interface plus notices, interface plus content, or all of that plus AI answers and support? | I638: Three tiers - tier 1 is interface, notices, content and AI; tier 2 is interface, notices and content; tier 3 is interface and notices only | J638: decision record | K638: CQG0188
A639: Product Owner | B639: 37 | C639: Before sprint 0 | D639: Blocker | F639: XCUT | G639: UXD | H639: Do all nine EdVidura surfaces - quiz player, eBook reader, chatbot widget, dashboards, authoring tool, XR store, mobile app, admin consoles and support console - share one component library, or does each squad build its own? | I639: One shared web component library covering all browser surfaces, with documented parallel kits for Metabase and Unity that share tokens but not code | J639: decision record | K639: CQH0079
A640: Product Owner | B640: 38 | C640: Before sprint 0 | D640: Blocker | E640: HARD | F640: XCUT | G640: UXD | H640: Is there a UX research budget, and do we have access to any real learners or instructors before first release - or are we designing entirely from documents and assumptions? | I640: HARD BLOCKER - no default possible | J640: named person | K640: CQH0144
A641: Product Owner | B641: 39 | C641: Before sprint 0 | D641: Blocker | F641: XCUT | G641: PM | H641: Which clients genuinely have to work offline and which merely tolerate a brief disconnection - because offline-first is expensive and applying it everywhere doubles four squads of work? | I641: Full offline-first for the microlearning app, the MOE capture app and the lab edge; the XR store and the dashboards are connection-tolerant with a cached read-only view only | J641: decision record | K641: CQE0269
A642: Product Owner | B642: 40 | C642: Before sprint 0 | D642: Blocker | E642: HARD | F642: XCUT | G642: UXD | H642: Which languages must the interface ship in at first release - English only, English plus Hindi, or a wider Indic set - and who supplies and pays for the translations? | I642: HARD BLOCKER - no default possible | J642: signed document | K642: CQH0108
A643: Product Owner | B643: 41 | C643: Before sprint 0 | D643: Shaper | F643: D18 | G643: PRODM | H643: Is the analytics suite a product we sell as self-service exploration, or a fixed set of curated dashboards - because self-service means giving customers SQL access to the mart and that changes the entire isolation and cost model? | I643: Curated dashboards only for release one; no native query access for customers, with an explicit self-service exploration slice considered later once RLS is proven | J643: decision record | K643: CQE0031
A644: Product Owner | B644: 42 | C644: Before sprint 0 | D644: Shaper | F644: D18 | G644: BI | H644: There are dashboards named for commanders, instructors, learners, training officers and programme staff - which one am I building in sprint one, and is there a wireframe or a list of the questions it must answer? | I644: Start with the instructor cohort-progress dashboard because it has the clearest data available today, and treat the commander view as sprint three | J644: link to existing spec | K644: CQT0048
A645: Product Owner | B645: 43 | C645: Before sprint 0 | D645: Shaper | F645: D20 | G645: PRODM | H645: Is this lab a reference site we sell from, or an operational training facility with real learners - because a demonstration room and a production classroom have different uptime, safety and support obligations? | I645: Both, in sequence - a reference and demonstration site for the first quarter, then an operational classroom, with the support model designed to the operational standard from the start | J645: decision record | K645: CQE0093
A646: Product Owner | B646: 44 | C646: Before sprint 0 | D646: Shaper | F646: D25 | G646: DA | H646: Will this result be used in marketing or in a future procurement, and if so does it need external validation by an academic partner or a third-party evaluator to survive scrutiny? | I646: Design for external defensibility from the start - pre-register the analysis plan internally before baseline capture and keep the analysis reproducible from raw data | J646: decision record | K646: CQF0054
A647: Product Owner | B647: 45 | C647: Before sprint 0 | D647: Shaper | F647: E12 | G647: PRODM | H647: Is the kit something we sell to a customer to self-deploy, or an internal delivery tool - because a sold kit needs documentation, warranty and liability positions that an internal tool does not? | I647: An internal delivery tool for release one, with a customer self-deploy variant explicitly out of scope until three sites have been delivered by us | J647: decision record | K647: CQE0186
A648: Product Owner | B648: 46 | C648: Before sprint 0 | D648: Shaper | F648: XCUT | G648: AIG | H648: How much capability are we knowingly giving up by running local quantised models in an enclave rather than a frontier hosted model - and has the client been told in writing that the enclave assistant will be materially less capable than what they were shown in a demo? | I648: Demonstrations use the same local quantised model that will be deployed, and any capability gap is documented in the solution description before contract | J648: signed document | K648: CQT0184
A649: Product Owner | B649: 47 | C649: Before sprint 0 | D649: Shaper | F649: XCUT | G649: PRODM | H649: Is per-customer theming a sold feature with a price attached, a standard capability we give away, or an assumption nobody has tested with a customer? | I649: Treat basic theming as standard and included, and anything beyond the token allowlist as a chargeable professional services engagement | J649: decision record | K649: CQH0095
A650: Product Owner | B650: 48 | C650: Before sprint 0 | D650: Shaper | F650: XCUT | G650: PRODM | H650: Is there a single definition of done that applies across all squads, including documentation, tests, accessibility and support handoff - or does each squad set its own? | I650: One programme definition of done covering tests at the required layers, updated documentation, accessibility pass, support notes and evidence published, with squads free to add but not subtract | J650: decision record | K650: CQF0238
A651: Product Owner | B651: 49 | C651: Before first code | D651: Blocker | F651: D01 | G651: AI | H651: Which document set is the learner chatbot allowed to answer from on day one - only manuals approved in the M25 lineage service, or also DCT-authored lessons and course pages? | I651: approved technical manuals only; DCT lessons excluded until a separate corpus decision is recorded | J651: decision record | K651: CQC0001
A652: Product Owner | B652: 50 | C652: Before first code | D652: Blocker | F652: D01 | G652: AIG | H652: Is there a written list of what the learner chatbot must refuse to answer, and can I read it today - because I am implementing refusals from my own judgement and that will not survive a review? | I652: A written refusal policy covering out-of-corpus questions, safety-critical procedures without a citation, personal data requests and anything about other learners - held in the repo alongside the prompts | J652: link to existing spec | K652: CQT0139
A653: Product Owner | B653: 51 | C653: Before first code | D653: Blocker | F653: D01 | G653: UXD | H653: What does one citation look like inside an answer - an inline numbered marker, a footnote block under the answer, or a side panel - and does it show manual title, revision and page or just the title? | I653: inline numbered markers that expand to a footnote card showing manual title, revision ID, effective date and page anchor | J653: decision record | K653: CQC0004
A654: Product Owner | B654: 52 | C654: Before first code | D654: Blocker | F654: D01 | G654: FE | H654: Do I build the chat UI from our own component library or reuse an existing chat component, and where is the design system I am supposed to be using? | I654: build on the EdVidura component library if one exists; otherwise Radix primitives plus our tokens, no third-party chat widget | J654: link to existing spec | K654: CQC0029
... A729: Product Owner | B729: 127 | C729: Before first code | D729: Blocker | F729: XCUT | G729: AI | H729: The index returns nothing above the relevance threshold - does the chatbot refuse, answer from the base model with a disclaimer, or escalate to a human, and who owns that policy across all three chatbots? | I729: Refuse with a stated reason and offer a search of the manual index plus a route to raise a question to an SME; never answer from base model knowledge on technical content | J729: decision record | K729: CQH0065
A730: Product Owner | B730: 128 | C730: Before first code | D730: Blocker | E730: HARD | F730: XCUT | G730: FE | H730: Which Indic scripts must actually render - Devanagari only, or Tamil, Telugu, Bengali and Gurmukhi as well - and which font family do we license and ship for them? | I730: HARD BLOCKER - no default possible | J730: signed document | K730: CQH0112
A731: Product Owner | B731: 129 | C731: Before first code | D731: Blocker | F731: XCUT | G731: BE | H731: What is the maximum offline period a client must survive without data loss - a day, a week, a quarter - because that number sets every queue size, token lifetime and cache budget across all four clients? | I731: 90 days for lab edge and MOE devices, 30 days for the microlearning app and the XR store, published as a platform commitment that every client is tested against | J731: number with units | K731: CQE0240
A732: Product Owner | B732: 130 | C732: Before first code | D732: Blocker | F732: XCUT | G732: UXD | H732: Metabase dashboards cannot consume our components - do we accept two visual languages, restyle Metabase to our tokens, or build our own dashboard shell around embedded charts? | I732: Restyle Metabase with our token values and embed it inside our own application shell, accepting minor divergence inside chart chrome | J732: decision record | K732: CQH0086
A733: Product Owner | B733: 131 | C733: Before first code | D733: Shaper | F733: D01 | G733: AIG | H733: When a learner asks something the corpus does not cover - a general question about a technology rather than the manual - do I refuse, or let the model answer from its own knowledge with a warning that it is not from an approved source? | I733: Refuse and offer to search the corpus differently; the bot never answers from model parametric knowledge in the learner-facing assistant | J733: decision record | K733: CQT0140
A734: Product Owner | B734: 132 | C734: Before first code | D734: Shaper | F734: D01 | G734: AIG | H734: What is our product stance when the model is uncertain - do we refuse, or do we hedge and let the learner judge - because in a maintenance training context a hedged answer is often more dangerous than no answer, and this stance shapes every guardrail we build? | I734: Refuse rather than hedge for anything procedural or safety-relevant; hedging is permitted only for conceptual and study-support questions, and the two classes are distinguished by the corpus the answer comes from | J734: decision record | K734: CQT0185
A735: Product Owner | B735: 133 | C735: Before first code | D735: Shaper | F735: D01 | G735: UXD | H735: How is a superseded source visually flagged if a superseded chunk is ever surfaced - a red strike on the citation card, a full-answer warning bar, or is the answer simply blocked? | I735: superseded chunks are never retrievable, so the surface case is only a stale corpus; show a persistent amber bar giving corpus-verified-as-of date | J735: decision record | K735: CQC0006
A736: Product Owner | B736: 134 | C736: Before first code | D736: Shaper | F736: D02 | G736: AI | H736: What does grounded mean for us in practice - must every sentence in an answer be traceable to a retrieved chunk, or is it enough that the answer does not contradict the sources - because that changes how I build the generation step? | I736: Every factual claim must carry a citation to a retrieved chunk; unsupported sentences are removed before the answer is returned, and if nothing is supported the bot refuses | J736: decision record | K736: CQT0130
A737: Product Owner | B737: 135 | C737: Before first code | D737: Shaper | F737: D02 | G737: BE | H737: If a learner submits the same attempt twice because the page hung during grading, do I grade both, dedupe on an idempotency key, or reject the second? | I737: dedupe on an attempt idempotency key; the second submit returns the first attempt state and never creates a second grading job | J737: decision record | K737: CQC0057
A738: Product Owner | B738: 136 | C738: Before first code | D738: Shaper | F738: D06 | G738: FE | H738: On the learner experience-index screen, which four or five facts do we show above the fold - last activity, total completions, current competencies, or something else - because I need the field list to build the header component? | I738: Show last activity date, completions in the last 12 months, in-progress items and count of held competencies | J738: decision record | K738: CQB0006
A739: Product Owner | B739: 137 | C739: Before first code | D739: Shaper | F739: D06 | G739: UXD | H739: What does a learner see in the experience index on day one when no records exist for them at all - an empty state with guidance, a hidden screen, or a seeded placeholder record? | I739: An explicit empty state that names what will appear here and where records come from, with no seeded data | J739: decision record | K739: CQB0007
A740: Product Owner | B740: 138 | C740: Before first code | D740: Shaper | F740: D06 | G740: FE | H740: Which Indic scripts must the learner index render at launch and what text-expansion allowance do I design the labels to - 30 percent, 50 percent, or a per-language figure? | I740: Design for Devanagari plus English at launch with a 40 percent expansion allowance and no fixed-width labels | J740: decision record | K740: CQB0011
A741: Product Owner | B741: 139 | C741: Before first code | D741: Shaper | F741: D07 | G741: FE | H741: On the catalogue search screen, what are the default filters visible without opening an advanced panel - organisation, competency, delivery mode, language, duration - and in what order? | I741: Show competency, delivery mode and language by default; everything else behind an advanced panel | J741: decision record | K741: CQB0042
A742: Product Owner | B742: 140 | C742: Before first code | D742: Shaper | F742: D11 | G742: FE | H742: What is the autosave interval on the canvas, and does an autosave create a version history entry or only the explicit save? | I742: Autosave every 20 seconds when dirty, autosaves overwrite a working draft, version entries created only on explicit save or publish | J742: number with units | K742: CQD0042
... A1172: Programme Manager | B1172: 6 | C1172: Before sprint 0 | D1172: Blocker | F1172: D09 | G1172: PM | H1172: Where does the evidence repository live - our own document system, the client system, or a shared space - and who provisions it? | I1172: Our own version-controlled repository with a defined export to the client at assessment time | J1172: decision record | K1172: CQB0195
A1173: Programme Manager | B1173: 7 | C1173: Before sprint 0 | D1173: Blocker | E1173: HARD | F1173: D09 | G1173: PM | H1173: By what date must Level 3 be attained, and is that date driven by a contract, a client programme milestone, or our own plan? | I1173: HARD BLOCKER - no default possible | J1173: signed document | K1173: CQB0184
A1174: Programme Manager | B1174: 8 | C1174: Before sprint 0 | D1174: Blocker | F1174: D14 | G1174: PM | H1174: Which team owns content-building, accessibility QA and manual-watch - because I keep finding those responsibilities assumed inside the sequencing engine? | I1174: sequencing only; content-building sits with the DCT, accessibility QA with the tagging module, manual-watch with the lineage service | J1174: decision record | K1174: CQC0123
A1175: Programme Manager | B1175: 9 | C1175: Before sprint 0 | D1175: Blocker | F1175: D14 | G1175: PRODM | H1175: There is a naming clash where more than one thing is called the PLE - which module is the customer-facing PLE, and are both controlling documents corrected? | I1175: the sequencing engine is the PLE; the signal producer is renamed, and both controlling documents are re-issued | J1175: decision record | K1175: CQC0124
A1176: Programme Manager | B1176: 10 | C1176: Before sprint 0 | D1176: Blocker | E1176: HARD | F1176: D17 | G1176: PRODM | H1176: Which two organisations are the first pair to federate, and has anyone from either of them agreed to this in writing yet? | I1176: HARD BLOCKER - no default possible | J1176: named person | K1176: CQB0166
A1177: Programme Manager | B1177: 11 | C1177: Before sprint 0 | D1177: Blocker | E1177: HARD | F1177: D19 | G1177: MXR | H1177: Which headset model is the fleet standard - I cannot pick a runtime, a controller input map or a build target until somebody names the device and the quantity we are buying? | I1177: HARD BLOCKER - no default possible | J1177: decision record | K1177: CQE0036
A1178: Programme Manager | B1178: 12 | C1178: Before sprint 0 | D1178: Blocker | F1178: D19 | G1178: MXR | H1178: Where do I get a headset to develop against, is it already enrolled in device management, and if I have to unenrol it to sideload builds will I be able to test the managed install path at all? | I1178: Two headsets per XR developer - one unmanaged for daily development and one enrolled in the same management configuration as the sites for install-path testing | J1178: named person | K1178: CQT0212
A1179: Programme Manager | B1179: 13 | C1179: Before sprint 0 | D1179: Blocker | F1179: D19 | G1179: MXR | H1179: Which headset family are we committing to, and what is the exit if it is discontinued or becomes unavailable in India - do titles run on a successor without rework, and who carries the cost if they do not? | I1179: Target OpenXR with all vendor-specific behaviour behind an abstraction, so a headset family change is a requalification and a retest rather than a rewrite of interactions | J1179: decision record | K1179: CQT0233
A1180: Programme Manager | B1180: 14 | C1180: Before sprint 0 | D1180: Blocker | E1180: HARD | F1180: D20 | G1180: PM | H1180: Which physical building is the reference site - I need a named address and a site owner, because until a room exists I cannot survey it, size the power or plan a delivery date? | I1180: HARD BLOCKER - no default possible | J1180: named person | K1180: CQE0067
A1181: Programme Manager | B1181: 15 | C1181: Before sprint 0 | D1181: Blocker | E1181: HARD | F1181: D20 | G1181: MXR | H1181: Which headset model and how many units is the lab fleet - I cannot specify charging, storage, hygiene consumables, spares or the network load without the device and the count? | I1181: HARD BLOCKER - no default possible | J1181: decision record | K1181: CQE0069
A1182: Programme Manager | B1182: 16 | C1182: Before sprint 0 | D1182: Blocker | E1182: HARD | F1182: D20 | G1182: PM | H1182: Is the reference lab funded as capital expenditure, and what is the ceiling - because the difference between a six-headset room and a thirty-headset lab is the entire design, not a variation? | I1182: HARD BLOCKER - no default possible | J1182: signed document | K1182: CQE0068
A1183: Programme Manager | B1183: 17 | C1183: Before sprint 0 | D1183: Blocker | F1183: D20 | G1183: PM | H1183: What is the customs and import lead time for the headsets and the rack hardware into India, and who is the importer of record - because that number sets the delivery date, not the build schedule? | I1183: Assume 10 to 14 weeks from purchase order to on-site for imported XR hardware including customs clearance, with a named customs broker engaged before the order is placed | J1183: number with units | K1183: CQE0071
A1184: Programme Manager | B1184: 18 | C1184: Before sprint 0 | D1184: Blocker | F1184: D22 | G1184: AIG | H1184: Which parts of the walkthrough engine are mine versus the XR title team - do I own the in-headset experience or only the scoring behind it? | I1184: the XR title team owns the in-headset experience; I own capture, scoring, evidence and the supervisor surfaces | J1184: decision record | K1184: CQC0164
A1185: Programme Manager | B1185: 19 | C1185: Before sprint 0 | D1185: Blocker | F1185: D23 | G1185: PM | H1185: What can I promise for slice A given the assignment source is unowned - a working engine with manually entered assignments, or nothing demonstrable until the source exists? | I1185: Slice A delivers the diff engine, the SME confirmation flow and the supervisor screen against manually entered assignments for one equipment family | J1185: decision record | K1185: CQD0168
A1186: Programme Manager | B1186: 20 | C1186: Before sprint 0 | D1186: Blocker | F1186: D25 | G1186: PM | H1186: What is the last calendar date I can capture the baseline at site one before rollout contaminates it, and who has the authority to hold the rollout if the baseline is not captured by then? | I1186: Baseline capture closes two weeks before the first trainee touches the platform at each site, and the programme manager holds the rollout until the baseline sign-off exists | J1186: decision record | K1186: CQF0039
A1187: Programme Manager | B1187: 21 | C1187: Before sprint 0 | D1187: Blocker | F1187: D25 | G1187: DA | H1187: What improvement are we actually claiming - is a specific percentage reduction in time-to-ready written into a contract or a proposal - because the target changes the sample size and the measurement duration I have to plan for? | I1187: Design to detect a 20 percent reduction in median time-to-ready with 80 percent power, and state the detectable effect explicitly in the plan | J1187: signed document | K1187: CQF0042
A1188: Programme Manager | B1188: 22 | C1188: Before sprint 0 | D1188: Blocker | F1188: D26 | G1188: PM | H1188: What does done look like for D26 - a working app, or a completed measurement of a real exercise with an accepted result - because those are different milestones months apart? | I1188: Done is one real exercise measured end to end with a result produced in the agreed format, not a functionally complete app | J1188: decision record | K1188: CQE0150
A1189: Programme Manager | B1189: 23 | C1189: Before sprint 0 | D1189: Blocker | F1189: D27 | G1189: ID | H1189: How many trainers, at how many sites, over how many months - I need three numbers before I can size a curriculum, a delivery calendar or an SME roster? | I1189: 40 trainers across 4 sites over 9 months in cohorts of 10, revised once the site rollout order is fixed | J1189: number with units | K1189: CQF0069
A1190: Programme Manager | B1190: 24 | C1190: Before sprint 0 | D1190: Blocker | F1190: D27 | G1190: ID | H1190: What is the trainer to embedded SME ratio and how many contact hours does each trainer get - give me numbers, because that is the difference between a workshop and a mentoring relationship? | I1190: One embedded SME per 10 trainers, 24 contact hours of workshop plus 8 hours of observed practice per trainer | J1190: number with units | K1190: CQF0076
A1191: Programme Manager | B1191: 25 | C1191: Before sprint 0 | D1191: Blocker | E1191: HARD | F1191: D28 | G1191: PRODM | H1191: Is Level 5 attainment contractually required or aspirational - because that determines whether we resource it as a committed deliverable or a stretch goal? | I1191: HARD BLOCKER - no default possible | J1191: signed document | K1191: CQB0237
A1192: Programme Manager | B1192: 26 | C1192: Before sprint 0 | D1192: Blocker | F1192: D28 | G1192: PM | H1192: Which artefacts constitute the Level 5 deliverable - a mapping dataset, a governance charter, an optimisation measurement plan, and an assessment report - and which of those exist in draft anywhere? | I1192: A governed mapping dataset, a competency governance charter, a measurement plan with baselines, and an independent assessment report | J1192: signed document | K1192: CQB0211
...

Sheet Assumption Register
A1: Assumption Register
A2: Every default the team will proceed on if no answer arrives, ranked by exposure. This is the register that keeps work moving — and the one to read before a steering meeting. HIGH = a blocker whose wrong default causes a rebuild, migration, breach or contractual consequence.
A4: Exposure | B4: ProductID | C4: Role | D4: The question we are proceeding without | E4: We are assuming | F4: Cost if this assumption is wrong | G4: Who must confirm | H4: Needed by | I4: CQID | J4: Confirmed? | K4: Date
A5: HIGH | B5: D01 | C5: AI | D5: Which document set is the learner chatbot allowed to answer from on day one - only manuals approved in the M25 lineage service, or also DCT-authored lessons and course pages? | E5: approved technical manuals only; DCT lessons excluded until a separate corpus decision is recorded | F5: widening the corpus after launch is a full re-index plus a fresh ACL review, about 2 sprints | G5: Product Owner | H5: Before first code | I5: CQC0001
A6: HIGH | B6: D01 | C6: DE | D6: What are the mandatory fields on every chunk - I have doc ID, revision, effective date and supersedes - and is there anything else retrieval or the UI needs, like page anchor or classification? | E6: doc ID, revision, effective date, supersedes, page anchor, section path, tenant ID and classification marking on every chunk | F6: adding a mandatory field after ingest is a full re-embed and re-index of the manual corpus, days of GPU time we have not budgeted | G6: Data Owner | H6: Before first code | I6: CQC0015
A7: HIGH | B7: D01 | C7: UXD | D7: What does one citation look like inside an answer - an inline numbered marker, a footnote block under the answer, or a side panel - and does it show manual title, revision and page or just the title? | E7: inline numbered markers that expand to a footnote card showing manual title, revision ID, effective date and page anchor | F7: changing citation shape after build means reworking the answer contract and every screenshot in the accreditation pack | G7: Product Owner | H7: Before first code | I7: CQC0004
A8: HIGH | B8: D02 | C8: BE | D8: Which service owns an instructor-uploaded PDF once it is submitted for test-bank generation - the quiz service M8, the shared document store, or the M27 AI service? | E8: the shared document store owns the file; M8 holds only a reference and M27 reads by reference | F8: if the quiz service owns bytes we duplicate storage, retention and virus scanning, and the migration out is a data move | G8: Solution Architect | H8: Before first code | I8: CQC0035
A9: HIGH | B9: D02 | C9: FE | D9: Where does the grader queue actually live - inside the LMS via an LTI launch, in our own web app, or both - because that changes the whole navigation model? | E9: our own web app with an LTI deep link from the LMS into a specific queue, single sign-on via the platform identity service | F9: building LMS-native first and then extracting a standalone app is a full rebuild of the shell and the auth path | G9: Product Owner | H9: Before first code | I9: CQC0065
A10: HIGH | B10: D03 | C10: SEC | D10: If no baseline is named by the end of sprint 0, do you accept us proceeding on ISO/IEC 27001:2022 Annex A mapped to CIS Controls v8 as the working baseline, with a documented re-map risk logged against the programme? | E10: Proceed on ISO/IEC 27001:2022 Annex A mapped to CIS v8, evidence tagged with a neutral control ID so a later re-map is a lookup table rather than a rewrite | F10: If the real baseline turns out to be a defence catalogue with enclave-specific controls we have no evidence for, we lose the collection period and restart with a shorter runway | G10: Programme Manager | H10: Before first code | I10: CQF0003
A11: HIGH | B11: D03 | C11: AIG | D11: Is there a classification or sensitivity limit on what content may be put into the retrieval index at all - because if some manuals cannot be ingested, that is a filter in my ingest pipeline and I have not been given a list? | E11: Only content explicitly marked releasable at the deployment's classification may be ingested, with the marking read from the content management system and enforced in the pipeline, defaulting to reject | F11: A restricted document indexed and quoted back to an unauthorised learner is a security incident requiring index destruction and a full investigation | G11: Security/Accreditation | H11: Before first code | I11: CQT0148
A12: HIGH | B12: D03 | C12: AIG | D12: If an AI answer contributes to an incident on live equipment, who is liable - EdVidura, the client, the manual's publisher - and does our contract already say, because that answer should be shaping how conservative every guardrail is? | E12: The platform is explicitly advisory - approved manuals remain the authority, every safety-relevant answer carries that statement, and the contract records that operational decisions remain the client's | F12: An unallocated liability surfaces only after an incident, at which point the contract wording rather than the engineering decides the outcome | G12: Legal & Compliance | H12: Before sprint 0 | I12: CQT0189
A13: HIGH | B13: D04 | C13: PRODM | D13: Who holds block authority - can a reviewer stop a lesson from publishing, or is the review advisory with the author free to proceed? | E13: A reviewer may block only on safety, factual accuracy or accessibility defects; everything else is advisory and recorded but does not stop publish | F13: Full block authority with no staffing means content stops moving; purely advisory means the protocol changes nothing and the assurance claim is hollow | G13: Product Owner | H13: Before first release | I13: CQD0172
A14: HIGH | B14: D05 | C14: SEC | D14: Does the evidence package contain learner data - audit query outputs, sample statements - and if so what is the redaction rule before it leaves our environment? | E14: All evidence uses synthetic or pseudonymised subjects; no real learner identifier leaves the environment in an evidence artefact. | F14: A privacy breach committed in the act of proving our compliance maturity. | G14: Legal & Compliance | H14: Before first release | I14: CQA0131
A15: HIGH | B15: D05 | C15: SDET | D15: What counts as a contract test for L2 - consumer-driven contracts in CI, or is an OpenAPI schema check enough - because the effort differs by an order of magnitude. | E15: Consumer-driven contract tests in CI for every claimed service, with a schema check alone treated as insufficient. | F15: Building a lightweight check that the assessor rejects, then retrofitting real contract tests across every service. | G15: Solution Architect | H15: Before first integration | I15: CQA0123
A16: HIGH | B16: D06 | C16: BE | D16: For the ELRR, is the row I persist a full copy of the xAPI statement or a derived experience-summary record that points back to a statement ID in the LRS - which of those two is the primary table I create in sprint 1? | E16: Store a derived experience-summary row keyed to the LRS statement ID; do not copy raw statements into ELRR | F16: Full re-ingest of every record plus a table rewrite once volumes are real - about 3 weeks of engineering and a frozen reporting window | G16: Solution Architect | H16: Before first code | I16: CQB0001
... A2544: LOW | B2544: XCUT | C2544: SUP | D2544: Is there one artefact that documents the whole journey with an owner per hop, and who keeps it current - because I am inheriting support for something described in four separate architecture decks. | E2544: One maintained journey map per major journey listing hops, owning squads, SLOs and runbook links, updated as part of every interface change | F2544: Without it, support diagnoses from tribal knowledge and every hop change silently invalidates the mental model support is operating on | G2544: Programme Manager | H2544: Before first release | I2544: CQH0076

Sheet Clarification Bank
A1: CQID | B1: ProductID | C1: Product | D1: Role | E1: RoleName | F1: Level | G1: LifecycleStage | H1: BlockingClass | I1: NeededBy | J1: Question | K1: WhatIAmBuilding | L1: BlockedWork | M1: ProposedDefault | N1: CostIfDefaultWrong | O1: AddressedTo | P1: AnswerForm | Q1: ParentCQID | R1: FollowUps | S1: Status | T1: AnsweredBy | U1: AnswerDate | V1: DecisionRecord
A2: CQC0001 | B2: D01 | C2: AI SME Chatbot - Learner-Facing | D2: AI | E2: AI/ML Engineer | F2: L1 Junior | G2: Understand | H2: Blocker | I2: Before first code | J2: Which document set is the learner chatbot allowed to answer from on day one - only manuals approved in the M25 lineage service, or also DCT-authored lessons and course pages? | K2: the retrieval corpus definition and the ingest allow-list for M15 | L2: I cannot configure the ingest allow-list or build the first index, and corpus scope decides my chunking rules | M2: approved technical manuals only; DCT lessons excluded until a separate corpus decision is recorded | N2: widening the corpus after launch is a full re-index plus a fresh ACL review, about 2 sprints | O2: Product Owner | P2: decision record | Q2: - | R2: Do authored lessons ever enter this corpus? / Who approves an addition? / One corpus per tenant or one shared? | S2: Open
A3: CQT0146 | B3: D01 | C3: AI SME Chatbot - Learner-Facing | D3: AIG | E3: AI Generalist | F3: L1 Junior | G3: Understand | H3: Blocker | I3: Before first code | J3: Who is the named owner of the guardrail policy - the person I go to when a case is not covered - because right now the answer to a novel case is whatever the engineer on the ticket decides? | K3: my escalation route for guardrail questions | L3: consistent guardrail behaviour, and whether decisions get recorded anywhere reusable | M3: A named guardrail policy owner in the product team, with a decision log where each novel case and its ruling is recorded and becomes an evaluation case | N3: Guardrail decisions made inconsistently and invisibly by whoever picks up the ticket, with no way to explain the system's behaviour to a client | O3: Programme Manager | P3: named person | Q3: - | R3: Who is it? / Where is the decision log? / What is the turnaround on a novel case? | S3: Open
A4: CQT0183 | B4: D01 | C4: AI SME Chatbot - Learner-Facing | D4: AIG | E4: AI Generalist | F4: L4 Architect | G4: Understand | H4: Blocker | I4: Before first code | J4: Do we run one assistant serving learners and authors with role-based prompts and corpus filters, or three separate deployments - and what do we permanently give up in each case: shared improvement in the first, or three times the evaluation and governance load in the second? | K4: the assistant topology decision that fixes our governance model | L4: the deployment architecture, the corpus governance model and the evaluation and red-team effort per release | M4: Three separate deployments sharing the inference platform and the evaluation harness but not the corpus, prompts or guardrail configuration | N4: A shared assistant means a single configuration error crosses audiences; separate ones triple the governance load forever and diverge in quality | O4: Solution Architect | P4: decision record | Q4: CQT0142 | R4: Who funds three evaluation sets? / Can the harness genuinely be shared? / Does a fourth assistant arrive later? | S4: Open
A5: CQC0010 | B5: D01 | C5: AI SME Chatbot - Learner-Facing | D5: AI | E5: AI/ML Engineer | F5: L4 Architect | G5: Scope | H5: Blocker | I5: Before first code | J5: There are three chatbots on the programme - M15 learner-facing, M23 authoring support and the M27 assessment assistant. Which components do they share as one deployed service and which are duplicated per bot? | K5: the M15 service boundary and its dependency list | L5: I cannot decide whether to build retrieval as a library inside M15 or as a shared retrieval service the other two call | M5: share the E04 inference service and one embedding pipeline; keep retrieval, prompts, guardrails and corpora separate per bot | N5: building shared retrieval later means extracting a service from three codebases with three ACL models, 3 to 4 sprints | O5: Solution Architect | P5: decision record | Q5: - | R5: Do they share a vector store instance? / Do they share the eval harness? / Who owns the shared code? | S5: Open
A6: CQC0024 | B6: D01 | C6: AI SME Chatbot - Learner-Facing | D6: PRODM | E6: Product Manager | F6: L4 Architect | G6: Scope | H6: Blocker | I6: Before sprint 0 | J6: Is practice quiz generation part of the learner chatbot at all, or does every quiz item come from M8 and M27 - because I keep being asked for it in demos? | K6: the M15 feature boundary | L6: I cannot say no to demo requests, and if it is in scope I need an item model M15 does not have | M6: out of scope for M15; the chatbot may only link to existing M8 items, never generate them | N6: building a second item bank inside the chatbot creates ungoverned assessment items with no review gate, a compliance problem not a feature | O6: Product Owner | P6: decision record | Q6: - | R6: Can the chatbot at least select existing items? / Does that need M8 API? / Is the demo promise already made? | S6: Open
A7: CQU0127 | B7: D01 | C7: AI SME Chatbot - Learner-Facing | D7: ID | E7: Instructional Designer | F7: L1 Junior | G7: Scope | H7: Shaper | I7: Before first release | J7: Is the learner-facing assistant instructional content subject to the pedagogy gate, or is it a tool that sits outside instructional review entirely? | K7: the review scope boundary for conversational surfaces | L7: whether the assistant's prompts, refusals and guidance wording go through instructional review at all | M7: the assistant is in scope for instructional review of its system prompt, its guidance wording and its refusal messages, but individual generated answers are governed by the AI quality gate instead | N7: leaving the assistant outside instructional review means the most-used learning surface in the product has had no instructional design input at all | O7: Instructional Designer | P7: decision record | Q7: - | R7: Who reviews the system prompt / How often / What about refusal wording | S7: Open
A8: CQC0002 | B8: D01 | C8: AI SME Chatbot - Learner-Facing | D8: BE | E8: Back-End Developer | F8: L1 Junior | G8: Interfaces | H8: Blocker | I8: Before first code | J8: Do I call the shared inference service at E04 through the published OpenAI-compatible contract, or does M15 get its own direct model handle on the appliance? | K8: the chat orchestration service and its outbound client | L8: I cannot write the client, the retry policy or the priority-class header until the calling contract is fixed | M8: E04 published contract only, with priority class chat on every call and no direct model handle | N8: a direct handle bypasses admission control and gets ripped out when grading starts preempting, about 1 sprint | O8: Solution Architect | P8: link to existing spec | Q8: - | R8: Which priority class does chat use? / Is the contract versioned? / Who owns the client library? | S8: Open
A9: CQC0026 | B9: D01 | C9: AI SME Chatbot - Learner-Facing | D9: BE | E9: Back-End Developer | F9: L3 Senior | G9: Interfaces | H9: Blocker | I9: Before first code | J9: How long do I retain a learner conversation, and is the transcript readable by an instructor, by support, or by nobody? | K9: the conversation store and its access model | L9: I cannot design the store, the retention job or the access control on transcripts | M9: 90 day retention, learner and support readable with an audit record, instructor access denied by default | N9: instructor readable by default is a DPDP consent question we have not asked, and reversing it means purging live data | O9: Legal & Compliance | P9: decision record | Q9: - | R9: Is there a consent notice at first use? / Does an enclave differ? / Can a learner delete their own history? | S9: Open
A10: CQU0100 | B10: D01 | C10: AI SME Chatbot - Learner-Facing | D10: PRODM | E10: Product Manager | F10: L1 Junior | G10: Interfaces | H10: Shaper | I10: Before first integration | J10: Is the learner-facing chatbot sold as something learners reach directly, or only inside the customer's LMS - because that changes who we are contracting with about learner accounts? | K10: the distribution model for the learner assistant | L10: the identity model, the pricing unit and the data protection responsibilities we take on | M10: delivered through the customer LMS by default with the customer as controller of learner identity, and a direct-access mode only where a customer has no LMS and accepts the separate terms | N10: direct learner access makes us a processor of learner personal data with consent obligations we have not designed for, which is a data protection assessment we have not done | O10: Product Owner | P10: decision record | Q10: - | R10: Who holds learner identity / Who is the controller / Is direct access ever offered | S10: Open
A11: CQC0027 | B11: D01 | C11: AI SME Chatbot - Learner-Facing | D11: AI | E11: AI/ML Engineer | F11: L2 Mid | G11: Interfaces | H11: Shaper | I11: Before first integration | J11: If E04 activates a new embedding model version, does my index become invalid immediately and who tells me - or do I pin the embedding version per index and refuse mismatched queries? | K11: the index metadata and the embedding version guard | L11: I cannot make retrieval safe across a model change, and a silent mismatch degrades answers without any alarm | M11: pin the embedding model version in index metadata and hard-fail any query whose serving version differs, with an operator alert | N11: an unnoticed mismatch returns plausible but wrong chunks and nothing in the pipeline detects it | O11: Another squad | P11: decision record | Q11: - | R11: Who notifies consumers of a model change? / Is re-embedding scheduled or on demand? / How long does a full re-embed take? | S11: Open
A12: CQC0015 | B12: D01 | C12: AI SME Chatbot - Learner-Facing | D12: DE | E12: Data Engineer | F12: L2 Mid | G12: Data | H12: Blocker | I12: Before first code | J12: What are the mandatory fields on every chunk - I have doc ID, revision, effective date and supersedes - and is there anything else retrieval or the UI needs, like page anchor or classification? | K12: the chunk schema and the ingest writer | L12: I cannot freeze the chunk schema, and a later field addition means re-embedding the whole corpus | M12: doc ID, revision, effective date, supersedes, page anchor, section path, tenant ID and classification marking on every chunk | N12: adding a mandatory field after ingest is a full re-embed and re-index of the manual corpus, days of GPU time we have not budgeted | O12: Data Owner | P12: schema/sample file | Q12: - | R12: Is classification marking per chunk or per document? / Who owns the schema? / Does the UI need section path? | S12: Open
A13: CQC0016 | B13: D01 | C13: AI SME Chatbot - Learner-Facing | D13: AI | E13: AI/ML Engineer | F13: L2 Mid | G13: Data | H13: Blocker | I13: Before first code | J13: When a manual revision is withdrawn, how many minutes or hours may pass before its chunks stop being retrievable - what is the supersession SLA? | K13: the tombstone application path in the retrieval layer | L13: I cannot choose between blocking at query time on every request and waiting for a re-index, and the Scenario 4 drill has no pass criterion | M13: HARD BLOCKER - no default possible | N13: if the number is minutes I need a query-time tombstone check on every retrieval; if it is a day I do not - and the two designs do not convert into each other | O13: NOBODY OWNS THIS | P13: number with units | Q13: - | R13: Is the number different in an enclave on media updates? / Who declares a withdrawal? / Is zero leakage measured? | S13: Open
... A2704: CQH0076 | B2704: XCUT | C2704: Whole Product - End-to-End Journeys, Seams and Ownership | D2704: SUP | E2704: Support & Service Engineer | F2704: L4 Architect | G2704: Handover | H2704: Refiner | I2704: Before first release | J2704: Is there one artefact that documents the whole journey with an owner per hop, and who keeps it current - because I am inheriting support for something described in four separate architecture decks. | K2704: the journey map I hand to the support function at go-live | L2704: the support handover pack, the runbook set and the diagnostic training | M2704: One maintained journey map per major journey listing hops, owning squads, SLOs and runbook links, updated as part of every interface change | N2704: Without it, support diagnoses from tribal knowledge and every hop change silently invalidates the mental model support is operating on | O2704: Programme Manager | P2704: link to existing spec | Q2704: - | R2704: Does a journey map exist / Who maintains it / Is it in the definition of done for an interface change | S2704: Open

Sheet Coverage — Role x Level
A1: Coverage — Role x Level
A2: Loop 11 verification gate: every Role x Level cell must hold at least 20 clarifications.
A4: Code | B4: Role | C4: L1 Junior | D4: L2 Mid | E4: L3 Senior | F4: L4 Architect | G4: Total | H4: Floor 20
A5: FE | B5: Front-End Developer | C5: 33 | D5: 81 | E5: 21 | F5: 21 | G5: 156 | H5: OK
A6: BE | B6: Back-End Developer | C6: 33 | D6: 197 | E6: 79 | F6: 33 | G6: 342 | H6: OK
A7: DE | B7: Data Engineer | C7: 21 | D7: 74 | E7: 48 | F7: 21 | G7: 164 | H7: OK
A8: BI | B8: BI / Analytics Developer (Metabase) | C8: 21 | D8: 29 | E8: 21 | F8: 21 | G8: 92 | H8: OK
A9: DA | B9: Data Analyst | C9: 21 | D9: 32 | E9: 26 | F9: 21 | G9: 100 | H9: OK
A10: AI | B10: AI/ML Engineer | C10: 21 | D10: 44 | E10: 55 | F10: 26 | G10: 146 | H10: OK
A11: AIG | B11: AI Generalist | C11: 21 | D11: 21 | E11: 21 | F11: 21 | G11: 84 | H11: OK
A12: MXR | B12: Mobile & XR Developer | C12: 21 | D12: 29 | E12: 21 | F12: 21 | G12: 92 | H12: OK
A13: DEVOPS | B13: DevSecOps / Platform Engineer | C13: 21 | D13: 56 | E13: 70 | F13: 21 | G13: 168 | H13: OK
A14: SEC | B14: Security Engineer | C14: 21 | D14: 44 | E14: 83 | F14: 24 | G14: 172 | H14: OK
A15: QA | B15: QA / Test Engineer | C15: 21 | D15: 65 | E15: 27 | F15: 21 | G15: 134 | H15: OK
A16: SDET | B16: Test Architect / SDET | C16: 21 | D16: 30 | E16: 52 | F16: 21 | G16: 124 | H16: OK
... A21: UXD | B21: UI/UX Designer | C21: 31 | D21: 172 | E21: 91 | F21: 21 | G21: 315 | H21: OK

Sheet Coverage — by product
A1: Coverage — by product
A2: Floors: >=30 clarifications per product, >=5 UI/UX questions each, all 12 lifecycle stages represented.
A4: ProductID | B4: Product | C4: Questions | D4: Roles | E4: Levels | F4: Stages/12 | G4: UI/UX | H4: Blockers | I4: Hard blockers | J4: Unowned | K4: Floor 30
A5: D01 | B5: AI SME Chatbot — Learner-Facing | C5: 55 | D5: 14 | E5: 4 | F5: 12 | G5: 9 | H5: 23 | I5: 4 | J5: 4 | K5: OK
A6: D02 | B6: AI Assessment Tools & Test Banks + Auto Grader | C6: 45 | D6: 15 | E6: 4 | F6: 12 | G6: 7 | H6: 21 | I6: 4 | J6: 4 | K6: OK
A7: D03 | B7: Security Accreditation & Authorisation to Operate — Initiation | C7: 43 | D7: 12 | E7: 4 | F7: 12 | G7: 6 | H7: 16 | I7: 5 | J7: 4 | K7: OK
A8: D04 | B8: Pedagogy Design Review Protocol | C8: 33 | D8: 6 | E8: 4 | F8: 12 | G8: 5 | H8: 9 | I8: 1 | J8: 2 | K8: OK
A9: D05 | B9: TLA CMM Level 2 — Microservices | C9: 33 | D9: 11 | E9: 4 | F9: 12 | G9: 5 | H9: 11 | I9: 6 | J9: 7 | K9: OK
A10: D06 | B10: TLA Experience-Index (ELRR) | C10: 41 | D10: 15 | E10: 4 | F10: 12 | G10: 7 | H10: 12 | I10: 2 | J10: 1 | K10: OK
A11: D07 | B11: TLA Course Catalogue (ECC) | C11: 38 | D11: 15 | E11: 4 | F11: 12 | G11: 7 | H11: 12 | I11: 3 | J11: 1 | K11: OK
A12: D08 | B12: TLA Competency-Registry | C12: 41 | D12: 15 | E12: 4 | F12: 12 | G12: 6 | H12: 18 | I12: 5 | J12: 2 | K12: OK
A13: D09 | B13: TLA CMM Level 3 | C13: 33 | D13: 13 | E13: 4 | F13: 12 | G13: 5 | H13: 12 | I13: 4 | J13: 1 | K13: OK
A14: D10 | B14: PDFs & Technical Manuals Integration — Live TO Connection | C14: 33 | D14: 11 | E14: 4 | F14: 12 | G14: 5 | H14: 14 | I14: 3 | J14: 1 | K14: OK
A15: D11 | B15: DCT — Content Authoring & Lesson Planner | C15: 37 | D15: 12 | E15: 4 | F15: 12 | G15: 8 | H15: 14 | I15: 0 | J15: 0 | K15: OK
A16: D12 | B16: Interactive eBooks — Technical Manuals Digitization | C16: 46 | D16: 15 | E16: 4 | F16: 12 | G16: 7 | H16: 18 | I16: 1 | J16: 1 | K16: OK
... A46: XCUT | B46: Cross-cutting concern / Whole Product | C46: 1057 | D46: 17 | E46: 4 | F46: 12 | G46: 123 | H46: 453 | I46: 54 | J46: 57 | K46: OK

Sheet Lists
A1: Controlled vocabularies (named ranges)
A3: RoleList | B3: LevelList | C3: StageList | D3: BlockList | E3: NeedList | F3: AddrList | G3: StatusList
A4: FE | B4: L1 Junior | C4: Understand | D4: Blocker | E4: Before sprint 0 | F4: Another squad | G4: Open
A5: BE | B5: L2 Mid | C5: Scope | D5: Shaper | E5: Before first code | F5: Client SME | G5: Asked
A6: DE | B6: L3 Senior | C6: Interfaces | D6: Refiner | E6: Before first integration | F6: Data Owner | G6: Answered
A7: BI | B7: L4 Architect | C7: Data | E7: Before first release | F7: Instructional Designer | G7: Assumed & proceeding
A8: DA | C8: Rules | E8: Before scale | F8: Legal & Compliance | G8: Escalated
A9: AI | C9: UI/UX | F9: NOBODY OWNS THIS
A10: AIG | C10: Failure | F10: Product Owner
A11: MXR | C11: Non-functionals | F11: Programme Manager
A12: DEVOPS | C12: BuildEnv | F12: Security/Accreditation
A13: SEC | C13: Test&Acceptance | F13: Solution Architect
A14: QA | C14: Deploy&Operate | F14: Vendor
A15: SDET | C15: Handover
A16: PM
A17: PRODM
A18: ID
A19: SUP
A20: UXD

Sheet How to use
A1: How to use the clarification bank
A3: WHAT THIS IS
A4: The premise | B4: Everyone on this team can build anything on the list. Nobody has been told what the products are, how they behave, what they connect to, or what 'done' means. These are the questions the team asks the programme — not questions asked of the team.
A5: Why every row has a default | B5: A team that stops working while it waits for answers misses the release. Every question proposes what we will do if nobody answers, and what it costs if that default is wrong. Silence therefore produces a logged assumption, not a stalled sprint.
A6: Hard blockers | B6: Some things cannot be defaulted — you cannot invent a customer's LMS, a competency framework, a GPU budget or an accrediting authority. Those rows are marked HARD BLOCKER and appear on the Critical Answer Path.
A8: THE FIVE WAYS TO USE IT
A9: 1. Kickoff a product | B9: Open **Product Kickoff Packs**, filter to one ProductID. That is the squad's kickoff agenda, grouped by lifecycle stage with blockers first. Walk it in the room; anything you cannot answer becomes an assumption or an escalation before a line of code is written.
A10: 2. Brief a person | B10: Open **Role Packs**, filter to the role. Work the 'Before sprint 0' block, then 'Before first code'. This is what that person needs before they can be productive.
A11: 3. Run the decisions | B11: Open **Decision Agenda**, filter to one answerer. Run the meeting as a review of proposed defaults: for each row they say CONFIRM or give the correction. This turns hundreds of questions into a handful of short meetings.
A12: 4. Manage the risk | B12: Open **Assumption Register**, sorted by exposure. The HIGH rows are the assumptions that cause a rebuild, migration, breach or contract problem if wrong. Read this before any steering meeting.
A13: 5. Escalate what nobody owns | B13: Open **Escalation — nobody owns this**. These are not meetings; they are governance findings. Each needs a name attached before it can even be scheduled.
A15: READING A ROW
A16: Blocking class | B16: Blocker = cannot start. Shaper = can start, will rework if the answer differs. Refiner = safe to defer.
A17: Needed by | B17: Before sprint 0 / first code / first integration / first release / scale. Sort by this to see what is actually urgent.
A18: Level | B18: The seniority of the person asking, which changes what they need: L1 what and where · L2 rules and edge cases · L3 commitments and failure · L4 boundaries and trade-offs.
A19: Answer must arrive as | B19: A decision record, a schema or sample file, a number with units, a named person, a signed document, or a link to an existing spec. Verbal reassurance is not an answer — it will be re-asked next sprint.
A21: KEEPING IT ALIVE
A22: When you get an answer | B22: Fill AnsweredBy, AnswerDate and DecisionRecord, and set Status to Answered. If you proceed without one, set Status to 'Assumed & proceeding' — the Assumption Register then reflects reality.
A23: When a new product or squad starts | B23: Add rows; never renumber a CQID. They are referenced by the packs, the agenda and the register.
A24: When an answer creates a new question | B24: Add it with the original CQID as its parent. That is how the second wave gets captured instead of being rediscovered in integration.
